[
  {
    "fecha": "2024-04-14T19:00Z",
    "ht": "Athletico Paranaense",
    "at": "Cuiabá",
    "hg": 4,
    "ag": 0,
    "hst": 9,
    "ast": 0,
    "hs": 20,
    "as": 1,
    "hc": 7,
    "ac": 0,
    "evt_id": "699350",
    "temp": 2024
  },
  {
    "fecha": "2024-04-14T19:00Z",
    "ht": "Atlético Goianiense",
    "at": "Flamengo",
    "hg": 1,
    "ag": 2,
    "hst": 4,
    "ast": 2,
    "hs": 11,
    "as": 15,
    "hc": 4,
    "ac": 4,
    "evt_id": "699351",
    "temp": 2024
  },
  {
    "fecha": "2024-04-14T19:00Z",
    "ht": "Corinthians",
    "at": "Atlético-MG",
    "hg": 0,
    "ag": 0,
    "hst": 2,
    "ast": 3,
    "hs": 14,
    "as": 8,
    "hc": 3,
    "ac": 3,
    "evt_id": "699352",
    "temp": 2024
  },
  {
    "fecha": "2024-04-13T21:30Z",
    "ht": "Criciúma",
    "at": "Juventude",
    "hg": 1,
    "ag": 1,
    "hst": 3,
    "ast": 4,
    "hs": 10,
    "as": 15,
    "hc": 0,
    "ac": 4,
    "evt_id": "699353",
    "temp": 2024
  },
  {
    "fecha": "2024-04-14T20:00Z",
    "ht": "Cruzeiro",
    "at": "Botafogo",
    "hg": 3,
    "ag": 2,
    "hst": 5,
    "ast": 3,
    "hs": 15,
    "as": 6,
    "hc": 6,
    "ac": 3,
    "evt_id": "699354",
    "temp": 2024
  },
  {
    "fecha": "2024-04-14T00:00Z",
    "ht": "Fluminense",
    "at": "Red Bull Bragantino",
    "hg": 2,
    "ag": 2,
    "hst": 11,
    "ast": 8,
    "hs": 26,
    "as": 16,
    "hc": 13,
    "ac": 6,
    "evt_id": "699355",
    "temp": 2024
  },
  {
    "fecha": "2024-04-13T21:30Z",
    "ht": "Internacional",
    "at": "Bahia",
    "hg": 2,
    "ag": 1,
    "hst": 9,
    "ast": 4,
    "hs": 17,
    "as": 9,
    "hc": 6,
    "ac": 3,
    "evt_id": "699356",
    "temp": 2024
  },
  {
    "fecha": "2024-04-14T00:00Z",
    "ht": "São Paulo",
    "at": "Fortaleza",
    "hg": 1,
    "ag": 2,
    "hst": 5,
    "ast": 2,
    "hs": 14,
    "as": 6,
    "hc": 11,
    "ac": 4,
    "evt_id": "699357",
    "temp": 2024
  },
  {
    "fecha": "2024-04-14T19:00Z",
    "ht": "Vasco da Gama",
    "at": "Grêmio",
    "hg": 2,
    "ag": 1,
    "hst": 3,
    "ast": 2,
    "hs": 15,
    "as": 9,
    "hc": 3,
    "ac": 5,
    "evt_id": "699358",
    "temp": 2024
  },
  {
    "fecha": "2024-04-14T21:30Z",
    "ht": "Vitória",
    "at": "Palmeiras",
    "hg": 0,
    "ag": 1,
    "hst": 5,
    "ast": 4,
    "hs": 13,
    "as": 15,
    "hc": 3,
    "ac": 10,
    "evt_id": "699359",
    "temp": 2024
  },
  {
    "fecha": "2024-04-17T23:00Z",
    "ht": "Atlético-MG",
    "at": "Criciúma",
    "hg": 1,
    "ag": 1,
    "hst": 6,
    "ast": 1,
    "hs": 22,
    "as": 5,
    "hc": 9,
    "ac": 2,
    "evt_id": "699360",
    "temp": 2024
  },
  {
    "fecha": "2024-04-17T00:30Z",
    "ht": "Bahia",
    "at": "Fluminense",
    "hg": 2,
    "ag": 1,
    "hst": 5,
    "ast": 3,
    "hs": 12,
    "as": 9,
    "hc": 4,
    "ac": 3,
    "evt_id": "699361",
    "temp": 2024
  },
  {
    "fecha": "2024-04-19T00:30Z",
    "ht": "Botafogo",
    "at": "Atlético Goianiense",
    "hg": 1,
    "ag": 0,
    "hst": 4,
    "ast": 3,
    "hs": 13,
    "as": 12,
    "hc": 8,
    "ac": 8,
    "evt_id": "699362",
    "temp": 2024
  },
  {
    "fecha": "2024-06-05T23:00Z",
    "ht": "Cuiabá",
    "at": "Vitória",
    "hg": 0,
    "ag": 0,
    "hst": 0,
    "ast": 4,
    "hs": 11,
    "as": 13,
    "hc": 4,
    "ac": 3,
    "evt_id": "699363",
    "temp": 2024
  },
  {
    "fecha": "2024-04-18T00:30Z",
    "ht": "Flamengo",
    "at": "São Paulo",
    "hg": 2,
    "ag": 1,
    "hst": 0,
    "ast": 0,
    "hs": 0,
    "as": 0,
    "hc": 0,
    "ac": 0,
    "evt_id": "699364",
    "temp": 2024
  },
  {
    "fecha": "2024-04-17T23:00Z",
    "ht": "Fortaleza",
    "at": "Cruzeiro",
    "hg": 1,
    "ag": 1,
    "hst": 3,
    "ast": 6,
    "hs": 14,
    "as": 14,
    "hc": 7,
    "ac": 5,
    "evt_id": "699365",
    "temp": 2024
  },
  {
    "fecha": "2024-04-17T22:00Z",
    "ht": "Grêmio",
    "at": "Athletico Paranaense",
    "hg": 2,
    "ag": 0,
    "hst": 7,
    "ast": 0,
    "hs": 14,
    "as": 4,
    "hc": 9,
    "ac": 2,
    "evt_id": "699366",
    "temp": 2024
  },
  {
    "fecha": "2024-04-17T23:00Z",
    "ht": "Juventude",
    "at": "Corinthians",
    "hg": 2,
    "ag": 0,
    "hst": 8,
    "ast": 2,
    "hs": 16,
    "as": 17,
    "hc": 6,
    "ac": 7,
    "evt_id": "699367",
    "temp": 2024
  },
  {
    "fecha": "2024-04-17T23:00Z",
    "ht": "Palmeiras",
    "at": "Internacional",
    "hg": 0,
    "ag": 1,
    "hst": 3,
    "ast": 2,
    "hs": 18,
    "as": 5,
    "hc": 6,
    "ac": 2,
    "evt_id": "699368",
    "temp": 2024
  },
  {
    "fecha": "2024-04-17T22:00Z",
    "ht": "Red Bull Bragantino",
    "at": "Vasco da Gama",
    "hg": 2,
    "ag": 1,
    "hst": 5,
    "ast": 3,
    "hs": 17,
    "as": 13,
    "hc": 4,
    "ac": 6,
    "evt_id": "699369",
    "temp": 2024
  },
  {
    "fecha": "2024-04-21T19:00Z",
    "ht": "Athletico Paranaense",
    "at": "Internacional",
    "hg": 1,
    "ag": 0,
    "hst": 3,
    "ast": 4,
    "hs": 13,
    "as": 20,
    "hc": 5,
    "ac": 3,
    "evt_id": "699370",
    "temp": 2024
  },
  {
    "fecha": "2024-04-21T21:30Z",
    "ht": "Atlético Goianiense",
    "at": "São Paulo",
    "hg": 0,
    "ag": 3,
    "hst": 1,
    "ast": 7,
    "hs": 9,
    "as": 19,
    "hc": 4,
    "ac": 3,
    "evt_id": "699371",
    "temp": 2024
  },
  {
    "fecha": "2024-04-21T00:00Z",
    "ht": "Atlético-MG",
    "at": "Cruzeiro",
    "hg": 3,
    "ag": 0,
    "hst": 4,
    "ast": 3,
    "hs": 9,
    "as": 10,
    "hc": 4,
    "ac": 4,
    "evt_id": "699372",
    "temp": 2024
  },
  {
    "fecha": "2024-04-21T21:30Z",
    "ht": "Botafogo",
    "at": "Juventude",
    "hg": 5,
    "ag": 1,
    "hst": 6,
    "ast": 1,
    "hs": 13,
    "as": 12,
    "hc": 5,
    "ac": 4,
    "evt_id": "699373",
    "temp": 2024
  },
  {
    "fecha": "2024-07-24T22:00Z",
    "ht": "Criciúma",
    "at": "Fortaleza",
    "hg": 1,
    "ag": 1,
    "hst": 7,
    "ast": 4,
    "hs": 13,
    "as": 15,
    "hc": 4,
    "ac": 5,
    "evt_id": "699374",
    "temp": 2024
  },
  {
    "fecha": "2024-04-20T19:00Z",
    "ht": "Fluminense",
    "at": "Vasco da Gama",
    "hg": 2,
    "ag": 1,
    "hst": 8,
    "ast": 5,
    "hs": 11,
    "as": 21,
    "hc": 2,
    "ac": 7,
    "evt_id": "699375",
    "temp": 2024
  },
  {
    "fecha": "2024-04-20T21:30Z",
    "ht": "Grêmio",
    "at": "Cuiabá",
    "hg": 1,
    "ag": 0,
    "hst": 4,
    "ast": 3,
    "hs": 7,
    "as": 14,
    "hc": 3,
    "ac": 4,
    "evt_id": "699376",
    "temp": 2024
  },
  {
    "fecha": "2024-04-21T19:00Z",
    "ht": "Palmeiras",
    "at": "Flamengo",
    "hg": 0,
    "ag": 0,
    "hst": 1,
    "ast": 3,
    "hs": 12,
    "as": 8,
    "hc": 6,
    "ac": 5,
    "evt_id": "699377",
    "temp": 2024
  },
  {
    "fecha": "2024-04-20T21:30Z",
    "ht": "Red Bull Bragantino",
    "at": "Corinthians",
    "hg": 1,
    "ag": 0,
    "hst": 3,
    "ast": 4,
    "hs": 10,
    "as": 15,
    "hc": 3,
    "ac": 4,
    "evt_id": "699378",
    "temp": 2024
  },
  {
    "fecha": "2024-04-21T19:00Z",
    "ht": "Vitória",
    "at": "Bahia",
    "hg": 2,
    "ag": 2,
    "hst": 8,
    "ast": 7,
    "hs": 13,
    "as": 20,
    "hc": 2,
    "ac": 7,
    "evt_id": "699379",
    "temp": 2024
  },
  {
    "fecha": "2024-04-28T00:00Z",
    "ht": "Bahia",
    "at": "Grêmio",
    "hg": 1,
    "ag": 0,
    "hst": 4,
    "ast": 2,
    "hs": 14,
    "as": 3,
    "hc": 4,
    "ac": 0,
    "evt_id": "699380",
    "temp": 2024
  },
  {
    "fecha": "2024-04-28T19:00Z",
    "ht": "Corinthians",
    "at": "Fluminense",
    "hg": 3,
    "ag": 0,
    "hst": 7,
    "ast": 2,
    "hs": 17,
    "as": 13,
    "hc": 6,
    "ac": 8,
    "evt_id": "699381",
    "temp": 2024
  },
  {
    "fecha": "2024-04-28T19:00Z",
    "ht": "Cruzeiro",
    "at": "Vitória",
    "hg": 3,
    "ag": 1,
    "hst": 6,
    "ast": 3,
    "hs": 15,
    "as": 8,
    "hc": 10,
    "ac": 4,
    "evt_id": "699382",
    "temp": 2024
  },
  {
    "fecha": "2024-04-27T21:30Z",
    "ht": "Cuiabá",
    "at": "Atlético-MG",
    "hg": 0,
    "ag": 3,
    "hst": 1,
    "ast": 5,
    "hs": 4,
    "as": 12,
    "hc": 3,
    "ac": 10,
    "evt_id": "699383",
    "temp": 2024
  },
  {
    "fecha": "2024-04-28T21:30Z",
    "ht": "Fortaleza",
    "at": "Red Bull Bragantino",
    "hg": 1,
    "ag": 1,
    "hst": 5,
    "ast": 4,
    "hs": 22,
    "as": 10,
    "hc": 12,
    "ac": 6,
    "evt_id": "699384",
    "temp": 2024
  },
  {
    "fecha": "2024-04-27T19:00Z",
    "ht": "Vasco da Gama",
    "at": "Criciúma",
    "hg": 0,
    "ag": 4,
    "hst": 5,
    "ast": 10,
    "hs": 21,
    "as": 17,
    "hc": 5,
    "ac": 4,
    "evt_id": "699385",
    "temp": 2024
  },
  {
    "fecha": "2024-04-28T23:00Z",
    "ht": "Internacional",
    "at": "Atlético Goianiense",
    "hg": 1,
    "ag": 1,
    "hst": 5,
    "ast": 2,
    "hs": 22,
    "as": 4,
    "hc": 13,
    "ac": 0,
    "evt_id": "699386",
    "temp": 2024
  },
  {
    "fecha": "2024-04-28T21:30Z",
    "ht": "Juventude",
    "at": "Athletico Paranaense",
    "hg": 1,
    "ag": 1,
    "hst": 5,
    "ast": 6,
    "hs": 15,
    "as": 15,
    "hc": 4,
    "ac": 6,
    "evt_id": "699387",
    "temp": 2024
  },
  {
    "fecha": "2024-04-29T23:00Z",
    "ht": "São Paulo",
    "at": "Palmeiras",
    "hg": 0,
    "ag": 0,
    "hst": 1,
    "ast": 3,
    "hs": 16,
    "as": 9,
    "hc": 6,
    "ac": 4,
    "evt_id": "699388",
    "temp": 2024
  },
  {
    "fecha": "2024-04-28T14:00Z",
    "ht": "Flamengo",
    "at": "Botafogo",
    "hg": 0,
    "ag": 2,
    "hst": 0,
    "ast": 3,
    "hs": 15,
    "as": 9,
    "hc": 8,
    "ac": 3,
    "evt_id": "699389",
    "temp": 2024
  },
  {
    "fecha": "2024-05-05T19:00Z",
    "ht": "Athletico Paranaense",
    "at": "Vasco da Gama",
    "hg": 1,
    "ag": 0,
    "hst": 7,
    "ast": 1,
    "hs": 26,
    "as": 7,
    "hc": 7,
    "ac": 5,
    "evt_id": "699390",
    "temp": 2024
  },
  {
    "fecha": "2024-05-05T21:30Z",
    "ht": "Botafogo",
    "at": "Bahia",
    "hg": 1,
    "ag": 2,
    "hst": 5,
    "ast": 4,
    "hs": 16,
    "as": 10,
    "hc": 5,
    "ac": 1,
    "evt_id": "699391",
    "temp": 2024
  },
  {
    "fecha": "2024-05-05T00:00Z",
    "ht": "Corinthians",
    "at": "Fortaleza",
    "hg": 0,
    "ag": 0,
    "hst": 9,
    "ast": 2,
    "hs": 18,
    "as": 12,
    "hc": 9,
    "ac": 5,
    "evt_id": "699392",
    "temp": 2024
  },
  {
    "fecha": "2024-08-28T22:30Z",
    "ht": "Cruzeiro",
    "at": "Internacional",
    "hg": 0,
    "ag": 0,
    "hst": 4,
    "ast": 0,
    "hs": 19,
    "as": 1,
    "hc": 10,
    "ac": 3,
    "evt_id": "699393",
    "temp": 2024
  },
  {
    "fecha": "2024-05-05T21:30Z",
    "ht": "Cuiabá",
    "at": "Palmeiras",
    "hg": 0,
    "ag": 2,
    "hst": 1,
    "ast": 6,
    "hs": 9,
    "as": 15,
    "hc": 6,
    "ac": 6,
    "evt_id": "699394",
    "temp": 2024
  },
  {
    "fecha": "2024-05-04T19:00Z",
    "ht": "Fluminense",
    "at": "Atlético-MG",
    "hg": 2,
    "ag": 2,
    "hst": 5,
    "ast": 7,
    "hs": 11,
    "as": 19,
    "hc": 4,
    "ac": 11,
    "evt_id": "699395",
    "temp": 2024
  },
  {
    "fecha": "2024-09-25T22:00Z",
    "ht": "Grêmio",
    "at": "Criciúma",
    "hg": 1,
    "ag": 2,
    "hst": 3,
    "ast": 4,
    "hs": 15,
    "as": 11,
    "hc": 6,
    "ac": 3,
    "evt_id": "699396",
    "temp": 2024
  },
  {
    "fecha": "2024-06-05T22:00Z",
    "ht": "Juventude",
    "at": "Atlético Goianiense",
    "hg": 1,
    "ag": 0,
    "hst": 2,
    "ast": 5,
    "hs": 8,
    "as": 22,
    "hc": 4,
    "ac": 7,
    "evt_id": "699397",
    "temp": 2024
  },
  {
    "fecha": "2024-05-04T21:30Z",
    "ht": "Red Bull Bragantino",
    "at": "Flamengo",
    "hg": 1,
    "ag": 1,
    "hst": 3,
    "ast": 6,
    "hs": 18,
    "as": 19,
    "hc": 8,
    "ac": 4,
    "evt_id": "699398",
    "temp": 2024
  },
  {
    "fecha": "2024-05-05T19:00Z",
    "ht": "Vitória",
    "at": "São Paulo",
    "hg": 1,
    "ag": 3,
    "hst": 2,
    "ast": 8,
    "hs": 6,
    "as": 20,
    "hc": 3,
    "ac": 8,
    "evt_id": "699399",
    "temp": 2024
  },
  {
    "fecha": "2024-05-12T19:00Z",
    "ht": "Atlético Goianiense",
    "at": "Cruzeiro",
    "hg": 0,
    "ag": 1,
    "hst": 5,
    "ast": 5,
    "hs": 17,
    "as": 12,
    "hc": 5,
    "ac": 6,
    "evt_id": "699400",
    "temp": 2024
  },
  {
    "fecha": "2024-10-09T22:30Z",
    "ht": "Atlético-MG",
    "at": "Grêmio",
    "hg": 2,
    "ag": 1,
    "hst": 5,
    "ast": 4,
    "hs": 14,
    "as": 14,
    "hc": 4,
    "ac": 10,
    "evt_id": "699401",
    "temp": 2024
  },
  {
    "fecha": "2024-05-12T21:30Z",
    "ht": "Bahia",
    "at": "Red Bull Bragantino",
    "hg": 1,
    "ag": 0,
    "hst": 3,
    "ast": 5,
    "hs": 8,
    "as": 15,
    "hc": 6,
    "ac": 7,
    "evt_id": "699402",
    "temp": 2024
  },
  {
    "fecha": "2024-06-09T19:00Z",
    "ht": "Criciúma",
    "at": "Cuiabá",
    "hg": 2,
    "ag": 5,
    "hst": 9,
    "ast": 7,
    "hs": 23,
    "as": 13,
    "hc": 6,
    "ac": 2,
    "evt_id": "699403",
    "temp": 2024
  },
  {
    "fecha": "2024-05-11T19:00Z",
    "ht": "Flamengo",
    "at": "Corinthians",
    "hg": 2,
    "ag": 0,
    "hst": 9,
    "ast": 3,
    "hs": 18,
    "as": 13,
    "hc": 13,
    "ac": 6,
    "evt_id": "699404",
    "temp": 2024
  },
  {
    "fecha": "2024-05-12T19:00Z",
    "ht": "Fortaleza",
    "at": "Botafogo",
    "hg": 1,
    "ag": 1,
    "hst": 4,
    "ast": 5,
    "hs": 10,
    "as": 11,
    "hc": 6,
    "ac": 6,
    "evt_id": "699405",
    "temp": 2024
  },
  {
    "fecha": "2024-08-14T22:30Z",
    "ht": "Internacional",
    "at": "Juventude",
    "hg": 2,
    "ag": 1,
    "hst": 10,
    "ast": 3,
    "hs": 21,
    "as": 8,
    "hc": 8,
    "ac": 1,
    "evt_id": "699406",
    "temp": 2024
  },
  {
    "fecha": "2024-05-12T19:00Z",
    "ht": "Palmeiras",
    "at": "Athletico Paranaense",
    "hg": 0,
    "ag": 2,
    "hst": 5,
    "ast": 6,
    "hs": 23,
    "as": 11,
    "hc": 9,
    "ac": 6,
    "evt_id": "699407",
    "temp": 2024
  },
  {
    "fecha": "2024-05-13T23:00Z",
    "ht": "São Paulo",
    "at": "Fluminense",
    "hg": 2,
    "ag": 1,
    "hst": 8,
    "ast": 2,
    "hs": 15,
    "as": 7,
    "hc": 7,
    "ac": 4,
    "evt_id": "699408",
    "temp": 2024
  },
  {
    "fecha": "2024-05-12T21:30Z",
    "ht": "Vasco da Gama",
    "at": "Vitória",
    "hg": 2,
    "ag": 1,
    "hst": 8,
    "ast": 5,
    "hs": 17,
    "as": 13,
    "hc": 4,
    "ac": 4,
    "evt_id": "699409",
    "temp": 2024
  },
  {
    "fecha": "2024-06-02T19:00Z",
    "ht": "Atlético-MG",
    "at": "Bahia",
    "hg": 1,
    "ag": 1,
    "hst": 4,
    "ast": 2,
    "hs": 21,
    "as": 9,
    "hc": 5,
    "ac": 4,
    "evt_id": "699410",
    "temp": 2024
  },
  {
    "fecha": "2024-06-02T00:00Z",
    "ht": "Corinthians",
    "at": "Botafogo",
    "hg": 0,
    "ag": 1,
    "hst": 7,
    "ast": 2,
    "hs": 16,
    "as": 9,
    "hc": 2,
    "ac": 5,
    "evt_id": "699411",
    "temp": 2024
  },
  {
    "fecha": "2024-06-02T19:00Z",
    "ht": "Criciúma",
    "at": "Palmeiras",
    "hg": 1,
    "ag": 2,
    "hst": 4,
    "ast": 5,
    "hs": 12,
    "as": 23,
    "hc": 4,
    "ac": 6,
    "evt_id": "699412",
    "temp": 2024
  },
  {
    "fecha": "2024-06-01T21:30Z",
    "ht": "Cuiabá",
    "at": "Internacional",
    "hg": 0,
    "ag": 1,
    "hst": 3,
    "ast": 3,
    "hs": 8,
    "as": 9,
    "hc": 0,
    "ac": 2,
    "evt_id": "699413",
    "temp": 2024
  },
  {
    "fecha": "2024-06-01T21:30Z",
    "ht": "Fluminense",
    "at": "Juventude",
    "hg": 1,
    "ag": 1,
    "hst": 4,
    "ast": 4,
    "hs": 17,
    "as": 12,
    "hc": 5,
    "ac": 3,
    "evt_id": "699414",
    "temp": 2024
  },
  {
    "fecha": "2024-06-02T21:30Z",
    "ht": "Fortaleza",
    "at": "Athletico Paranaense",
    "hg": 1,
    "ag": 0,
    "hst": 4,
    "ast": 2,
    "hs": 11,
    "as": 15,
    "hc": 3,
    "ac": 4,
    "evt_id": "699415",
    "temp": 2024
  },
  {
    "fecha": "2024-06-01T19:00Z",
    "ht": "Grêmio",
    "at": "Red Bull Bragantino",
    "hg": 0,
    "ag": 2,
    "hst": 1,
    "ast": 4,
    "hs": 9,
    "as": 14,
    "hc": 6,
    "ac": 0,
    "evt_id": "699416",
    "temp": 2024
  },
  {
    "fecha": "2024-06-02T21:30Z",
    "ht": "São Paulo",
    "at": "Cruzeiro",
    "hg": 2,
    "ag": 0,
    "hst": 4,
    "ast": 3,
    "hs": 11,
    "as": 10,
    "hc": 4,
    "ac": 2,
    "evt_id": "699417",
    "temp": 2024
  },
  {
    "fecha": "2024-06-02T19:00Z",
    "ht": "Vasco da Gama",
    "at": "Flamengo",
    "hg": 1,
    "ag": 6,
    "hst": 2,
    "ast": 18,
    "hs": 2,
    "as": 30,
    "hc": 1,
    "ac": 8,
    "evt_id": "699418",
    "temp": 2024
  },
  {
    "fecha": "2024-06-01T19:00Z",
    "ht": "Vitória",
    "at": "Atlético Goianiense",
    "hg": 0,
    "ag": 2,
    "hst": 3,
    "ast": 5,
    "hs": 12,
    "as": 12,
    "hc": 3,
    "ac": 4,
    "evt_id": "699419",
    "temp": 2024
  },
  {
    "fecha": "2024-06-13T23:00Z",
    "ht": "Athletico Paranaense",
    "at": "Criciúma",
    "hg": 3,
    "ag": 1,
    "hst": 7,
    "ast": 4,
    "hs": 23,
    "as": 12,
    "hc": 5,
    "ac": 3,
    "evt_id": "699420",
    "temp": 2024
  },
  {
    "fecha": "2024-06-11T22:00Z",
    "ht": "Atlético Goianiense",
    "at": "Corinthians",
    "hg": 2,
    "ag": 2,
    "hst": 7,
    "ast": 3,
    "hs": 22,
    "as": 7,
    "hc": 3,
    "ac": 4,
    "evt_id": "699421",
    "temp": 2024
  },
  {
    "fecha": "2024-06-14T00:30Z",
    "ht": "Bahia",
    "at": "Fortaleza",
    "hg": 1,
    "ag": 0,
    "hst": 3,
    "ast": 6,
    "hs": 12,
    "as": 21,
    "hc": 5,
    "ac": 9,
    "evt_id": "699422",
    "temp": 2024
  },
  {
    "fecha": "2024-06-11T23:00Z",
    "ht": "Botafogo",
    "at": "Fluminense",
    "hg": 1,
    "ag": 0,
    "hst": 6,
    "ast": 0,
    "hs": 19,
    "as": 6,
    "hc": 14,
    "ac": 2,
    "evt_id": "699423",
    "temp": 2024
  },
  {
    "fecha": "2024-06-13T23:00Z",
    "ht": "Flamengo",
    "at": "Grêmio",
    "hg": 2,
    "ag": 1,
    "hst": 6,
    "ast": 5,
    "hs": 16,
    "as": 15,
    "hc": 4,
    "ac": 6,
    "evt_id": "699424",
    "temp": 2024
  },
  {
    "fecha": "2024-06-12T00:30Z",
    "ht": "Red Bull Bragantino",
    "at": "Atlético-MG",
    "hg": 1,
    "ag": 2,
    "hst": 5,
    "ast": 4,
    "hs": 15,
    "as": 10,
    "hc": 8,
    "ac": 5,
    "evt_id": "699425",
    "temp": 2024
  },
  {
    "fecha": "2024-06-13T23:00Z",
    "ht": "Internacional",
    "at": "São Paulo",
    "hg": 0,
    "ag": 0,
    "hst": 0,
    "ast": 4,
    "hs": 7,
    "as": 9,
    "hc": 5,
    "ac": 3,
    "evt_id": "699426",
    "temp": 2024
  },
  {
    "fecha": "2024-06-11T22:00Z",
    "ht": "Juventude",
    "at": "Vitória",
    "hg": 1,
    "ag": 1,
    "hst": 2,
    "ast": 4,
    "hs": 12,
    "as": 18,
    "hc": 5,
    "ac": 4,
    "evt_id": "699427",
    "temp": 2024
  },
  {
    "fecha": "2024-06-14T00:30Z",
    "ht": "Palmeiras",
    "at": "Vasco da Gama",
    "hg": 2,
    "ag": 0,
    "hst": 0,
    "ast": 0,
    "hs": 0,
    "as": 0,
    "hc": 0,
    "ac": 0,
    "evt_id": "699428",
    "temp": 2024
  },
  {
    "fecha": "2024-06-13T22:00Z",
    "ht": "Cruzeiro",
    "at": "Cuiabá",
    "hg": 2,
    "ag": 1,
    "hst": 6,
    "ast": 5,
    "hs": 12,
    "as": 16,
    "hc": 6,
    "ac": 4,
    "evt_id": "699429",
    "temp": 2024
  },
  {
    "fecha": "2024-06-16T00:00Z",
    "ht": "Fluminense",
    "at": "Atlético Goianiense",
    "hg": 1,
    "ag": 2,
    "hst": 5,
    "ast": 7,
    "hs": 9,
    "as": 17,
    "hc": 3,
    "ac": 3,
    "evt_id": "699430",
    "temp": 2024
  },
  {
    "fecha": "2024-06-16T21:30Z",
    "ht": "Cuiabá",
    "at": "Fortaleza",
    "hg": 5,
    "ag": 0,
    "hst": 13,
    "ast": 0,
    "hs": 21,
    "as": 2,
    "hc": 5,
    "ac": 1,
    "evt_id": "699431",
    "temp": 2024
  },
  {
    "fecha": "2024-06-16T21:30Z",
    "ht": "Grêmio",
    "at": "Botafogo",
    "hg": 1,
    "ag": 2,
    "hst": 4,
    "ast": 5,
    "hs": 15,
    "as": 14,
    "hc": 7,
    "ac": 4,
    "evt_id": "699432",
    "temp": 2024
  },
  {
    "fecha": "2024-06-16T21:30Z",
    "ht": "Vasco da Gama",
    "at": "Cruzeiro",
    "hg": 0,
    "ag": 0,
    "hst": 0,
    "ast": 0,
    "hs": 0,
    "as": 0,
    "hc": 0,
    "ac": 0,
    "evt_id": "699433",
    "temp": 2024
  },
  {
    "fecha": "2024-06-15T21:30Z",
    "ht": "Red Bull Bragantino",
    "at": "Juventude",
    "hg": 2,
    "ag": 1,
    "hst": 2,
    "ast": 6,
    "hs": 6,
    "as": 14,
    "hc": 1,
    "ac": 1,
    "evt_id": "699434",
    "temp": 2024
  },
  {
    "fecha": "2024-06-16T19:00Z",
    "ht": "Vitória",
    "at": "Internacional",
    "hg": 2,
    "ag": 1,
    "hst": 4,
    "ast": 5,
    "hs": 11,
    "as": 15,
    "hc": 4,
    "ac": 2,
    "evt_id": "699435",
    "temp": 2024
  },
  {
    "fecha": "2024-06-16T19:00Z",
    "ht": "Athletico Paranaense",
    "at": "Flamengo",
    "hg": 1,
    "ag": 1,
    "hst": 3,
    "ast": 6,
    "hs": 14,
    "as": 9,
    "hc": 5,
    "ac": 9,
    "evt_id": "699436",
    "temp": 2024
  },
  {
    "fecha": "2024-06-17T23:30Z",
    "ht": "Atlético-MG",
    "at": "Palmeiras",
    "hg": 0,
    "ag": 4,
    "hst": 3,
    "ast": 9,
    "hs": 11,
    "as": 22,
    "hc": 3,
    "ac": 6,
    "evt_id": "699437",
    "temp": 2024
  },
  {
    "fecha": "2024-06-16T19:00Z",
    "ht": "Corinthians",
    "at": "São Paulo",
    "hg": 2,
    "ag": 2,
    "hst": 8,
    "ast": 7,
    "hs": 16,
    "as": 12,
    "hc": 9,
    "ac": 5,
    "evt_id": "699438",
    "temp": 2024
  },
  {
    "fecha": "2024-06-16T21:30Z",
    "ht": "Criciúma",
    "at": "Bahia",
    "hg": 2,
    "ag": 2,
    "hst": 5,
    "ast": 6,
    "hs": 17,
    "as": 22,
    "hc": 6,
    "ac": 7,
    "evt_id": "699439",
    "temp": 2024
  },
  {
    "fecha": "2024-06-19T22:00Z",
    "ht": "Atlético Goianiense",
    "at": "Criciúma",
    "hg": 1,
    "ag": 2,
    "hst": 1,
    "ast": 7,
    "hs": 12,
    "as": 19,
    "hc": 5,
    "ac": 1,
    "evt_id": "699440",
    "temp": 2024
  },
  {
    "fecha": "2024-06-19T22:00Z",
    "ht": "Botafogo",
    "at": "Athletico Paranaense",
    "hg": 1,
    "ag": 1,
    "hst": 1,
    "ast": 6,
    "hs": 8,
    "as": 16,
    "hc": 5,
    "ac": 9,
    "evt_id": "699441",
    "temp": 2024
  },
  {
    "fecha": "2024-06-20T00:30Z",
    "ht": "Cruzeiro",
    "at": "Fluminense",
    "hg": 2,
    "ag": 0,
    "hst": 5,
    "ast": 4,
    "hs": 17,
    "as": 9,
    "hc": 6,
    "ac": 5,
    "evt_id": "699442",
    "temp": 2024
  },
  {
    "fecha": "2024-06-20T23:00Z",
    "ht": "Flamengo",
    "at": "Bahia",
    "hg": 2,
    "ag": 1,
    "hst": 3,
    "ast": 3,
    "hs": 14,
    "as": 8,
    "hc": 6,
    "ac": 2,
    "evt_id": "699443",
    "temp": 2024
  },
  {
    "fecha": "2024-06-20T00:30Z",
    "ht": "Internacional",
    "at": "Corinthians",
    "hg": 1,
    "ag": 0,
    "hst": 5,
    "ast": 3,
    "hs": 11,
    "as": 13,
    "hc": 3,
    "ac": 7,
    "evt_id": "699444",
    "temp": 2024
  },
  {
    "fecha": "2024-06-20T21:30Z",
    "ht": "Vitória",
    "at": "Atlético-MG",
    "hg": 4,
    "ag": 2,
    "hst": 6,
    "ast": 7,
    "hs": 12,
    "as": 19,
    "hc": 2,
    "ac": 4,
    "evt_id": "699445",
    "temp": 2024
  },
  {
    "fecha": "2024-06-19T23:00Z",
    "ht": "Juventude",
    "at": "Vasco da Gama",
    "hg": 2,
    "ag": 0,
    "hst": 0,
    "ast": 0,
    "hs": 0,
    "as": 0,
    "hc": 0,
    "ac": 0,
    "evt_id": "699446",
    "temp": 2024
  },
  {
    "fecha": "2024-06-21T00:30Z",
    "ht": "Palmeiras",
    "at": "Red Bull Bragantino",
    "hg": 2,
    "ag": 1,
    "hst": 7,
    "ast": 3,
    "hs": 24,
    "as": 13,
    "hc": 10,
    "ac": 3,
    "evt_id": "699447",
    "temp": 2024
  },
  {
    "fecha": "2024-06-19T23:00Z",
    "ht": "São Paulo",
    "at": "Cuiabá",
    "hg": 0,
    "ag": 1,
    "hst": 4,
    "ast": 3,
    "hs": 15,
    "as": 11,
    "hc": 4,
    "ac": 6,
    "evt_id": "699448",
    "temp": 2024
  },
  {
    "fecha": "2024-06-19T23:00Z",
    "ht": "Fortaleza",
    "at": "Grêmio",
    "hg": 1,
    "ag": 0,
    "hst": 4,
    "ast": 2,
    "hs": 13,
    "as": 8,
    "hc": 8,
    "ac": 3,
    "evt_id": "699449",
    "temp": 2024
  },
  {
    "fecha": "2024-06-23T19:00Z",
    "ht": "Athletico Paranaense",
    "at": "Corinthians",
    "hg": 1,
    "ag": 1,
    "hst": 7,
    "ast": 6,
    "hs": 20,
    "as": 15,
    "hc": 11,
    "ac": 2,
    "evt_id": "699450",
    "temp": 2024
  },
  {
    "fecha": "2024-06-23T21:30Z",
    "ht": "Atlético-MG",
    "at": "Fortaleza",
    "hg": 1,
    "ag": 1,
    "hst": 8,
    "ast": 3,
    "hs": 21,
    "as": 13,
    "hc": 3,
    "ac": 4,
    "evt_id": "699451",
    "temp": 2024
  },
  {
    "fecha": "2024-06-23T19:00Z",
    "ht": "Bahia",
    "at": "Cruzeiro",
    "hg": 4,
    "ag": 1,
    "hst": 6,
    "ast": 1,
    "hs": 14,
    "as": 7,
    "hc": 3,
    "ac": 1,
    "evt_id": "699452",
    "temp": 2024
  },
  {
    "fecha": "2024-06-22T19:00Z",
    "ht": "Criciúma",
    "at": "Botafogo",
    "hg": 2,
    "ag": 1,
    "hst": 4,
    "ast": 2,
    "hs": 16,
    "as": 11,
    "hc": 4,
    "ac": 7,
    "evt_id": "699453",
    "temp": 2024
  },
  {
    "fecha": "2024-06-22T21:30Z",
    "ht": "Cuiabá",
    "at": "Atlético Goianiense",
    "hg": 0,
    "ag": 0,
    "hst": 3,
    "ast": 9,
    "hs": 10,
    "as": 18,
    "hc": 5,
    "ac": 4,
    "evt_id": "699454",
    "temp": 2024
  },
  {
    "fecha": "2024-06-23T19:00Z",
    "ht": "Fluminense",
    "at": "Flamengo",
    "hg": 0,
    "ag": 1,
    "hst": 0,
    "ast": 4,
    "hs": 2,
    "as": 14,
    "hc": 2,
    "ac": 6,
    "evt_id": "699455",
    "temp": 2024
  },
  {
    "fecha": "2024-06-22T20:30Z",
    "ht": "Grêmio",
    "at": "Internacional",
    "hg": 0,
    "ag": 1,
    "hst": 2,
    "ast": 2,
    "hs": 10,
    "as": 16,
    "hc": 5,
    "ac": 4,
    "evt_id": "699456",
    "temp": 2024
  },
  {
    "fecha": "2024-06-23T21:30Z",
    "ht": "Palmeiras",
    "at": "Juventude",
    "hg": 3,
    "ag": 1,
    "hst": 10,
    "ast": 8,
    "hs": 28,
    "as": 16,
    "hc": 11,
    "ac": 4,
    "evt_id": "699457",
    "temp": 2024
  },
  {
    "fecha": "2024-06-23T21:30Z",
    "ht": "Red Bull Bragantino",
    "at": "Vitória",
    "hg": 2,
    "ag": 1,
    "hst": 6,
    "ast": 5,
    "hs": 16,
    "as": 10,
    "hc": 6,
    "ac": 7,
    "evt_id": "699458",
    "temp": 2024
  },
  {
    "fecha": "2024-06-23T00:30Z",
    "ht": "Vasco da Gama",
    "at": "São Paulo",
    "hg": 4,
    "ag": 1,
    "hst": 7,
    "ast": 2,
    "hs": 14,
    "as": 10,
    "hc": 2,
    "ac": 8,
    "evt_id": "699459",
    "temp": 2024
  },
  {
    "fecha": "2024-06-26T23:00Z",
    "ht": "Atlético Goianiense",
    "at": "Grêmio",
    "hg": 1,
    "ag": 1,
    "hst": 5,
    "ast": 4,
    "hs": 16,
    "as": 11,
    "hc": 5,
    "ac": 8,
    "evt_id": "699460",
    "temp": 2024
  },
  {
    "fecha": "2024-06-27T00:30Z",
    "ht": "Bahia",
    "at": "Vasco da Gama",
    "hg": 2,
    "ag": 1,
    "hst": 8,
    "ast": 3,
    "hs": 17,
    "as": 9,
    "hc": 7,
    "ac": 0,
    "evt_id": "699461",
    "temp": 2024
  },
  {
    "fecha": "2024-06-26T22:00Z",
    "ht": "Botafogo",
    "at": "Red Bull Bragantino",
    "hg": 2,
    "ag": 1,
    "hst": 4,
    "ast": 6,
    "hs": 12,
    "as": 13,
    "hc": 7,
    "ac": 4,
    "evt_id": "699462",
    "temp": 2024
  },
  {
    "fecha": "2024-06-26T23:00Z",
    "ht": "Corinthians",
    "at": "Cuiabá",
    "hg": 1,
    "ag": 1,
    "hst": 7,
    "ast": 4,
    "hs": 24,
    "as": 13,
    "hc": 13,
    "ac": 1,
    "evt_id": "699463",
    "temp": 2024
  },
  {
    "fecha": "2024-06-26T22:00Z",
    "ht": "Cruzeiro",
    "at": "Athletico Paranaense",
    "hg": 2,
    "ag": 0,
    "hst": 7,
    "ast": 3,
    "hs": 22,
    "as": 14,
    "hc": 7,
    "ac": 12,
    "evt_id": "699464",
    "temp": 2024
  },
  {
    "fecha": "2024-06-27T22:00Z",
    "ht": "Fluminense",
    "at": "Vitória",
    "hg": 0,
    "ag": 1,
    "hst": 5,
    "ast": 6,
    "hs": 12,
    "as": 9,
    "hc": 6,
    "ac": 2,
    "evt_id": "699465",
    "temp": 2024
  },
  {
    "fecha": "2024-06-27T00:30Z",
    "ht": "Fortaleza",
    "at": "Palmeiras",
    "hg": 3,
    "ag": 0,
    "hst": 6,
    "ast": 7,
    "hs": 12,
    "as": 17,
    "hc": 3,
    "ac": 8,
    "evt_id": "699466",
    "temp": 2024
  },
  {
    "fecha": "2024-06-27T00:30Z",
    "ht": "Internacional",
    "at": "Atlético-MG",
    "hg": 1,
    "ag": 2,
    "hst": 6,
    "ast": 5,
    "hs": 13,
    "as": 15,
    "hc": 5,
    "ac": 9,
    "evt_id": "699467",
    "temp": 2024
  },
  {
    "fecha": "2024-06-26T23:00Z",
    "ht": "Juventude",
    "at": "Flamengo",
    "hg": 2,
    "ag": 1,
    "hst": 8,
    "ast": 5,
    "hs": 15,
    "as": 9,
    "hc": 7,
    "ac": 8,
    "evt_id": "699468",
    "temp": 2024
  },
  {
    "fecha": "2024-06-27T23:00Z",
    "ht": "São Paulo",
    "at": "Criciúma",
    "hg": 2,
    "ag": 1,
    "hst": 6,
    "ast": 2,
    "hs": 13,
    "as": 10,
    "hc": 2,
    "ac": 2,
    "evt_id": "699469",
    "temp": 2024
  },
  {
    "fecha": "2024-06-30T14:00Z",
    "ht": "Atlético-MG",
    "at": "Atlético Goianiense",
    "hg": 1,
    "ag": 1,
    "hst": 6,
    "ast": 6,
    "hs": 15,
    "as": 12,
    "hc": 5,
    "ac": 8,
    "evt_id": "699470",
    "temp": 2024
  },
  {
    "fecha": "2024-06-30T21:30Z",
    "ht": "Criciúma",
    "at": "Internacional",
    "hg": 1,
    "ag": 1,
    "hst": 7,
    "ast": 4,
    "hs": 17,
    "as": 12,
    "hc": 5,
    "ac": 5,
    "evt_id": "699471",
    "temp": 2024
  },
  {
    "fecha": "2024-06-29T21:30Z",
    "ht": "Cuiabá",
    "at": "Red Bull Bragantino",
    "hg": 1,
    "ag": 1,
    "hst": 2,
    "ast": 5,
    "hs": 5,
    "as": 14,
    "hc": 3,
    "ac": 11,
    "evt_id": "699472",
    "temp": 2024
  },
  {
    "fecha": "2024-06-30T21:30Z",
    "ht": "Flamengo",
    "at": "Cruzeiro",
    "hg": 2,
    "ag": 1,
    "hst": 3,
    "ast": 5,
    "hs": 7,
    "as": 14,
    "hc": 2,
    "ac": 5,
    "evt_id": "699473",
    "temp": 2024
  },
  {
    "fecha": "2024-06-30T19:00Z",
    "ht": "Fortaleza",
    "at": "Juventude",
    "hg": 2,
    "ag": 1,
    "hst": 7,
    "ast": 3,
    "hs": 19,
    "as": 12,
    "hc": 7,
    "ac": 5,
    "evt_id": "699474",
    "temp": 2024
  },
  {
    "fecha": "2024-06-30T19:00Z",
    "ht": "Grêmio",
    "at": "Fluminense",
    "hg": 1,
    "ag": 0,
    "hst": 9,
    "ast": 3,
    "hs": 16,
    "as": 8,
    "hc": 6,
    "ac": 1,
    "evt_id": "699475",
    "temp": 2024
  },
  {
    "fecha": "2024-07-01T23:00Z",
    "ht": "Palmeiras",
    "at": "Corinthians",
    "hg": 2,
    "ag": 0,
    "hst": 10,
    "ast": 3,
    "hs": 20,
    "as": 13,
    "hc": 7,
    "ac": 3,
    "evt_id": "699476",
    "temp": 2024
  },
  {
    "fecha": "2024-06-30T19:00Z",
    "ht": "São Paulo",
    "at": "Bahia",
    "hg": 3,
    "ag": 1,
    "hst": 4,
    "ast": 6,
    "hs": 10,
    "as": 15,
    "hc": 4,
    "ac": 4,
    "evt_id": "699477",
    "temp": 2024
  },
  {
    "fecha": "2024-06-29T21:30Z",
    "ht": "Vasco da Gama",
    "at": "Botafogo",
    "hg": 1,
    "ag": 1,
    "hst": 2,
    "ast": 6,
    "hs": 10,
    "as": 13,
    "hc": 0,
    "ac": 5,
    "evt_id": "699478",
    "temp": 2024
  },
  {
    "fecha": "2024-06-30T21:30Z",
    "ht": "Vitória",
    "at": "Athletico Paranaense",
    "hg": 0,
    "ag": 1,
    "hst": 3,
    "ast": 2,
    "hs": 16,
    "as": 7,
    "hc": 7,
    "ac": 6,
    "evt_id": "699479",
    "temp": 2024
  },
  {
    "fecha": "2024-07-04T00:30Z",
    "ht": "Athletico Paranaense",
    "at": "São Paulo",
    "hg": 1,
    "ag": 2,
    "hst": 4,
    "ast": 8,
    "hs": 12,
    "as": 13,
    "hc": 6,
    "ac": 2,
    "evt_id": "699480",
    "temp": 2024
  },
  {
    "fecha": "2024-07-04T00:30Z",
    "ht": "Atlético-MG",
    "at": "Flamengo",
    "hg": 2,
    "ag": 4,
    "hst": 4,
    "ast": 8,
    "hs": 11,
    "as": 14,
    "hc": 4,
    "ac": 4,
    "evt_id": "699481",
    "temp": 2024
  },
  {
    "fecha": "2024-07-04T22:00Z",
    "ht": "Bahia",
    "at": "Juventude",
    "hg": 2,
    "ag": 0,
    "hst": 9,
    "ast": 2,
    "hs": 22,
    "as": 10,
    "hc": 6,
    "ac": 7,
    "evt_id": "699482",
    "temp": 2024
  },
  {
    "fecha": "2024-07-04T23:00Z",
    "ht": "Corinthians",
    "at": "Vitória",
    "hg": 3,
    "ag": 2,
    "hst": 5,
    "ast": 6,
    "hs": 14,
    "as": 18,
    "hc": 9,
    "ac": 9,
    "evt_id": "699483",
    "temp": 2024
  },
  {
    "fecha": "2024-07-04T00:30Z",
    "ht": "Red Bull Bragantino",
    "at": "Atlético Goianiense",
    "hg": 3,
    "ag": 1,
    "hst": 5,
    "ast": 6,
    "hs": 13,
    "as": 13,
    "hc": 3,
    "ac": 8,
    "evt_id": "699484",
    "temp": 2024
  },
  {
    "fecha": "2024-07-03T22:00Z",
    "ht": "Cuiabá",
    "at": "Botafogo",
    "hg": 1,
    "ag": 2,
    "hst": 6,
    "ast": 4,
    "hs": 11,
    "as": 6,
    "hc": 7,
    "ac": 5,
    "evt_id": "699485",
    "temp": 2024
  },
  {
    "fecha": "2024-07-04T23:00Z",
    "ht": "Fluminense",
    "at": "Internacional",
    "hg": 1,
    "ag": 1,
    "hst": 3,
    "ast": 4,
    "hs": 8,
    "as": 12,
    "hc": 3,
    "ac": 4,
    "evt_id": "699486",
    "temp": 2024
  },
  {
    "fecha": "2024-07-04T22:00Z",
    "ht": "Grêmio",
    "at": "Palmeiras",
    "hg": 2,
    "ag": 2,
    "hst": 5,
    "ast": 5,
    "hs": 14,
    "as": 21,
    "hc": 5,
    "ac": 10,
    "evt_id": "699487",
    "temp": 2024
  },
  {
    "fecha": "2024-07-03T23:00Z",
    "ht": "Vasco da Gama",
    "at": "Fortaleza",
    "hg": 2,
    "ag": 0,
    "hst": 9,
    "ast": 4,
    "hs": 19,
    "as": 10,
    "hc": 7,
    "ac": 3,
    "evt_id": "699488",
    "temp": 2024
  },
  {
    "fecha": "2024-07-03T23:00Z",
    "ht": "Criciúma",
    "at": "Cruzeiro",
    "hg": 1,
    "ag": 0,
    "hst": 6,
    "ast": 6,
    "hs": 13,
    "as": 17,
    "hc": 7,
    "ac": 10,
    "evt_id": "699489",
    "temp": 2024
  },
  {
    "fecha": "2024-07-06T23:00Z",
    "ht": "São Paulo",
    "at": "Red Bull Bragantino",
    "hg": 2,
    "ag": 0,
    "hst": 4,
    "ast": 3,
    "hs": 14,
    "as": 10,
    "hc": 6,
    "ac": 3,
    "evt_id": "699490",
    "temp": 2024
  },
  {
    "fecha": "2024-07-07T21:30Z",
    "ht": "Vitória",
    "at": "Criciúma",
    "hg": 2,
    "ag": 1,
    "hst": 3,
    "ast": 2,
    "hs": 9,
    "as": 13,
    "hc": 6,
    "ac": 3,
    "evt_id": "699491",
    "temp": 2024
  },
  {
    "fecha": "2024-07-07T21:30Z",
    "ht": "Atlético Goianiense",
    "at": "Athletico Paranaense",
    "hg": 1,
    "ag": 2,
    "hst": 3,
    "ast": 6,
    "hs": 12,
    "as": 17,
    "hc": 4,
    "ac": 11,
    "evt_id": "699492",
    "temp": 2024
  },
  {
    "fecha": "2024-07-07T23:30Z",
    "ht": "Botafogo",
    "at": "Atlético-MG",
    "hg": 3,
    "ag": 0,
    "hst": 8,
    "ast": 2,
    "hs": 19,
    "as": 6,
    "hc": 3,
    "ac": 2,
    "evt_id": "699493",
    "temp": 2024
  },
  {
    "fecha": "2024-07-07T19:00Z",
    "ht": "Cruzeiro",
    "at": "Corinthians",
    "hg": 3,
    "ag": 0,
    "hst": 5,
    "ast": 2,
    "hs": 12,
    "as": 15,
    "hc": 8,
    "ac": 8,
    "evt_id": "699494",
    "temp": 2024
  },
  {
    "fecha": "2024-07-06T23:00Z",
    "ht": "Flamengo",
    "at": "Cuiabá",
    "hg": 1,
    "ag": 1,
    "hst": 10,
    "ast": 3,
    "hs": 20,
    "as": 7,
    "hc": 7,
    "ac": 0,
    "evt_id": "699495",
    "temp": 2024
  },
  {
    "fecha": "2024-07-07T19:00Z",
    "ht": "Fortaleza",
    "at": "Fluminense",
    "hg": 1,
    "ag": 0,
    "hst": 6,
    "ast": 3,
    "hs": 19,
    "as": 11,
    "hc": 12,
    "ac": 3,
    "evt_id": "699496",
    "temp": 2024
  },
  {
    "fecha": "2024-07-07T21:00Z",
    "ht": "Internacional",
    "at": "Vasco da Gama",
    "hg": 1,
    "ag": 2,
    "hst": 6,
    "ast": 6,
    "hs": 14,
    "as": 8,
    "hc": 4,
    "ac": 4,
    "evt_id": "699497",
    "temp": 2024
  },
  {
    "fecha": "2024-07-07T19:00Z",
    "ht": "Juventude",
    "at": "Grêmio",
    "hg": 3,
    "ag": 0,
    "hst": 6,
    "ast": 5,
    "hs": 14,
    "as": 13,
    "hc": 3,
    "ac": 8,
    "evt_id": "699498",
    "temp": 2024
  },
  {
    "fecha": "2024-07-07T21:30Z",
    "ht": "Palmeiras",
    "at": "Bahia",
    "hg": 2,
    "ag": 0,
    "hst": 4,
    "ast": 3,
    "hs": 12,
    "as": 13,
    "hc": 4,
    "ac": 3,
    "evt_id": "699499",
    "temp": 2024
  },
  {
    "fecha": "2024-07-11T23:00Z",
    "ht": "Criciúma",
    "at": "Fluminense",
    "hg": 1,
    "ag": 1,
    "hst": 4,
    "ast": 10,
    "hs": 13,
    "as": 18,
    "hc": 2,
    "ac": 5,
    "evt_id": "699500",
    "temp": 2024
  },
  {
    "fecha": "2024-07-12T00:30Z",
    "ht": "Atlético-MG",
    "at": "São Paulo",
    "hg": 2,
    "ag": 1,
    "hst": 5,
    "ast": 4,
    "hs": 14,
    "as": 11,
    "hc": 2,
    "ac": 6,
    "evt_id": "699501",
    "temp": 2024
  },
  {
    "fecha": "2024-07-10T22:00Z",
    "ht": "Athletico Paranaense",
    "at": "Bahia",
    "hg": 1,
    "ag": 3,
    "hst": 8,
    "ast": 5,
    "hs": 22,
    "as": 7,
    "hc": 9,
    "ac": 2,
    "evt_id": "699502",
    "temp": 2024
  },
  {
    "fecha": "2024-09-05T23:00Z",
    "ht": "Cuiabá",
    "at": "Juventude",
    "hg": 0,
    "ag": 0,
    "hst": 3,
    "ast": 3,
    "hs": 12,
    "as": 9,
    "hc": 3,
    "ac": 3,
    "evt_id": "699503",
    "temp": 2024
  },
  {
    "fecha": "2024-07-10T21:30Z",
    "ht": "Grêmio",
    "at": "Cruzeiro",
    "hg": 0,
    "ag": 2,
    "hst": 3,
    "ast": 6,
    "hs": 8,
    "as": 14,
    "hc": 1,
    "ac": 5,
    "evt_id": "699504",
    "temp": 2024
  },
  {
    "fecha": "2024-07-11T23:00Z",
    "ht": "Flamengo",
    "at": "Fortaleza",
    "hg": 1,
    "ag": 2,
    "hst": 7,
    "ast": 2,
    "hs": 21,
    "as": 7,
    "hc": 9,
    "ac": 4,
    "evt_id": "699505",
    "temp": 2024
  },
  {
    "fecha": "2024-07-12T00:30Z",
    "ht": "Vitória",
    "at": "Botafogo",
    "hg": 0,
    "ag": 1,
    "hst": 5,
    "ast": 4,
    "hs": 11,
    "as": 15,
    "hc": 4,
    "ac": 5,
    "evt_id": "699506",
    "temp": 2024
  },
  {
    "fecha": "2024-07-10T22:00Z",
    "ht": "Vasco da Gama",
    "at": "Corinthians",
    "hg": 2,
    "ag": 0,
    "hst": 3,
    "ast": 2,
    "hs": 14,
    "as": 11,
    "hc": 7,
    "ac": 5,
    "evt_id": "699507",
    "temp": 2024
  },
  {
    "fecha": "2024-07-11T22:30Z",
    "ht": "Palmeiras",
    "at": "Atlético Goianiense",
    "hg": 3,
    "ag": 1,
    "hst": 6,
    "ast": 3,
    "hs": 23,
    "as": 11,
    "hc": 9,
    "ac": 2,
    "evt_id": "699508",
    "temp": 2024
  },
  {
    "fecha": "2024-09-25T22:00Z",
    "ht": "Red Bull Bragantino",
    "at": "Internacional",
    "hg": 2,
    "ag": 2,
    "hst": 4,
    "ast": 11,
    "hs": 11,
    "as": 24,
    "hc": 1,
    "ac": 9,
    "evt_id": "699509",
    "temp": 2024
  },
  {
    "fecha": "2024-10-30T22:00Z",
    "ht": "Internacional",
    "at": "Flamengo",
    "hg": 1,
    "ag": 1,
    "hst": 5,
    "ast": 3,
    "hs": 18,
    "as": 12,
    "hc": 5,
    "ac": 5,
    "evt_id": "699510",
    "temp": 2024
  },
  {
    "fecha": "2024-07-18T00:30Z",
    "ht": "Fortaleza",
    "at": "Vitória",
    "hg": 3,
    "ag": 1,
    "hst": 4,
    "ast": 3,
    "hs": 12,
    "as": 11,
    "hc": 1,
    "ac": 6,
    "evt_id": "699511",
    "temp": 2024
  },
  {
    "fecha": "2024-10-22T22:30Z",
    "ht": "Fluminense",
    "at": "Athletico Paranaense",
    "hg": 1,
    "ag": 0,
    "hst": 5,
    "ast": 2,
    "hs": 14,
    "as": 6,
    "hc": 5,
    "ac": 3,
    "evt_id": "699512",
    "temp": 2024
  },
  {
    "fecha": "2024-07-13T19:00Z",
    "ht": "Cruzeiro",
    "at": "Red Bull Bragantino",
    "hg": 2,
    "ag": 1,
    "hst": 4,
    "ast": 5,
    "hs": 10,
    "as": 15,
    "hc": 1,
    "ac": 8,
    "evt_id": "699513",
    "temp": 2024
  },
  {
    "fecha": "2024-07-17T00:00Z",
    "ht": "Corinthians",
    "at": "Criciúma",
    "hg": 2,
    "ag": 1,
    "hst": 7,
    "ast": 4,
    "hs": 14,
    "as": 16,
    "hc": 5,
    "ac": 5,
    "evt_id": "699514",
    "temp": 2024
  },
  {
    "fecha": "2024-07-18T00:30Z",
    "ht": "Botafogo",
    "at": "Palmeiras",
    "hg": 1,
    "ag": 0,
    "hst": 7,
    "ast": 5,
    "hs": 16,
    "as": 18,
    "hc": 5,
    "ac": 4,
    "evt_id": "699515",
    "temp": 2024
  },
  {
    "fecha": "2024-07-13T19:00Z",
    "ht": "Bahia",
    "at": "Cuiabá",
    "hg": 1,
    "ag": 2,
    "hst": 2,
    "ast": 3,
    "hs": 14,
    "as": 14,
    "hc": 8,
    "ac": 4,
    "evt_id": "699516",
    "temp": 2024
  },
  {
    "fecha": "2024-07-17T22:00Z",
    "ht": "Atlético Goianiense",
    "at": "Vasco da Gama",
    "hg": 0,
    "ag": 1,
    "hst": 7,
    "ast": 5,
    "hs": 19,
    "as": 14,
    "hc": 4,
    "ac": 6,
    "evt_id": "699517",
    "temp": 2024
  },
  {
    "fecha": "2024-07-16T22:00Z",
    "ht": "Juventude",
    "at": "Atlético-MG",
    "hg": 1,
    "ag": 1,
    "hst": 2,
    "ast": 5,
    "hs": 8,
    "as": 20,
    "hc": 1,
    "ac": 8,
    "evt_id": "699518",
    "temp": 2024
  },
  {
    "fecha": "2024-07-17T23:00Z",
    "ht": "São Paulo",
    "at": "Grêmio",
    "hg": 1,
    "ag": 0,
    "hst": 8,
    "ast": 5,
    "hs": 14,
    "as": 19,
    "hc": 8,
    "ac": 9,
    "evt_id": "699519",
    "temp": 2024
  },
  {
    "fecha": "2024-07-21T00:00Z",
    "ht": "Palmeiras",
    "at": "Cruzeiro",
    "hg": 2,
    "ag": 0,
    "hst": 5,
    "ast": 2,
    "hs": 15,
    "as": 8,
    "hc": 6,
    "ac": 4,
    "evt_id": "699520",
    "temp": 2024
  },
  {
    "fecha": "2024-07-21T21:30Z",
    "ht": "Juventude",
    "at": "São Paulo",
    "hg": 0,
    "ag": 0,
    "hst": 0,
    "ast": 2,
    "hs": 10,
    "as": 11,
    "hc": 1,
    "ac": 4,
    "evt_id": "699521",
    "temp": 2024
  },
  {
    "fecha": "2024-07-21T14:00Z",
    "ht": "Grêmio",
    "at": "Vitória",
    "hg": 2,
    "ag": 0,
    "hst": 6,
    "ast": 0,
    "hs": 13,
    "as": 5,
    "hc": 7,
    "ac": 4,
    "evt_id": "699522",
    "temp": 2024
  },
  {
    "fecha": "2024-07-21T21:30Z",
    "ht": "Fortaleza",
    "at": "Atlético Goianiense",
    "hg": 3,
    "ag": 1,
    "hst": 3,
    "ast": 2,
    "hs": 12,
    "as": 10,
    "hc": 5,
    "ac": 6,
    "evt_id": "699523",
    "temp": 2024
  },
  {
    "fecha": "2024-07-20T19:00Z",
    "ht": "Flamengo",
    "at": "Criciúma",
    "hg": 2,
    "ag": 1,
    "hst": 6,
    "ast": 4,
    "hs": 15,
    "as": 16,
    "hc": 7,
    "ac": 4,
    "evt_id": "699524",
    "temp": 2024
  },
  {
    "fecha": "2024-07-21T23:00Z",
    "ht": "Cuiabá",
    "at": "Fluminense",
    "hg": 0,
    "ag": 1,
    "hst": 6,
    "ast": 4,
    "hs": 16,
    "as": 10,
    "hc": 6,
    "ac": 4,
    "evt_id": "699525",
    "temp": 2024
  },
  {
    "fecha": "2024-07-20T21:30Z",
    "ht": "Botafogo",
    "at": "Internacional",
    "hg": 1,
    "ag": 0,
    "hst": 4,
    "ast": 1,
    "hs": 10,
    "as": 10,
    "hc": 2,
    "ac": 1,
    "evt_id": "699526",
    "temp": 2024
  },
  {
    "fecha": "2024-07-21T19:00Z",
    "ht": "Bahia",
    "at": "Corinthians",
    "hg": 0,
    "ag": 1,
    "hst": 7,
    "ast": 2,
    "hs": 17,
    "as": 7,
    "hc": 6,
    "ac": 3,
    "evt_id": "699527",
    "temp": 2024
  },
  {
    "fecha": "2024-07-21T19:00Z",
    "ht": "Atlético-MG",
    "at": "Vasco da Gama",
    "hg": 2,
    "ag": 0,
    "hst": 3,
    "ast": 1,
    "hs": 15,
    "as": 8,
    "hc": 6,
    "ac": 1,
    "evt_id": "699528",
    "temp": 2024
  },
  {
    "fecha": "2024-07-21T21:30Z",
    "ht": "Red Bull Bragantino",
    "at": "Athletico Paranaense",
    "hg": 1,
    "ag": 0,
    "hst": 3,
    "ast": 7,
    "hs": 12,
    "as": 19,
    "hc": 2,
    "ac": 11,
    "evt_id": "699529",
    "temp": 2024
  },
  {
    "fecha": "2024-10-24T22:00Z",
    "ht": "Vasco da Gama",
    "at": "Cuiabá",
    "hg": 1,
    "ag": 0,
    "hst": 2,
    "ast": 2,
    "hs": 13,
    "as": 13,
    "hc": 3,
    "ac": 2,
    "evt_id": "699530",
    "temp": 2024
  },
  {
    "fecha": "2024-07-24T22:30Z",
    "ht": "São Paulo",
    "at": "Botafogo",
    "hg": 2,
    "ag": 2,
    "hst": 6,
    "ast": 6,
    "hs": 15,
    "as": 12,
    "hc": 7,
    "ac": 1,
    "evt_id": "699531",
    "temp": 2024
  },
  {
    "fecha": "2024-09-11T22:30Z",
    "ht": "Internacional",
    "at": "Fortaleza",
    "hg": 2,
    "ag": 1,
    "hst": 8,
    "ast": 1,
    "hs": 16,
    "as": 12,
    "hc": 8,
    "ac": 3,
    "evt_id": "699532",
    "temp": 2024
  },
  {
    "fecha": "2024-07-25T00:30Z",
    "ht": "Fluminense",
    "at": "Palmeiras",
    "hg": 1,
    "ag": 0,
    "hst": 2,
    "ast": 1,
    "hs": 14,
    "as": 7,
    "hc": 4,
    "ac": 2,
    "evt_id": "699533",
    "temp": 2024
  },
  {
    "fecha": "2024-07-24T22:00Z",
    "ht": "Cruzeiro",
    "at": "Juventude",
    "hg": 2,
    "ag": 0,
    "hst": 5,
    "ast": 2,
    "hs": 12,
    "as": 7,
    "hc": 6,
    "ac": 5,
    "evt_id": "699534",
    "temp": 2024
  },
  {
    "fecha": "2024-08-28T22:30Z",
    "ht": "Criciúma",
    "at": "Red Bull Bragantino",
    "hg": 1,
    "ag": 0,
    "hst": 2,
    "ast": 6,
    "hs": 13,
    "as": 15,
    "hc": 6,
    "ac": 8,
    "evt_id": "699535",
    "temp": 2024
  },
  {
    "fecha": "2024-07-25T23:00Z",
    "ht": "Corinthians",
    "at": "Grêmio",
    "hg": 2,
    "ag": 2,
    "hst": 7,
    "ast": 7,
    "hs": 14,
    "as": 18,
    "hc": 4,
    "ac": 5,
    "evt_id": "699536",
    "temp": 2024
  },
  {
    "fecha": "2024-07-25T00:30Z",
    "ht": "Atlético Goianiense",
    "at": "Bahia",
    "hg": 1,
    "ag": 1,
    "hst": 4,
    "ast": 2,
    "hs": 15,
    "as": 7,
    "hc": 8,
    "ac": 4,
    "evt_id": "699537",
    "temp": 2024
  },
  {
    "fecha": "2024-11-16T21:30Z",
    "ht": "Athletico Paranaense",
    "at": "Atlético-MG",
    "hg": 1,
    "ag": 0,
    "hst": 5,
    "ast": 3,
    "hs": 17,
    "as": 13,
    "hc": 4,
    "ac": 3,
    "evt_id": "699538",
    "temp": 2024
  },
  {
    "fecha": "2024-07-24T23:00Z",
    "ht": "Vitória",
    "at": "Flamengo",
    "hg": 1,
    "ag": 2,
    "hst": 3,
    "ast": 4,
    "hs": 10,
    "as": 8,
    "hc": 4,
    "ac": 8,
    "evt_id": "699539",
    "temp": 2024
  },
  {
    "fecha": "2024-07-28T22:00Z",
    "ht": "Atlético-MG",
    "at": "Corinthians",
    "hg": 2,
    "ag": 1,
    "hst": 4,
    "ast": 7,
    "hs": 10,
    "as": 11,
    "hc": 4,
    "ac": 4,
    "evt_id": "699540",
    "temp": 2024
  },
  {
    "fecha": "2024-07-27T23:00Z",
    "ht": "Bahia",
    "at": "Internacional",
    "hg": 1,
    "ag": 1,
    "hst": 3,
    "ast": 2,
    "hs": 9,
    "as": 12,
    "hc": 4,
    "ac": 2,
    "evt_id": "699541",
    "temp": 2024
  },
  {
    "fecha": "2024-07-28T00:30Z",
    "ht": "Botafogo",
    "at": "Cruzeiro",
    "hg": 0,
    "ag": 3,
    "hst": 10,
    "ast": 5,
    "hs": 19,
    "as": 12,
    "hc": 8,
    "ac": 1,
    "evt_id": "699542",
    "temp": 2024
  },
  {
    "fecha": "2024-07-28T22:00Z",
    "ht": "Cuiabá",
    "at": "Athletico Paranaense",
    "hg": 1,
    "ag": 2,
    "hst": 5,
    "ast": 4,
    "hs": 21,
    "as": 11,
    "hc": 12,
    "ac": 2,
    "evt_id": "699543",
    "temp": 2024
  },
  {
    "fecha": "2024-07-28T19:00Z",
    "ht": "Flamengo",
    "at": "Atlético Goianiense",
    "hg": 2,
    "ag": 0,
    "hst": 6,
    "ast": 3,
    "hs": 12,
    "as": 12,
    "hc": 6,
    "ac": 3,
    "evt_id": "699544",
    "temp": 2024
  },
  {
    "fecha": "2024-07-28T00:30Z",
    "ht": "Fortaleza",
    "at": "São Paulo",
    "hg": 1,
    "ag": 0,
    "hst": 2,
    "ast": 1,
    "hs": 11,
    "as": 12,
    "hc": 3,
    "ac": 10,
    "evt_id": "699545",
    "temp": 2024
  },
  {
    "fecha": "2024-07-28T22:00Z",
    "ht": "Grêmio",
    "at": "Vasco da Gama",
    "hg": 1,
    "ag": 0,
    "hst": 3,
    "ast": 1,
    "hs": 20,
    "as": 13,
    "hc": 8,
    "ac": 3,
    "evt_id": "699546",
    "temp": 2024
  },
  {
    "fecha": "2024-07-27T22:00Z",
    "ht": "Juventude",
    "at": "Criciúma",
    "hg": 1,
    "ag": 2,
    "hst": 5,
    "ast": 7,
    "hs": 12,
    "as": 14,
    "hc": 5,
    "ac": 7,
    "evt_id": "699547",
    "temp": 2024
  },
  {
    "fecha": "2024-07-27T22:00Z",
    "ht": "Palmeiras",
    "at": "Vitória",
    "hg": 0,
    "ag": 2,
    "hst": 3,
    "ast": 3,
    "hs": 21,
    "as": 10,
    "hc": 13,
    "ac": 2,
    "evt_id": "699548",
    "temp": 2024
  },
  {
    "fecha": "2024-07-28T14:00Z",
    "ht": "Red Bull Bragantino",
    "at": "Fluminense",
    "hg": 0,
    "ag": 1,
    "hst": 2,
    "ast": 3,
    "hs": 13,
    "as": 7,
    "hc": 5,
    "ac": 6,
    "evt_id": "699549",
    "temp": 2024
  },
  {
    "fecha": "2024-08-04T19:00Z",
    "ht": "Athletico Paranaense",
    "at": "Grêmio",
    "hg": 0,
    "ag": 2,
    "hst": 3,
    "ast": 7,
    "hs": 18,
    "as": 9,
    "hc": 9,
    "ac": 0,
    "evt_id": "699550",
    "temp": 2024
  },
  {
    "fecha": "2024-08-03T23:00Z",
    "ht": "Atlético Goianiense",
    "at": "Botafogo",
    "hg": 1,
    "ag": 4,
    "hst": 3,
    "ast": 9,
    "hs": 9,
    "as": 13,
    "hc": 3,
    "ac": 8,
    "evt_id": "699551",
    "temp": 2024
  },
  {
    "fecha": "2024-08-04T19:00Z",
    "ht": "Corinthians",
    "at": "Juventude",
    "hg": 1,
    "ag": 1,
    "hst": 10,
    "ast": 3,
    "hs": 34,
    "as": 6,
    "hc": 11,
    "ac": 3,
    "evt_id": "699552",
    "temp": 2024
  },
  {
    "fecha": "2024-08-03T23:00Z",
    "ht": "Criciúma",
    "at": "Atlético-MG",
    "hg": 2,
    "ag": 1,
    "hst": 5,
    "ast": 3,
    "hs": 13,
    "as": 19,
    "hc": 5,
    "ac": 1,
    "evt_id": "699553",
    "temp": 2024
  },
  {
    "fecha": "2024-08-04T19:00Z",
    "ht": "Fluminense",
    "at": "Bahia",
    "hg": 1,
    "ag": 0,
    "hst": 6,
    "ast": 3,
    "hs": 12,
    "as": 11,
    "hc": 3,
    "ac": 3,
    "evt_id": "699554",
    "temp": 2024
  },
  {
    "fecha": "2024-08-03T19:00Z",
    "ht": "Vitória",
    "at": "Cuiabá",
    "hg": 1,
    "ag": 0,
    "hst": 3,
    "ast": 2,
    "hs": 17,
    "as": 9,
    "hc": 4,
    "ac": 5,
    "evt_id": "699555",
    "temp": 2024
  },
  {
    "fecha": "2024-08-04T20:00Z",
    "ht": "Internacional",
    "at": "Palmeiras",
    "hg": 1,
    "ag": 1,
    "hst": 7,
    "ast": 5,
    "hs": 16,
    "as": 17,
    "hc": 4,
    "ac": 11,
    "evt_id": "699556",
    "temp": 2024
  },
  {
    "fecha": "2024-08-04T00:30Z",
    "ht": "São Paulo",
    "at": "Flamengo",
    "hg": 1,
    "ag": 0,
    "hst": 3,
    "ast": 0,
    "hs": 15,
    "as": 8,
    "hc": 8,
    "ac": 3,
    "evt_id": "699557",
    "temp": 2024
  },
  {
    "fecha": "2024-08-03T22:00Z",
    "ht": "Vasco da Gama",
    "at": "Red Bull Bragantino",
    "hg": 2,
    "ag": 2,
    "hst": 3,
    "ast": 3,
    "hs": 11,
    "as": 7,
    "hc": 4,
    "ac": 3,
    "evt_id": "699558",
    "temp": 2024
  },
  {
    "fecha": "2024-08-06T00:00Z",
    "ht": "Cruzeiro",
    "at": "Fortaleza",
    "hg": 1,
    "ag": 2,
    "hst": 7,
    "ast": 4,
    "hs": 15,
    "as": 11,
    "hc": 5,
    "ac": 1,
    "evt_id": "699559",
    "temp": 2024
  },
  {
    "fecha": "2024-08-11T19:00Z",
    "ht": "São Paulo",
    "at": "Atlético Goianiense",
    "hg": 1,
    "ag": 0,
    "hst": 7,
    "ast": 6,
    "hs": 12,
    "as": 13,
    "hc": 3,
    "ac": 2,
    "evt_id": "699560",
    "temp": 2024
  },
  {
    "fecha": "2024-08-11T00:30Z",
    "ht": "Vasco da Gama",
    "at": "Fluminense",
    "hg": 2,
    "ag": 0,
    "hst": 3,
    "ast": 3,
    "hs": 8,
    "as": 12,
    "hc": 6,
    "ac": 3,
    "evt_id": "699561",
    "temp": 2024
  },
  {
    "fecha": "2024-08-11T00:30Z",
    "ht": "Corinthians",
    "at": "Red Bull Bragantino",
    "hg": 1,
    "ag": 1,
    "hst": 5,
    "ast": 6,
    "hs": 19,
    "as": 11,
    "hc": 6,
    "ac": 6,
    "evt_id": "699562",
    "temp": 2024
  },
  {
    "fecha": "2024-08-11T19:00Z",
    "ht": "Bahia",
    "at": "Vitória",
    "hg": 2,
    "ag": 0,
    "hst": 3,
    "ast": 5,
    "hs": 7,
    "as": 14,
    "hc": 3,
    "ac": 7,
    "evt_id": "699563",
    "temp": 2024
  },
  {
    "fecha": "2024-08-11T19:00Z",
    "ht": "Flamengo",
    "at": "Palmeiras",
    "hg": 1,
    "ag": 1,
    "hst": 7,
    "ast": 7,
    "hs": 11,
    "as": 9,
    "hc": 4,
    "ac": 2,
    "evt_id": "699564",
    "temp": 2024
  },
  {
    "fecha": "2024-08-10T19:00Z",
    "ht": "Fortaleza",
    "at": "Criciúma",
    "hg": 1,
    "ag": 0,
    "hst": 4,
    "ast": 2,
    "hs": 16,
    "as": 12,
    "hc": 4,
    "ac": 6,
    "evt_id": "699565",
    "temp": 2024
  },
  {
    "fecha": "2024-08-11T22:00Z",
    "ht": "Internacional",
    "at": "Athletico Paranaense",
    "hg": 2,
    "ag": 2,
    "hst": 4,
    "ast": 5,
    "hs": 23,
    "as": 12,
    "hc": 9,
    "ac": 0,
    "evt_id": "699566",
    "temp": 2024
  },
  {
    "fecha": "2024-08-11T14:00Z",
    "ht": "Juventude",
    "at": "Botafogo",
    "hg": 3,
    "ag": 2,
    "hst": 8,
    "ast": 10,
    "hs": 16,
    "as": 24,
    "hc": 6,
    "ac": 12,
    "evt_id": "699567",
    "temp": 2024
  },
  {
    "fecha": "2024-08-10T22:00Z",
    "ht": "Cuiabá",
    "at": "Grêmio",
    "hg": 1,
    "ag": 3,
    "hst": 3,
    "ast": 6,
    "hs": 15,
    "as": 10,
    "hc": 5,
    "ac": 5,
    "evt_id": "699568",
    "temp": 2024
  },
  {
    "fecha": "2024-08-11T00:30Z",
    "ht": "Cruzeiro",
    "at": "Atlético-MG",
    "hg": 0,
    "ag": 0,
    "hst": 1,
    "ast": 4,
    "hs": 6,
    "as": 12,
    "hc": 4,
    "ac": 4,
    "evt_id": "699569",
    "temp": 2024
  },
  {
    "fecha": "2024-08-18T21:30Z",
    "ht": "Athletico Paranaense",
    "at": "Juventude",
    "hg": 1,
    "ag": 2,
    "hst": 7,
    "ast": 5,
    "hs": 23,
    "as": 8,
    "hc": 10,
    "ac": 4,
    "evt_id": "699570",
    "temp": 2024
  },
  {
    "fecha": "2024-08-18T19:00Z",
    "ht": "Atlético Goianiense",
    "at": "Internacional",
    "hg": 1,
    "ag": 0,
    "hst": 5,
    "ast": 6,
    "hs": 13,
    "as": 19,
    "hc": 4,
    "ac": 7,
    "evt_id": "699571",
    "temp": 2024
  },
  {
    "fecha": "2024-08-17T19:00Z",
    "ht": "Atlético-MG",
    "at": "Cuiabá",
    "hg": 1,
    "ag": 1,
    "hst": 0,
    "ast": 0,
    "hs": 0,
    "as": 0,
    "hc": 0,
    "ac": 0,
    "evt_id": "699572",
    "temp": 2024
  },
  {
    "fecha": "2024-08-18T21:30Z",
    "ht": "Botafogo",
    "at": "Flamengo",
    "hg": 4,
    "ag": 1,
    "hst": 9,
    "ast": 4,
    "hs": 19,
    "as": 10,
    "hc": 5,
    "ac": 2,
    "evt_id": "699573",
    "temp": 2024
  },
  {
    "fecha": "2024-08-18T00:00Z",
    "ht": "Fluminense",
    "at": "Corinthians",
    "hg": 0,
    "ag": 0,
    "hst": 4,
    "ast": 2,
    "hs": 16,
    "as": 8,
    "hc": 6,
    "ac": 2,
    "evt_id": "699574",
    "temp": 2024
  },
  {
    "fecha": "2024-08-19T23:00Z",
    "ht": "Vitória",
    "at": "Cruzeiro",
    "hg": 2,
    "ag": 2,
    "hst": 5,
    "ast": 12,
    "hs": 14,
    "as": 25,
    "hc": 4,
    "ac": 7,
    "evt_id": "699575",
    "temp": 2024
  },
  {
    "fecha": "2024-08-17T19:00Z",
    "ht": "Grêmio",
    "at": "Bahia",
    "hg": 0,
    "ag": 2,
    "hst": 5,
    "ast": 5,
    "hs": 13,
    "as": 12,
    "hc": 1,
    "ac": 5,
    "evt_id": "699576",
    "temp": 2024
  },
  {
    "fecha": "2024-08-18T19:00Z",
    "ht": "Palmeiras",
    "at": "São Paulo",
    "hg": 2,
    "ag": 1,
    "hst": 8,
    "ast": 4,
    "hs": 24,
    "as": 8,
    "hc": 6,
    "ac": 1,
    "evt_id": "699577",
    "temp": 2024
  },
  {
    "fecha": "2024-08-17T21:30Z",
    "ht": "Red Bull Bragantino",
    "at": "Fortaleza",
    "hg": 1,
    "ag": 2,
    "hst": 9,
    "ast": 7,
    "hs": 13,
    "as": 14,
    "hc": 9,
    "ac": 2,
    "evt_id": "699578",
    "temp": 2024
  },
  {
    "fecha": "2024-08-18T19:00Z",
    "ht": "Criciúma",
    "at": "Vasco da Gama",
    "hg": 2,
    "ag": 2,
    "hst": 8,
    "ast": 4,
    "hs": 19,
    "as": 13,
    "hc": 9,
    "ac": 11,
    "evt_id": "699579",
    "temp": 2024
  },
  {
    "fecha": "2024-08-24T19:00Z",
    "ht": "Atlético Goianiense",
    "at": "Juventude",
    "hg": 2,
    "ag": 1,
    "hst": 7,
    "ast": 3,
    "hs": 19,
    "as": 13,
    "hc": 4,
    "ac": 5,
    "evt_id": "699580",
    "temp": 2024
  },
  {
    "fecha": "2024-08-25T00:00Z",
    "ht": "Atlético-MG",
    "at": "Fluminense",
    "hg": 0,
    "ag": 2,
    "hst": 0,
    "ast": 6,
    "hs": 19,
    "as": 8,
    "hc": 5,
    "ac": 2,
    "evt_id": "699581",
    "temp": 2024
  },
  {
    "fecha": "2024-08-25T19:00Z",
    "ht": "Bahia",
    "at": "Botafogo",
    "hg": 0,
    "ag": 0,
    "hst": 7,
    "ast": 5,
    "hs": 17,
    "as": 14,
    "hc": 4,
    "ac": 7,
    "evt_id": "699582",
    "temp": 2024
  },
  {
    "fecha": "2024-08-25T19:00Z",
    "ht": "Criciúma",
    "at": "Grêmio",
    "hg": 0,
    "ag": 1,
    "hst": 4,
    "ast": 4,
    "hs": 19,
    "as": 14,
    "hc": 6,
    "ac": 9,
    "evt_id": "699583",
    "temp": 2024
  },
  {
    "fecha": "2024-08-25T23:00Z",
    "ht": "Flamengo",
    "at": "Red Bull Bragantino",
    "hg": 2,
    "ag": 1,
    "hst": 7,
    "ast": 2,
    "hs": 13,
    "as": 12,
    "hc": 6,
    "ac": 10,
    "evt_id": "699584",
    "temp": 2024
  },
  {
    "fecha": "2024-08-25T19:00Z",
    "ht": "Fortaleza",
    "at": "Corinthians",
    "hg": 1,
    "ag": 0,
    "hst": 5,
    "ast": 4,
    "hs": 8,
    "as": 12,
    "hc": 3,
    "ac": 9,
    "evt_id": "699585",
    "temp": 2024
  },
  {
    "fecha": "2024-08-25T22:00Z",
    "ht": "Internacional",
    "at": "Cruzeiro",
    "hg": 1,
    "ag": 0,
    "hst": 9,
    "ast": 3,
    "hs": 19,
    "as": 5,
    "hc": 12,
    "ac": 3,
    "evt_id": "699586",
    "temp": 2024
  },
  {
    "fecha": "2024-08-24T21:30Z",
    "ht": "Palmeiras",
    "at": "Cuiabá",
    "hg": 5,
    "ag": 0,
    "hst": 9,
    "ast": 3,
    "hs": 14,
    "as": 10,
    "hc": 7,
    "ac": 1,
    "evt_id": "699587",
    "temp": 2024
  },
  {
    "fecha": "2024-08-25T21:30Z",
    "ht": "São Paulo",
    "at": "Vitória",
    "hg": 2,
    "ag": 1,
    "hst": 3,
    "ast": 4,
    "hs": 12,
    "as": 10,
    "hc": 4,
    "ac": 3,
    "evt_id": "699588",
    "temp": 2024
  },
  {
    "fecha": "2024-08-27T00:00Z",
    "ht": "Vasco da Gama",
    "at": "Athletico Paranaense",
    "hg": 2,
    "ag": 1,
    "hst": 5,
    "ast": 4,
    "hs": 7,
    "as": 9,
    "hc": 4,
    "ac": 5,
    "evt_id": "699589",
    "temp": 2024
  },
  {
    "fecha": "2024-09-01T21:30Z",
    "ht": "Athletico Paranaense",
    "at": "Palmeiras",
    "hg": 0,
    "ag": 2,
    "hst": 9,
    "ast": 10,
    "hs": 15,
    "as": 19,
    "hc": 4,
    "ac": 4,
    "evt_id": "699590",
    "temp": 2024
  },
  {
    "fecha": "2024-09-01T00:00Z",
    "ht": "Botafogo",
    "at": "Fortaleza",
    "hg": 2,
    "ag": 0,
    "hst": 7,
    "ast": 1,
    "hs": 22,
    "as": 10,
    "hc": 9,
    "ac": 6,
    "evt_id": "699591",
    "temp": 2024
  },
  {
    "fecha": "2024-09-01T19:00Z",
    "ht": "Corinthians",
    "at": "Flamengo",
    "hg": 2,
    "ag": 1,
    "hst": 4,
    "ast": 3,
    "hs": 13,
    "as": 10,
    "hc": 5,
    "ac": 2,
    "evt_id": "699592",
    "temp": 2024
  },
  {
    "fecha": "2024-09-01T14:00Z",
    "ht": "Cruzeiro",
    "at": "Atlético Goianiense",
    "hg": 3,
    "ag": 1,
    "hst": 6,
    "ast": 4,
    "hs": 11,
    "as": 17,
    "hc": 8,
    "ac": 3,
    "evt_id": "699593",
    "temp": 2024
  },
  {
    "fecha": "2024-08-31T21:30Z",
    "ht": "Cuiabá",
    "at": "Criciúma",
    "hg": 2,
    "ag": 1,
    "hst": 3,
    "ast": 3,
    "hs": 22,
    "as": 12,
    "hc": 5,
    "ac": 5,
    "evt_id": "699594",
    "temp": 2024
  },
  {
    "fecha": "2024-09-01T21:30Z",
    "ht": "Fluminense",
    "at": "São Paulo",
    "hg": 2,
    "ag": 0,
    "hst": 5,
    "ast": 3,
    "hs": 10,
    "as": 14,
    "hc": 5,
    "ac": 4,
    "evt_id": "699595",
    "temp": 2024
  },
  {
    "fecha": "2024-09-01T14:00Z",
    "ht": "Grêmio",
    "at": "Atlético-MG",
    "hg": 2,
    "ag": 3,
    "hst": 5,
    "ast": 13,
    "hs": 11,
    "as": 27,
    "hc": 5,
    "ac": 9,
    "evt_id": "699596",
    "temp": 2024
  },
  {
    "fecha": "2024-09-01T21:30Z",
    "ht": "Juventude",
    "at": "Internacional",
    "hg": 1,
    "ag": 3,
    "hst": 5,
    "ast": 8,
    "hs": 14,
    "as": 18,
    "hc": 6,
    "ac": 4,
    "evt_id": "699597",
    "temp": 2024
  },
  {
    "fecha": "2024-09-01T21:30Z",
    "ht": "Red Bull Bragantino",
    "at": "Bahia",
    "hg": 2,
    "ag": 1,
    "hst": 6,
    "ast": 6,
    "hs": 15,
    "as": 16,
    "hc": 5,
    "ac": 10,
    "evt_id": "699598",
    "temp": 2024
  },
  {
    "fecha": "2024-09-01T21:30Z",
    "ht": "Vitória",
    "at": "Vasco da Gama",
    "hg": 0,
    "ag": 1,
    "hst": 5,
    "ast": 6,
    "hs": 21,
    "as": 9,
    "hc": 10,
    "ac": 3,
    "evt_id": "699599",
    "temp": 2024
  },
  {
    "fecha": "2024-09-14T21:30Z",
    "ht": "Athletico Paranaense",
    "at": "Fortaleza",
    "hg": 1,
    "ag": 1,
    "hst": 9,
    "ast": 3,
    "hs": 30,
    "as": 10,
    "hc": 14,
    "ac": 4,
    "evt_id": "699600",
    "temp": 2024
  },
  {
    "fecha": "2024-09-15T19:00Z",
    "ht": "Red Bull Bragantino",
    "at": "Grêmio",
    "hg": 2,
    "ag": 2,
    "hst": 6,
    "ast": 4,
    "hs": 23,
    "as": 8,
    "hc": 6,
    "ac": 7,
    "evt_id": "699601",
    "temp": 2024
  },
  {
    "fecha": "2024-09-15T19:00Z",
    "ht": "Palmeiras",
    "at": "Criciúma",
    "hg": 5,
    "ag": 0,
    "hst": 8,
    "ast": 5,
    "hs": 14,
    "as": 14,
    "hc": 4,
    "ac": 6,
    "evt_id": "699602",
    "temp": 2024
  },
  {
    "fecha": "2024-09-15T00:00Z",
    "ht": "Botafogo",
    "at": "Corinthians",
    "hg": 2,
    "ag": 1,
    "hst": 10,
    "ast": 2,
    "hs": 21,
    "as": 12,
    "hc": 6,
    "ac": 3,
    "evt_id": "699603",
    "temp": 2024
  },
  {
    "fecha": "2024-09-15T19:00Z",
    "ht": "Juventude",
    "at": "Fluminense",
    "hg": 2,
    "ag": 1,
    "hst": 5,
    "ast": 1,
    "hs": 12,
    "as": 8,
    "hc": 8,
    "ac": 5,
    "evt_id": "699604",
    "temp": 2024
  },
  {
    "fecha": "2024-09-14T19:00Z",
    "ht": "Atlético Goianiense",
    "at": "Vitória",
    "hg": 0,
    "ag": 2,
    "hst": 4,
    "ast": 4,
    "hs": 13,
    "as": 7,
    "hc": 9,
    "ac": 5,
    "evt_id": "699605",
    "temp": 2024
  },
  {
    "fecha": "2024-09-16T23:00Z",
    "ht": "Internacional",
    "at": "Cuiabá",
    "hg": 3,
    "ag": 0,
    "hst": 7,
    "ast": 0,
    "hs": 15,
    "as": 2,
    "hc": 2,
    "ac": 3,
    "evt_id": "699606",
    "temp": 2024
  },
  {
    "fecha": "2024-09-15T21:30Z",
    "ht": "Flamengo",
    "at": "Vasco da Gama",
    "hg": 1,
    "ag": 1,
    "hst": 3,
    "ast": 2,
    "hs": 17,
    "as": 9,
    "hc": 5,
    "ac": 6,
    "evt_id": "699607",
    "temp": 2024
  },
  {
    "fecha": "2024-09-15T21:30Z",
    "ht": "Cruzeiro",
    "at": "São Paulo",
    "hg": 0,
    "ag": 1,
    "hst": 1,
    "ast": 4,
    "hs": 14,
    "as": 14,
    "hc": 7,
    "ac": 7,
    "evt_id": "699608",
    "temp": 2024
  },
  {
    "fecha": "2024-09-15T21:30Z",
    "ht": "Bahia",
    "at": "Atlético-MG",
    "hg": 3,
    "ag": 0,
    "hst": 4,
    "ast": 2,
    "hs": 16,
    "as": 5,
    "hc": 6,
    "ac": 1,
    "evt_id": "699609",
    "temp": 2024
  },
  {
    "fecha": "2024-09-22T19:00Z",
    "ht": "Atlético-MG",
    "at": "Red Bull Bragantino",
    "hg": 3,
    "ag": 0,
    "hst": 8,
    "ast": 3,
    "hs": 13,
    "as": 8,
    "hc": 4,
    "ac": 2,
    "evt_id": "699610",
    "temp": 2024
  },
  {
    "fecha": "2024-09-21T19:00Z",
    "ht": "Corinthians",
    "at": "Atlético Goianiense",
    "hg": 3,
    "ag": 0,
    "hst": 7,
    "ast": 3,
    "hs": 17,
    "as": 14,
    "hc": 6,
    "ac": 2,
    "evt_id": "699611",
    "temp": 2024
  },
  {
    "fecha": "2024-09-22T23:00Z",
    "ht": "Criciúma",
    "at": "Athletico Paranaense",
    "hg": 0,
    "ag": 0,
    "hst": 6,
    "ast": 3,
    "hs": 25,
    "as": 10,
    "hc": 12,
    "ac": 1,
    "evt_id": "699612",
    "temp": 2024
  },
  {
    "fecha": "2024-09-22T21:30Z",
    "ht": "Cuiabá",
    "at": "Cruzeiro",
    "hg": 0,
    "ag": 0,
    "hst": 4,
    "ast": 2,
    "hs": 9,
    "as": 13,
    "hc": 4,
    "ac": 5,
    "evt_id": "699613",
    "temp": 2024
  },
  {
    "fecha": "2024-09-21T21:30Z",
    "ht": "Fluminense",
    "at": "Botafogo",
    "hg": 0,
    "ag": 1,
    "hst": 5,
    "ast": 6,
    "hs": 13,
    "as": 9,
    "hc": 5,
    "ac": 4,
    "evt_id": "699614",
    "temp": 2024
  },
  {
    "fecha": "2024-09-22T00:00Z",
    "ht": "Fortaleza",
    "at": "Bahia",
    "hg": 4,
    "ag": 1,
    "hst": 7,
    "ast": 4,
    "hs": 11,
    "as": 9,
    "hc": 2,
    "ac": 1,
    "evt_id": "699615",
    "temp": 2024
  },
  {
    "fecha": "2024-09-22T21:30Z",
    "ht": "Grêmio",
    "at": "Flamengo",
    "hg": 3,
    "ag": 2,
    "hst": 3,
    "ast": 8,
    "hs": 12,
    "as": 20,
    "hc": 4,
    "ac": 6,
    "evt_id": "699616",
    "temp": 2024
  },
  {
    "fecha": "2024-09-22T21:30Z",
    "ht": "São Paulo",
    "at": "Internacional",
    "hg": 1,
    "ag": 3,
    "hst": 2,
    "ast": 6,
    "hs": 7,
    "as": 14,
    "hc": 2,
    "ac": 4,
    "evt_id": "699617",
    "temp": 2024
  },
  {
    "fecha": "2024-09-22T19:00Z",
    "ht": "Vasco da Gama",
    "at": "Palmeiras",
    "hg": 0,
    "ag": 1,
    "hst": 3,
    "ast": 3,
    "hs": 10,
    "as": 14,
    "hc": 5,
    "ac": 5,
    "evt_id": "699618",
    "temp": 2024
  },
  {
    "fecha": "2024-09-21T19:00Z",
    "ht": "Vitória",
    "at": "Juventude",
    "hg": 1,
    "ag": 0,
    "hst": 2,
    "ast": 2,
    "hs": 13,
    "as": 11,
    "hc": 4,
    "ac": 5,
    "evt_id": "699619",
    "temp": 2024
  },
  {
    "fecha": "2024-09-29T19:00Z",
    "ht": "Atlético Goianiense",
    "at": "Fluminense",
    "hg": 1,
    "ag": 0,
    "hst": 7,
    "ast": 2,
    "hs": 16,
    "as": 13,
    "hc": 4,
    "ac": 3,
    "evt_id": "699620",
    "temp": 2024
  },
  {
    "fecha": "2024-09-29T21:30Z",
    "ht": "Bahia",
    "at": "Criciúma",
    "hg": 1,
    "ag": 0,
    "hst": 7,
    "ast": 1,
    "hs": 21,
    "as": 2,
    "hc": 9,
    "ac": 1,
    "evt_id": "699621",
    "temp": 2024
  },
  {
    "fecha": "2024-09-29T00:00Z",
    "ht": "Botafogo",
    "at": "Grêmio",
    "hg": 0,
    "ag": 0,
    "hst": 3,
    "ast": 4,
    "hs": 15,
    "as": 11,
    "hc": 5,
    "ac": 3,
    "evt_id": "699622",
    "temp": 2024
  },
  {
    "fecha": "2024-09-29T21:30Z",
    "ht": "Cruzeiro",
    "at": "Vasco da Gama",
    "hg": 1,
    "ag": 1,
    "hst": 6,
    "ast": 4,
    "hs": 15,
    "as": 13,
    "hc": 11,
    "ac": 4,
    "evt_id": "699623",
    "temp": 2024
  },
  {
    "fecha": "2024-09-29T23:00Z",
    "ht": "Flamengo",
    "at": "Athletico Paranaense",
    "hg": 1,
    "ag": 0,
    "hst": 0,
    "ast": 0,
    "hs": 0,
    "as": 0,
    "hc": 0,
    "ac": 0,
    "evt_id": "699624",
    "temp": 2024
  },
  {
    "fecha": "2024-09-29T19:00Z",
    "ht": "Fortaleza",
    "at": "Cuiabá",
    "hg": 1,
    "ag": 0,
    "hst": 6,
    "ast": 1,
    "hs": 15,
    "as": 2,
    "hc": 7,
    "ac": 3,
    "evt_id": "699625",
    "temp": 2024
  },
  {
    "fecha": "2024-09-29T21:30Z",
    "ht": "Internacional",
    "at": "Vitória",
    "hg": 3,
    "ag": 1,
    "hst": 5,
    "ast": 4,
    "hs": 10,
    "as": 7,
    "hc": 2,
    "ac": 6,
    "evt_id": "699626",
    "temp": 2024
  },
  {
    "fecha": "2024-09-29T14:00Z",
    "ht": "Juventude",
    "at": "Red Bull Bragantino",
    "hg": 1,
    "ag": 1,
    "hst": 6,
    "ast": 6,
    "hs": 12,
    "as": 15,
    "hc": 4,
    "ac": 5,
    "evt_id": "699627",
    "temp": 2024
  },
  {
    "fecha": "2024-09-28T21:30Z",
    "ht": "Palmeiras",
    "at": "Atlético-MG",
    "hg": 2,
    "ag": 1,
    "hst": 8,
    "ast": 3,
    "hs": 15,
    "as": 6,
    "hc": 7,
    "ac": 3,
    "evt_id": "699628",
    "temp": 2024
  },
  {
    "fecha": "2024-09-29T19:00Z",
    "ht": "São Paulo",
    "at": "Corinthians",
    "hg": 3,
    "ag": 1,
    "hst": 8,
    "ast": 3,
    "hs": 19,
    "as": 11,
    "hc": 7,
    "ac": 2,
    "evt_id": "699629",
    "temp": 2024
  },
  {
    "fecha": "2024-10-05T19:30Z",
    "ht": "Athletico Paranaense",
    "at": "Botafogo",
    "hg": 0,
    "ag": 1,
    "hst": 3,
    "ast": 3,
    "hs": 26,
    "as": 11,
    "hc": 8,
    "ac": 3,
    "evt_id": "699630",
    "temp": 2024
  },
  {
    "fecha": "2024-10-05T19:30Z",
    "ht": "Atlético-MG",
    "at": "Vitória",
    "hg": 2,
    "ag": 2,
    "hst": 3,
    "ast": 3,
    "hs": 14,
    "as": 9,
    "hc": 2,
    "ac": 5,
    "evt_id": "699631",
    "temp": 2024
  },
  {
    "fecha": "2024-10-05T22:00Z",
    "ht": "Bahia",
    "at": "Flamengo",
    "hg": 0,
    "ag": 2,
    "hst": 2,
    "ast": 7,
    "hs": 9,
    "as": 14,
    "hc": 3,
    "ac": 7,
    "evt_id": "699632",
    "temp": 2024
  },
  {
    "fecha": "2024-10-05T22:00Z",
    "ht": "Corinthians",
    "at": "Internacional",
    "hg": 2,
    "ag": 2,
    "hst": 6,
    "ast": 3,
    "hs": 15,
    "as": 9,
    "hc": 9,
    "ac": 9,
    "evt_id": "699633",
    "temp": 2024
  },
  {
    "fecha": "2024-10-05T19:30Z",
    "ht": "Red Bull Bragantino",
    "at": "Palmeiras",
    "hg": 0,
    "ag": 0,
    "hst": 5,
    "ast": 5,
    "hs": 17,
    "as": 14,
    "hc": 1,
    "ac": 3,
    "evt_id": "699634",
    "temp": 2024
  },
  {
    "fecha": "2024-10-05T22:00Z",
    "ht": "Cuiabá",
    "at": "São Paulo",
    "hg": 2,
    "ag": 0,
    "hst": 3,
    "ast": 3,
    "hs": 7,
    "as": 12,
    "hc": 3,
    "ac": 7,
    "evt_id": "699635",
    "temp": 2024
  },
  {
    "fecha": "2024-10-04T00:30Z",
    "ht": "Fluminense",
    "at": "Cruzeiro",
    "hg": 1,
    "ag": 0,
    "hst": 5,
    "ast": 5,
    "hs": 14,
    "as": 13,
    "hc": 2,
    "ac": 2,
    "evt_id": "699636",
    "temp": 2024
  },
  {
    "fecha": "2024-10-05T00:30Z",
    "ht": "Grêmio",
    "at": "Fortaleza",
    "hg": 3,
    "ag": 1,
    "hst": 6,
    "ast": 5,
    "hs": 16,
    "as": 7,
    "hc": 10,
    "ac": 2,
    "evt_id": "699637",
    "temp": 2024
  },
  {
    "fecha": "2024-10-06T00:00Z",
    "ht": "Vasco da Gama",
    "at": "Juventude",
    "hg": 1,
    "ag": 1,
    "hst": 3,
    "ast": 5,
    "hs": 16,
    "as": 17,
    "hc": 3,
    "ac": 6,
    "evt_id": "699638",
    "temp": 2024
  },
  {
    "fecha": "2024-10-03T22:00Z",
    "ht": "Criciúma",
    "at": "Atlético Goianiense",
    "hg": 2,
    "ag": 0,
    "hst": 5,
    "ast": 3,
    "hs": 17,
    "as": 14,
    "hc": 7,
    "ac": 6,
    "evt_id": "699639",
    "temp": 2024
  },
  {
    "fecha": "2024-10-18T22:00Z",
    "ht": "Atlético Goianiense",
    "at": "Cuiabá",
    "hg": 0,
    "ag": 0,
    "hst": 4,
    "ast": 0,
    "hs": 16,
    "as": 6,
    "hc": 8,
    "ac": 4,
    "evt_id": "699640",
    "temp": 2024
  },
  {
    "fecha": "2024-10-18T23:00Z",
    "ht": "Botafogo",
    "at": "Criciúma",
    "hg": 1,
    "ag": 1,
    "hst": 7,
    "ast": 3,
    "hs": 25,
    "as": 6,
    "hc": 9,
    "ac": 1,
    "evt_id": "699641",
    "temp": 2024
  },
  {
    "fecha": "2024-10-17T23:00Z",
    "ht": "Corinthians",
    "at": "Athletico Paranaense",
    "hg": 5,
    "ag": 2,
    "hst": 8,
    "ast": 6,
    "hs": 14,
    "as": 22,
    "hc": 3,
    "ac": 8,
    "evt_id": "699642",
    "temp": 2024
  },
  {
    "fecha": "2024-10-19T00:30Z",
    "ht": "Cruzeiro",
    "at": "Bahia",
    "hg": 1,
    "ag": 1,
    "hst": 3,
    "ast": 4,
    "hs": 11,
    "as": 10,
    "hc": 5,
    "ac": 7,
    "evt_id": "699643",
    "temp": 2024
  },
  {
    "fecha": "2024-10-17T23:00Z",
    "ht": "Flamengo",
    "at": "Fluminense",
    "hg": 0,
    "ag": 2,
    "hst": 5,
    "ast": 3,
    "hs": 20,
    "as": 12,
    "hc": 5,
    "ac": 1,
    "evt_id": "699644",
    "temp": 2024
  },
  {
    "fecha": "2024-10-17T00:45Z",
    "ht": "Fortaleza",
    "at": "Atlético-MG",
    "hg": 1,
    "ag": 1,
    "hst": 1,
    "ast": 5,
    "hs": 14,
    "as": 18,
    "hc": 7,
    "ac": 3,
    "evt_id": "699645",
    "temp": 2024
  },
  {
    "fecha": "2024-10-19T19:00Z",
    "ht": "Internacional",
    "at": "Grêmio",
    "hg": 1,
    "ag": 0,
    "hst": 6,
    "ast": 7,
    "hs": 18,
    "as": 9,
    "hc": 3,
    "ac": 6,
    "evt_id": "699646",
    "temp": 2024
  },
  {
    "fecha": "2024-10-20T23:00Z",
    "ht": "Juventude",
    "at": "Palmeiras",
    "hg": 3,
    "ag": 5,
    "hst": 6,
    "ast": 7,
    "hs": 25,
    "as": 14,
    "hc": 7,
    "ac": 5,
    "evt_id": "699647",
    "temp": 2024
  },
  {
    "fecha": "2024-10-17T00:45Z",
    "ht": "São Paulo",
    "at": "Vasco da Gama",
    "hg": 3,
    "ag": 0,
    "hst": 6,
    "ast": 3,
    "hs": 14,
    "as": 9,
    "hc": 3,
    "ac": 5,
    "evt_id": "699648",
    "temp": 2024
  },
  {
    "fecha": "2024-10-19T19:00Z",
    "ht": "Vitória",
    "at": "Red Bull Bragantino",
    "hg": 1,
    "ag": 0,
    "hst": 3,
    "ast": 1,
    "hs": 11,
    "as": 9,
    "hc": 5,
    "ac": 5,
    "evt_id": "699649",
    "temp": 2024
  },
  {
    "fecha": "2024-10-26T21:30Z",
    "ht": "Athletico Paranaense",
    "at": "Cruzeiro",
    "hg": 3,
    "ag": 0,
    "hst": 6,
    "ast": 0,
    "hs": 19,
    "as": 2,
    "hc": 7,
    "ac": 1,
    "evt_id": "699650",
    "temp": 2024
  },
  {
    "fecha": "2024-10-26T22:00Z",
    "ht": "Atlético-MG",
    "at": "Internacional",
    "hg": 1,
    "ag": 3,
    "hst": 0,
    "ast": 0,
    "hs": 0,
    "as": 0,
    "hc": 0,
    "ac": 0,
    "evt_id": "699651",
    "temp": 2024
  },
  {
    "fecha": "2024-10-27T00:00Z",
    "ht": "Criciúma",
    "at": "São Paulo",
    "hg": 1,
    "ag": 1,
    "hst": 3,
    "ast": 3,
    "hs": 10,
    "as": 16,
    "hc": 6,
    "ac": 7,
    "evt_id": "699652",
    "temp": 2024
  },
  {
    "fecha": "2024-10-28T22:00Z",
    "ht": "Cuiabá",
    "at": "Corinthians",
    "hg": 0,
    "ag": 1,
    "hst": 5,
    "ast": 3,
    "hs": 13,
    "as": 9,
    "hc": 5,
    "ac": 2,
    "evt_id": "699653",
    "temp": 2024
  },
  {
    "fecha": "2024-10-26T19:30Z",
    "ht": "Flamengo",
    "at": "Juventude",
    "hg": 4,
    "ag": 2,
    "hst": 10,
    "ast": 3,
    "hs": 20,
    "as": 5,
    "hc": 8,
    "ac": 1,
    "evt_id": "699654",
    "temp": 2024
  },
  {
    "fecha": "2024-10-26T19:30Z",
    "ht": "Grêmio",
    "at": "Atlético Goianiense",
    "hg": 3,
    "ag": 1,
    "hst": 5,
    "ast": 5,
    "hs": 11,
    "as": 13,
    "hc": 4,
    "ac": 3,
    "evt_id": "699655",
    "temp": 2024
  },
  {
    "fecha": "2024-10-26T19:30Z",
    "ht": "Palmeiras",
    "at": "Fortaleza",
    "hg": 2,
    "ag": 2,
    "hst": 6,
    "ast": 3,
    "hs": 16,
    "as": 11,
    "hc": 3,
    "ac": 3,
    "evt_id": "699656",
    "temp": 2024
  },
  {
    "fecha": "2024-10-26T22:00Z",
    "ht": "Red Bull Bragantino",
    "at": "Botafogo",
    "hg": 0,
    "ag": 1,
    "hst": 1,
    "ast": 5,
    "hs": 6,
    "as": 19,
    "hc": 3,
    "ac": 6,
    "evt_id": "699657",
    "temp": 2024
  },
  {
    "fecha": "2024-10-29T00:00Z",
    "ht": "Vasco da Gama",
    "at": "Bahia",
    "hg": 3,
    "ag": 2,
    "hst": 8,
    "ast": 7,
    "hs": 15,
    "as": 12,
    "hc": 2,
    "ac": 4,
    "evt_id": "699658",
    "temp": 2024
  },
  {
    "fecha": "2024-10-26T19:30Z",
    "ht": "Vitória",
    "at": "Fluminense",
    "hg": 2,
    "ag": 1,
    "hst": 3,
    "ast": 4,
    "hs": 12,
    "as": 11,
    "hc": 7,
    "ac": 5,
    "evt_id": "699659",
    "temp": 2024
  },
  {
    "fecha": "2024-11-02T21:30Z",
    "ht": "Athletico Paranaense",
    "at": "Vitória",
    "hg": 1,
    "ag": 2,
    "hst": 6,
    "ast": 5,
    "hs": 25,
    "as": 11,
    "hc": 9,
    "ac": 3,
    "evt_id": "699660",
    "temp": 2024
  },
  {
    "fecha": "2024-11-07T00:00Z",
    "ht": "Atlético Goianiense",
    "at": "Atlético-MG",
    "hg": 1,
    "ag": 0,
    "hst": 3,
    "ast": 5,
    "hs": 13,
    "as": 12,
    "hc": 4,
    "ac": 7,
    "evt_id": "699661",
    "temp": 2024
  },
  {
    "fecha": "2024-11-06T00:30Z",
    "ht": "Bahia",
    "at": "São Paulo",
    "hg": 0,
    "ag": 3,
    "hst": 6,
    "ast": 4,
    "hs": 24,
    "as": 10,
    "hc": 10,
    "ac": 3,
    "evt_id": "699662",
    "temp": 2024
  },
  {
    "fecha": "2024-11-06T00:30Z",
    "ht": "Botafogo",
    "at": "Vasco da Gama",
    "hg": 3,
    "ag": 0,
    "hst": 5,
    "ast": 3,
    "hs": 20,
    "as": 11,
    "hc": 7,
    "ac": 4,
    "evt_id": "699663",
    "temp": 2024
  },
  {
    "fecha": "2024-11-02T21:30Z",
    "ht": "Juventude",
    "at": "Fortaleza",
    "hg": 0,
    "ag": 3,
    "hst": 6,
    "ast": 4,
    "hs": 17,
    "as": 11,
    "hc": 5,
    "ac": 3,
    "evt_id": "699664",
    "temp": 2024
  },
  {
    "fecha": "2024-11-07T00:00Z",
    "ht": "Cruzeiro",
    "at": "Flamengo",
    "hg": 0,
    "ag": 1,
    "hst": 5,
    "ast": 2,
    "hs": 15,
    "as": 11,
    "hc": 7,
    "ac": 4,
    "evt_id": "699665",
    "temp": 2024
  },
  {
    "fecha": "2024-11-02T00:00Z",
    "ht": "Fluminense",
    "at": "Grêmio",
    "hg": 2,
    "ag": 2,
    "hst": 7,
    "ast": 4,
    "hs": 18,
    "as": 7,
    "hc": 8,
    "ac": 2,
    "evt_id": "699666",
    "temp": 2024
  },
  {
    "fecha": "2024-11-06T00:30Z",
    "ht": "Internacional",
    "at": "Criciúma",
    "hg": 2,
    "ag": 0,
    "hst": 9,
    "ast": 4,
    "hs": 20,
    "as": 5,
    "hc": 7,
    "ac": 3,
    "evt_id": "699667",
    "temp": 2024
  },
  {
    "fecha": "2024-11-02T19:00Z",
    "ht": "Red Bull Bragantino",
    "at": "Cuiabá",
    "hg": 0,
    "ag": 0,
    "hst": 4,
    "ast": 1,
    "hs": 18,
    "as": 7,
    "hc": 12,
    "ac": 5,
    "evt_id": "699668",
    "temp": 2024
  },
  {
    "fecha": "2024-11-04T23:00Z",
    "ht": "Corinthians",
    "at": "Palmeiras",
    "hg": 2,
    "ag": 0,
    "hst": 4,
    "ast": 4,
    "hs": 6,
    "as": 17,
    "hc": 2,
    "ac": 9,
    "evt_id": "699669",
    "temp": 2024
  },
  {
    "fecha": "2024-11-09T22:00Z",
    "ht": "Atlético Goianiense",
    "at": "Red Bull Bragantino",
    "hg": 0,
    "ag": 0,
    "hst": 4,
    "ast": 7,
    "hs": 10,
    "as": 17,
    "hc": 7,
    "ac": 6,
    "evt_id": "699670",
    "temp": 2024
  },
  {
    "fecha": "2024-11-09T19:30Z",
    "ht": "Botafogo",
    "at": "Cuiabá",
    "hg": 0,
    "ag": 0,
    "hst": 5,
    "ast": 2,
    "hs": 28,
    "as": 4,
    "hc": 8,
    "ac": 1,
    "evt_id": "699671",
    "temp": 2024
  },
  {
    "fecha": "2024-11-09T22:00Z",
    "ht": "Cruzeiro",
    "at": "Criciúma",
    "hg": 2,
    "ag": 1,
    "hst": 9,
    "ast": 7,
    "hs": 26,
    "as": 12,
    "hc": 6,
    "ac": 5,
    "evt_id": "699672",
    "temp": 2024
  },
  {
    "fecha": "2024-11-13T23:00Z",
    "ht": "Flamengo",
    "at": "Atlético-MG",
    "hg": 0,
    "ag": 0,
    "hst": 6,
    "ast": 2,
    "hs": 25,
    "as": 16,
    "hc": 7,
    "ac": 4,
    "evt_id": "699673",
    "temp": 2024
  },
  {
    "fecha": "2024-11-09T22:00Z",
    "ht": "Fortaleza",
    "at": "Vasco da Gama",
    "hg": 3,
    "ag": 0,
    "hst": 8,
    "ast": 2,
    "hs": 14,
    "as": 4,
    "hc": 5,
    "ac": 1,
    "evt_id": "699674",
    "temp": 2024
  },
  {
    "fecha": "2024-11-08T22:00Z",
    "ht": "Internacional",
    "at": "Fluminense",
    "hg": 2,
    "ag": 0,
    "hst": 7,
    "ast": 2,
    "hs": 17,
    "as": 9,
    "hc": 4,
    "ac": 4,
    "evt_id": "699675",
    "temp": 2024
  },
  {
    "fecha": "2024-11-09T22:00Z",
    "ht": "Juventude",
    "at": "Bahia",
    "hg": 2,
    "ag": 1,
    "hst": 8,
    "ast": 3,
    "hs": 20,
    "as": 8,
    "hc": 7,
    "ac": 2,
    "evt_id": "699676",
    "temp": 2024
  },
  {
    "fecha": "2024-11-09T00:30Z",
    "ht": "Palmeiras",
    "at": "Grêmio",
    "hg": 1,
    "ag": 0,
    "hst": 14,
    "ast": 0,
    "hs": 33,
    "as": 6,
    "hc": 14,
    "ac": 1,
    "evt_id": "699677",
    "temp": 2024
  },
  {
    "fecha": "2024-11-10T00:00Z",
    "ht": "São Paulo",
    "at": "Athletico Paranaense",
    "hg": 2,
    "ag": 1,
    "hst": 3,
    "ast": 3,
    "hs": 10,
    "as": 9,
    "hc": 5,
    "ac": 6,
    "evt_id": "699678",
    "temp": 2024
  },
  {
    "fecha": "2024-11-09T19:30Z",
    "ht": "Vitória",
    "at": "Corinthians",
    "hg": 1,
    "ag": 2,
    "hst": 2,
    "ast": 7,
    "hs": 9,
    "as": 13,
    "hc": 14,
    "ac": 4,
    "evt_id": "699679",
    "temp": 2024
  },
  {
    "fecha": "2024-11-20T19:30Z",
    "ht": "Athletico Paranaense",
    "at": "Atlético Goianiense",
    "hg": 2,
    "ag": 0,
    "hst": 8,
    "ast": 6,
    "hs": 11,
    "as": 20,
    "hc": 6,
    "ac": 9,
    "evt_id": "699680",
    "temp": 2024
  },
  {
    "fecha": "2024-11-21T00:30Z",
    "ht": "Atlético-MG",
    "at": "Botafogo",
    "hg": 0,
    "ag": 0,
    "hst": 0,
    "ast": 4,
    "hs": 3,
    "as": 27,
    "hc": 1,
    "ac": 11,
    "evt_id": "699681",
    "temp": 2024
  },
  {
    "fecha": "2024-11-20T21:00Z",
    "ht": "Bahia",
    "at": "Palmeiras",
    "hg": 1,
    "ag": 2,
    "hst": 5,
    "ast": 2,
    "hs": 17,
    "as": 11,
    "hc": 4,
    "ac": 5,
    "evt_id": "699682",
    "temp": 2024
  },
  {
    "fecha": "2024-11-20T14:00Z",
    "ht": "Corinthians",
    "at": "Cruzeiro",
    "hg": 2,
    "ag": 1,
    "hst": 9,
    "ast": 2,
    "hs": 13,
    "as": 8,
    "hc": 3,
    "ac": 4,
    "evt_id": "699683",
    "temp": 2024
  },
  {
    "fecha": "2024-11-20T19:30Z",
    "ht": "Criciúma",
    "at": "Vitória",
    "hg": 0,
    "ag": 1,
    "hst": 1,
    "ast": 3,
    "hs": 13,
    "as": 14,
    "hc": 6,
    "ac": 5,
    "evt_id": "699684",
    "temp": 2024
  },
  {
    "fecha": "2024-11-20T22:00Z",
    "ht": "Cuiabá",
    "at": "Flamengo",
    "hg": 1,
    "ag": 2,
    "hst": 3,
    "ast": 7,
    "hs": 5,
    "as": 19,
    "hc": 4,
    "ac": 10,
    "evt_id": "699685",
    "temp": 2024
  },
  {
    "fecha": "2024-11-23T00:30Z",
    "ht": "Fluminense",
    "at": "Fortaleza",
    "hg": 2,
    "ag": 2,
    "hst": 5,
    "ast": 5,
    "hs": 10,
    "as": 11,
    "hc": 8,
    "ac": 4,
    "evt_id": "699686",
    "temp": 2024
  },
  {
    "fecha": "2024-11-20T22:00Z",
    "ht": "Grêmio",
    "at": "Juventude",
    "hg": 2,
    "ag": 2,
    "hst": 0,
    "ast": 0,
    "hs": 0,
    "as": 0,
    "hc": 0,
    "ac": 0,
    "evt_id": "699687",
    "temp": 2024
  },
  {
    "fecha": "2024-11-20T19:30Z",
    "ht": "Red Bull Bragantino",
    "at": "São Paulo",
    "hg": 1,
    "ag": 1,
    "hst": 5,
    "ast": 2,
    "hs": 18,
    "as": 10,
    "hc": 1,
    "ac": 1,
    "evt_id": "699688",
    "temp": 2024
  },
  {
    "fecha": "2024-11-21T23:00Z",
    "ht": "Vasco da Gama",
    "at": "Internacional",
    "hg": 0,
    "ag": 1,
    "hst": 2,
    "ast": 7,
    "hs": 12,
    "as": 16,
    "hc": 8,
    "ac": 3,
    "evt_id": "699689",
    "temp": 2024
  },
  {
    "fecha": "2024-11-23T22:30Z",
    "ht": "Atlético Goianiense",
    "at": "Palmeiras",
    "hg": 0,
    "ag": 1,
    "hst": 2,
    "ast": 3,
    "hs": 9,
    "as": 10,
    "hc": 4,
    "ac": 2,
    "evt_id": "699690",
    "temp": 2024
  },
  {
    "fecha": "2024-11-24T19:00Z",
    "ht": "Bahia",
    "at": "Athletico Paranaense",
    "hg": 1,
    "ag": 1,
    "hst": 8,
    "ast": 3,
    "hs": 25,
    "as": 6,
    "hc": 11,
    "ac": 1,
    "evt_id": "699691",
    "temp": 2024
  },
  {
    "fecha": "2024-11-23T22:30Z",
    "ht": "Botafogo",
    "at": "Vitória",
    "hg": 1,
    "ag": 1,
    "hst": 9,
    "ast": 4,
    "hs": 26,
    "as": 10,
    "hc": 10,
    "ac": 0,
    "evt_id": "699692",
    "temp": 2024
  },
  {
    "fecha": "2024-11-24T19:00Z",
    "ht": "Corinthians",
    "at": "Vasco da Gama",
    "hg": 3,
    "ag": 1,
    "hst": 8,
    "ast": 2,
    "hs": 23,
    "as": 8,
    "hc": 7,
    "ac": 6,
    "evt_id": "699693",
    "temp": 2024
  },
  {
    "fecha": "2024-11-28T00:00Z",
    "ht": "Cruzeiro",
    "at": "Grêmio",
    "hg": 1,
    "ag": 1,
    "hst": 3,
    "ast": 4,
    "hs": 19,
    "as": 9,
    "hc": 5,
    "ac": 1,
    "evt_id": "699694",
    "temp": 2024
  },
  {
    "fecha": "2024-11-26T22:00Z",
    "ht": "Fluminense",
    "at": "Criciúma",
    "hg": 0,
    "ag": 0,
    "hst": 3,
    "ast": 3,
    "hs": 19,
    "as": 10,
    "hc": 9,
    "ac": 4,
    "evt_id": "699695",
    "temp": 2024
  },
  {
    "fecha": "2024-11-26T23:00Z",
    "ht": "Fortaleza",
    "at": "Flamengo",
    "hg": 0,
    "ag": 0,
    "hst": 1,
    "ast": 4,
    "hs": 7,
    "as": 16,
    "hc": 5,
    "ac": 5,
    "evt_id": "699696",
    "temp": 2024
  },
  {
    "fecha": "2024-11-24T19:00Z",
    "ht": "Internacional",
    "at": "Red Bull Bragantino",
    "hg": 4,
    "ag": 1,
    "hst": 7,
    "ast": 1,
    "hs": 16,
    "as": 5,
    "hc": 8,
    "ac": 4,
    "evt_id": "699697",
    "temp": 2024
  },
  {
    "fecha": "2024-11-23T22:30Z",
    "ht": "Juventude",
    "at": "Cuiabá",
    "hg": 1,
    "ag": 1,
    "hst": 4,
    "ast": 1,
    "hs": 19,
    "as": 7,
    "hc": 6,
    "ac": 5,
    "evt_id": "699698",
    "temp": 2024
  },
  {
    "fecha": "2024-11-24T00:30Z",
    "ht": "São Paulo",
    "at": "Atlético-MG",
    "hg": 2,
    "ag": 2,
    "hst": 4,
    "ast": 3,
    "hs": 13,
    "as": 3,
    "hc": 7,
    "ac": 1,
    "evt_id": "699699",
    "temp": 2024
  },
  {
    "fecha": "2024-12-01T21:30Z",
    "ht": "Athletico Paranaense",
    "at": "Fluminense",
    "hg": 1,
    "ag": 1,
    "hst": 4,
    "ast": 4,
    "hs": 16,
    "as": 15,
    "hc": 3,
    "ac": 8,
    "evt_id": "699700",
    "temp": 2024
  },
  {
    "fecha": "2024-11-27T00:30Z",
    "ht": "Atlético-MG",
    "at": "Juventude",
    "hg": 2,
    "ag": 3,
    "hst": 6,
    "ast": 7,
    "hs": 21,
    "as": 13,
    "hc": 9,
    "ac": 5,
    "evt_id": "699701",
    "temp": 2024
  },
  {
    "fecha": "2024-11-30T22:30Z",
    "ht": "Criciúma",
    "at": "Corinthians",
    "hg": 2,
    "ag": 4,
    "hst": 4,
    "ast": 11,
    "hs": 12,
    "as": 19,
    "hc": 3,
    "ac": 7,
    "evt_id": "699702",
    "temp": 2024
  },
  {
    "fecha": "2024-11-30T22:30Z",
    "ht": "Cuiabá",
    "at": "Bahia",
    "hg": 1,
    "ag": 2,
    "hst": 2,
    "ast": 3,
    "hs": 11,
    "as": 12,
    "hc": 3,
    "ac": 4,
    "evt_id": "699703",
    "temp": 2024
  },
  {
    "fecha": "2024-12-01T19:00Z",
    "ht": "Grêmio",
    "at": "São Paulo",
    "hg": 2,
    "ag": 1,
    "hst": 8,
    "ast": 2,
    "hs": 16,
    "as": 7,
    "hc": 10,
    "ac": 6,
    "evt_id": "699704",
    "temp": 2024
  },
  {
    "fecha": "2024-12-01T21:30Z",
    "ht": "Vitória",
    "at": "Fortaleza",
    "hg": 2,
    "ag": 0,
    "hst": 8,
    "ast": 2,
    "hs": 19,
    "as": 11,
    "hc": 7,
    "ac": 8,
    "evt_id": "699705",
    "temp": 2024
  },
  {
    "fecha": "2024-11-27T00:30Z",
    "ht": "Palmeiras",
    "at": "Botafogo",
    "hg": 1,
    "ag": 3,
    "hst": 5,
    "ast": 7,
    "hs": 19,
    "as": 13,
    "hc": 5,
    "ac": 7,
    "evt_id": "699706",
    "temp": 2024
  },
  {
    "fecha": "2024-12-01T21:30Z",
    "ht": "Red Bull Bragantino",
    "at": "Cruzeiro",
    "hg": 1,
    "ag": 1,
    "hst": 2,
    "ast": 2,
    "hs": 7,
    "as": 22,
    "hc": 6,
    "ac": 10,
    "evt_id": "699707",
    "temp": 2024
  },
  {
    "fecha": "2024-12-01T00:30Z",
    "ht": "Vasco da Gama",
    "at": "Atlético Goianiense",
    "hg": 2,
    "ag": 2,
    "hst": 0,
    "ast": 0,
    "hs": 0,
    "as": 0,
    "hc": 0,
    "ac": 0,
    "evt_id": "699708",
    "temp": 2024
  },
  {
    "fecha": "2024-12-01T19:00Z",
    "ht": "Flamengo",
    "at": "Internacional",
    "hg": 3,
    "ag": 2,
    "hst": 10,
    "ast": 6,
    "hs": 17,
    "as": 12,
    "hc": 6,
    "ac": 4,
    "evt_id": "699709",
    "temp": 2024
  },
  {
    "fecha": "2024-12-05T23:00Z",
    "ht": "Athletico Paranaense",
    "at": "Red Bull Bragantino",
    "hg": 1,
    "ag": 2,
    "hst": 7,
    "ast": 4,
    "hs": 22,
    "as": 13,
    "hc": 6,
    "ac": 5,
    "evt_id": "699710",
    "temp": 2024
  },
  {
    "fecha": "2024-12-05T00:30Z",
    "ht": "Atlético Goianiense",
    "at": "Fortaleza",
    "hg": 3,
    "ag": 1,
    "hst": 10,
    "ast": 4,
    "hs": 27,
    "as": 12,
    "hc": 5,
    "ac": 3,
    "evt_id": "699711",
    "temp": 2024
  },
  {
    "fecha": "2024-12-03T23:00Z",
    "ht": "Corinthians",
    "at": "Bahia",
    "hg": 3,
    "ag": 0,
    "hst": 7,
    "ast": 2,
    "hs": 18,
    "as": 12,
    "hc": 7,
    "ac": 4,
    "evt_id": "699712",
    "temp": 2024
  },
  {
    "fecha": "2024-12-04T23:00Z",
    "ht": "Criciúma",
    "at": "Flamengo",
    "hg": 0,
    "ag": 3,
    "hst": 4,
    "ast": 7,
    "hs": 16,
    "as": 12,
    "hc": 7,
    "ac": 3,
    "evt_id": "699713",
    "temp": 2024
  },
  {
    "fecha": "2024-12-05T00:30Z",
    "ht": "Cruzeiro",
    "at": "Palmeiras",
    "hg": 1,
    "ag": 2,
    "hst": 3,
    "ast": 12,
    "hs": 9,
    "as": 31,
    "hc": 7,
    "ac": 6,
    "evt_id": "699714",
    "temp": 2024
  },
  {
    "fecha": "2024-12-05T23:00Z",
    "ht": "Fluminense",
    "at": "Cuiabá",
    "hg": 1,
    "ag": 0,
    "hst": 6,
    "ast": 3,
    "hs": 24,
    "as": 3,
    "hc": 10,
    "ac": 3,
    "evt_id": "699715",
    "temp": 2024
  },
  {
    "fecha": "2024-12-05T00:30Z",
    "ht": "Internacional",
    "at": "Botafogo",
    "hg": 0,
    "ag": 1,
    "hst": 6,
    "ast": 1,
    "hs": 14,
    "as": 2,
    "hc": 10,
    "ac": 1,
    "evt_id": "699716",
    "temp": 2024
  },
  {
    "fecha": "2024-12-04T23:00Z",
    "ht": "São Paulo",
    "at": "Juventude",
    "hg": 1,
    "ag": 2,
    "hst": 2,
    "ast": 7,
    "hs": 10,
    "as": 13,
    "hc": 12,
    "ac": 2,
    "evt_id": "699717",
    "temp": 2024
  },
  {
    "fecha": "2024-12-04T22:00Z",
    "ht": "Vasco da Gama",
    "at": "Atlético-MG",
    "hg": 2,
    "ag": 0,
    "hst": 4,
    "ast": 3,
    "hs": 11,
    "as": 11,
    "hc": 3,
    "ac": 6,
    "evt_id": "699718",
    "temp": 2024
  },
  {
    "fecha": "2024-12-04T23:00Z",
    "ht": "Vitória",
    "at": "Grêmio",
    "hg": 1,
    "ag": 1,
    "hst": 5,
    "ast": 2,
    "hs": 25,
    "as": 7,
    "hc": 7,
    "ac": 1,
    "evt_id": "699719",
    "temp": 2024
  },
  {
    "fecha": "2024-12-08T19:00Z",
    "ht": "Atlético-MG",
    "at": "Athletico Paranaense",
    "hg": 1,
    "ag": 0,
    "hst": 7,
    "ast": 4,
    "hs": 14,
    "as": 7,
    "hc": 5,
    "ac": 4,
    "evt_id": "699720",
    "temp": 2024
  },
  {
    "fecha": "2024-12-08T19:00Z",
    "ht": "Bahia",
    "at": "Atlético Goianiense",
    "hg": 2,
    "ag": 0,
    "hst": 5,
    "ast": 2,
    "hs": 17,
    "as": 13,
    "hc": 4,
    "ac": 5,
    "evt_id": "699721",
    "temp": 2024
  },
  {
    "fecha": "2024-12-08T19:00Z",
    "ht": "Botafogo",
    "at": "São Paulo",
    "hg": 2,
    "ag": 1,
    "hst": 8,
    "ast": 1,
    "hs": 17,
    "as": 5,
    "hc": 3,
    "ac": 0,
    "evt_id": "699722",
    "temp": 2024
  },
  {
    "fecha": "2024-12-08T19:00Z",
    "ht": "Cuiabá",
    "at": "Vasco da Gama",
    "hg": 1,
    "ag": 2,
    "hst": 4,
    "ast": 4,
    "hs": 11,
    "as": 11,
    "hc": 2,
    "ac": 5,
    "evt_id": "699723",
    "temp": 2024
  },
  {
    "fecha": "2024-12-08T19:00Z",
    "ht": "Fortaleza",
    "at": "Internacional",
    "hg": 3,
    "ag": 0,
    "hst": 5,
    "ast": 1,
    "hs": 10,
    "as": 11,
    "hc": 4,
    "ac": 3,
    "evt_id": "699724",
    "temp": 2024
  },
  {
    "fecha": "2024-12-08T19:00Z",
    "ht": "Red Bull Bragantino",
    "at": "Criciúma",
    "hg": 5,
    "ag": 1,
    "hst": 8,
    "ast": 4,
    "hs": 18,
    "as": 7,
    "hc": 6,
    "ac": 8,
    "evt_id": "699725",
    "temp": 2024
  },
  {
    "fecha": "2024-12-08T19:00Z",
    "ht": "Grêmio",
    "at": "Corinthians",
    "hg": 0,
    "ag": 3,
    "hst": 5,
    "ast": 6,
    "hs": 18,
    "as": 19,
    "hc": 6,
    "ac": 7,
    "evt_id": "699726",
    "temp": 2024
  },
  {
    "fecha": "2024-12-08T19:00Z",
    "ht": "Juventude",
    "at": "Cruzeiro",
    "hg": 0,
    "ag": 1,
    "hst": 7,
    "ast": 1,
    "hs": 21,
    "as": 8,
    "hc": 8,
    "ac": 1,
    "evt_id": "699727",
    "temp": 2024
  },
  {
    "fecha": "2024-12-08T19:00Z",
    "ht": "Palmeiras",
    "at": "Fluminense",
    "hg": 0,
    "ag": 1,
    "hst": 3,
    "ast": 5,
    "hs": 11,
    "as": 7,
    "hc": 11,
    "ac": 2,
    "evt_id": "699728",
    "temp": 2024
  },
  {
    "fecha": "2024-12-08T19:00Z",
    "ht": "Flamengo",
    "at": "Vitória",
    "hg": 2,
    "ag": 2,
    "hst": 4,
    "ast": 5,
    "hs": 23,
    "as": 12,
    "hc": 6,
    "ac": 4,
    "evt_id": "699729",
    "temp": 2024
  }
]