[
  {
    "fecha": "2022-11-05T15:30Z",
    "ht": "Universidad de Chile",
    "at": "Cobresal",
    "hg": 3,
    "ag": 4,
    "hst": 8,
    "ast": 7,
    "hs": 15,
    "as": 22,
    "hc": 5,
    "ac": 6,
    "evt_id": "629226",
    "temp": 2022
  },
  {
    "fecha": "2022-11-06T19:00Z",
    "ht": "Ñublense",
    "at": "Colo Colo",
    "hg": 1,
    "ag": 1,
    "hst": 4,
    "ast": 4,
    "hs": 12,
    "as": 21,
    "hc": 4,
    "ac": 9,
    "evt_id": "629227",
    "temp": 2022
  },
  {
    "fecha": "2022-11-06T19:00Z",
    "ht": "Coquimbo Unido",
    "at": "Curicó Unido",
    "hg": 1,
    "ag": 1,
    "hst": 6,
    "ast": 3,
    "hs": 12,
    "as": 10,
    "hc": 6,
    "ac": 1,
    "evt_id": "629228",
    "temp": 2022
  },
  {
    "fecha": "2022-11-05T15:30Z",
    "ht": "O'Higgins",
    "at": "Everton CD",
    "hg": 2,
    "ag": 0,
    "hst": 5,
    "ast": 6,
    "hs": 14,
    "as": 14,
    "hc": 6,
    "ac": 6,
    "evt_id": "629229",
    "temp": 2022
  },
  {
    "fecha": "2022-11-06T19:00Z",
    "ht": "Audax Italiano",
    "at": "La Serena",
    "hg": 3,
    "ag": 0,
    "hst": 9,
    "ast": 4,
    "hs": 19,
    "as": 13,
    "hc": 7,
    "ac": 7,
    "evt_id": "629230",
    "temp": 2022
  },
  {
    "fecha": "2022-11-05T15:30Z",
    "ht": "Palestino",
    "at": "Huachipato",
    "hg": 5,
    "ag": 0,
    "hst": 11,
    "ast": 0,
    "hs": 23,
    "as": 6,
    "hc": 2,
    "ac": 3,
    "evt_id": "629231",
    "temp": 2022
  },
  {
    "fecha": "2022-11-06T19:00Z",
    "ht": "Antofagasta",
    "at": "Universidad Católica",
    "hg": 0,
    "ag": 2,
    "hst": 5,
    "ast": 4,
    "hs": 15,
    "as": 9,
    "hc": 8,
    "ac": 8,
    "evt_id": "629232",
    "temp": 2022
  },
  {
    "fecha": "2022-11-06T22:00Z",
    "ht": "Unión La Calera",
    "at": "Unión Española",
    "hg": 2,
    "ag": 1,
    "hst": 3,
    "ast": 3,
    "hs": 10,
    "as": 15,
    "hc": 3,
    "ac": 8,
    "evt_id": "629233",
    "temp": 2022
  },
  {
    "fecha": "2022-10-30T18:00Z",
    "ht": "Everton CD",
    "at": "Antofagasta",
    "hg": 3,
    "ag": 0,
    "hst": 5,
    "ast": 3,
    "hs": 19,
    "as": 8,
    "hc": 6,
    "ac": 2,
    "evt_id": "629234",
    "temp": 2022
  },
  {
    "fecha": "2022-10-31T23:00Z",
    "ht": "Universidad Católica",
    "at": "Audax Italiano",
    "hg": 0,
    "ag": 0,
    "hst": 2,
    "ast": 4,
    "hs": 13,
    "as": 14,
    "hc": 1,
    "ac": 7,
    "evt_id": "629235",
    "temp": 2022
  },
  {
    "fecha": "2022-10-30T18:00Z",
    "ht": "Unión Española",
    "at": "Coquimbo Unido",
    "hg": 1,
    "ag": 3,
    "hst": 4,
    "ast": 6,
    "hs": 8,
    "as": 16,
    "hc": 1,
    "ac": 4,
    "evt_id": "629236",
    "temp": 2022
  },
  {
    "fecha": "2022-10-30T20:30Z",
    "ht": "Colo Colo",
    "at": "O'Higgins",
    "hg": 2,
    "ag": 0,
    "hst": 3,
    "ast": 4,
    "hs": 11,
    "as": 13,
    "hc": 3,
    "ac": 10,
    "evt_id": "629237",
    "temp": 2022
  },
  {
    "fecha": "2022-10-29T23:00Z",
    "ht": "Cobresal",
    "at": "Palestino",
    "hg": 1,
    "ag": 0,
    "hst": 2,
    "ast": 2,
    "hs": 10,
    "as": 12,
    "hc": 4,
    "ac": 7,
    "evt_id": "629238",
    "temp": 2022
  },
  {
    "fecha": "2022-10-30T15:30Z",
    "ht": "Huachipato",
    "at": "Universidad de Chile",
    "hg": 4,
    "ag": 0,
    "hst": 6,
    "ast": 2,
    "hs": 15,
    "as": 14,
    "hc": 1,
    "ac": 5,
    "evt_id": "629239",
    "temp": 2022
  },
  {
    "fecha": "2022-10-30T18:00Z",
    "ht": "La Serena",
    "at": "Unión La Calera",
    "hg": 2,
    "ag": 1,
    "hst": 4,
    "ast": 3,
    "hs": 19,
    "as": 8,
    "hc": 4,
    "ac": 1,
    "evt_id": "629240",
    "temp": 2022
  },
  {
    "fecha": "2022-10-31T20:30Z",
    "ht": "Curicó Unido",
    "at": "Ñublense",
    "hg": 1,
    "ag": 2,
    "hst": 4,
    "ast": 7,
    "hs": 12,
    "as": 12,
    "hc": 4,
    "ac": 1,
    "evt_id": "629241",
    "temp": 2022
  },
  {
    "fecha": "2022-10-21T22:30Z",
    "ht": "O'Higgins",
    "at": "Cobresal",
    "hg": 1,
    "ag": 0,
    "hst": 5,
    "ast": 1,
    "hs": 15,
    "as": 9,
    "hc": 6,
    "ac": 0,
    "evt_id": "629242",
    "temp": 2022
  },
  {
    "fecha": "2022-10-23T18:00Z",
    "ht": "Coquimbo Unido",
    "at": "Colo Colo",
    "hg": 0,
    "ag": 2,
    "hst": 0,
    "ast": 4,
    "hs": 9,
    "as": 10,
    "hc": 9,
    "ac": 3,
    "evt_id": "629243",
    "temp": 2022
  },
  {
    "fecha": "2022-10-24T23:30Z",
    "ht": "Audax Italiano",
    "at": "Curicó Unido",
    "hg": 1,
    "ag": 1,
    "hst": 4,
    "ast": 12,
    "hs": 10,
    "as": 20,
    "hc": 7,
    "ac": 10,
    "evt_id": "629244",
    "temp": 2022
  },
  {
    "fecha": "2022-10-22T23:00Z",
    "ht": "Universidad de Chile",
    "at": "Everton CD",
    "hg": 1,
    "ag": 1,
    "hst": 1,
    "ast": 4,
    "hs": 9,
    "as": 18,
    "hc": 3,
    "ac": 4,
    "evt_id": "629245",
    "temp": 2022
  },
  {
    "fecha": "2022-10-23T18:00Z",
    "ht": "Palestino",
    "at": "La Serena",
    "hg": 5,
    "ag": 0,
    "hst": 7,
    "ast": 4,
    "hs": 19,
    "as": 7,
    "hc": 6,
    "ac": 1,
    "evt_id": "629246",
    "temp": 2022
  },
  {
    "fecha": "2022-10-22T20:30Z",
    "ht": "Ñublense",
    "at": "Huachipato",
    "hg": 2,
    "ag": 0,
    "hst": 6,
    "ast": 3,
    "hs": 14,
    "as": 15,
    "hc": 3,
    "ac": 7,
    "evt_id": "629247",
    "temp": 2022
  },
  {
    "fecha": "2022-10-23T22:00Z",
    "ht": "Unión La Calera",
    "at": "Universidad Católica",
    "hg": 4,
    "ag": 0,
    "hst": 7,
    "ast": 0,
    "hs": 20,
    "as": 4,
    "hc": 8,
    "ac": 4,
    "evt_id": "629248",
    "temp": 2022
  },
  {
    "fecha": "2022-10-23T18:00Z",
    "ht": "Antofagasta",
    "at": "Unión Española",
    "hg": 2,
    "ag": 0,
    "hst": 3,
    "ast": 3,
    "hs": 18,
    "as": 13,
    "hc": 4,
    "ac": 3,
    "evt_id": "629249",
    "temp": 2022
  },
  {
    "fecha": "2022-10-09T23:15Z",
    "ht": "Everton CD",
    "at": "Cobresal",
    "hg": 3,
    "ag": 3,
    "hst": 8,
    "ast": 6,
    "hs": 17,
    "as": 9,
    "hc": 3,
    "ac": 3,
    "evt_id": "629250",
    "temp": 2022
  },
  {
    "fecha": "2022-10-07T22:00Z",
    "ht": "Huachipato",
    "at": "Coquimbo Unido",
    "hg": 0,
    "ag": 1,
    "hst": 2,
    "ast": 3,
    "hs": 17,
    "as": 5,
    "hc": 8,
    "ac": 1,
    "evt_id": "629251",
    "temp": 2022
  },
  {
    "fecha": "2022-10-09T20:30Z",
    "ht": "Colo Colo",
    "at": "Curicó Unido",
    "hg": 1,
    "ag": 1,
    "hst": 6,
    "ast": 1,
    "hs": 13,
    "as": 7,
    "hc": 8,
    "ac": 3,
    "evt_id": "629252",
    "temp": 2022
  },
  {
    "fecha": "2022-10-08T23:00Z",
    "ht": "Unión Española",
    "at": "O'Higgins",
    "hg": 0,
    "ag": 0,
    "hst": 5,
    "ast": 4,
    "hs": 11,
    "as": 19,
    "hc": 5,
    "ac": 2,
    "evt_id": "629253",
    "temp": 2022
  },
  {
    "fecha": "2022-10-15T21:00Z",
    "ht": "Antofagasta",
    "at": "Palestino",
    "hg": 0,
    "ag": 3,
    "hst": 0,
    "ast": 0,
    "hs": 0,
    "as": 0,
    "hc": 0,
    "ac": 0,
    "evt_id": "629254",
    "temp": 2022
  },
  {
    "fecha": "2022-10-09T15:30Z",
    "ht": "La Serena",
    "at": "Universidad de Chile",
    "hg": 1,
    "ag": 2,
    "hst": 1,
    "ast": 3,
    "hs": 13,
    "as": 14,
    "hc": 4,
    "ac": 3,
    "evt_id": "629255",
    "temp": 2022
  },
  {
    "fecha": "2022-10-10T20:30Z",
    "ht": "Audax Italiano",
    "at": "Unión La Calera",
    "hg": 0,
    "ag": 2,
    "hst": 4,
    "ast": 5,
    "hs": 12,
    "as": 11,
    "hc": 4,
    "ac": 1,
    "evt_id": "629256",
    "temp": 2022
  },
  {
    "fecha": "2022-10-08T18:00Z",
    "ht": "Universidad Católica",
    "at": "Ñublense",
    "hg": 2,
    "ag": 2,
    "hst": 6,
    "ast": 4,
    "hs": 12,
    "as": 17,
    "hc": 7,
    "ac": 2,
    "evt_id": "629257",
    "temp": 2022
  },
  {
    "fecha": "2022-10-01T15:00Z",
    "ht": "Huachipato",
    "at": "Antofagasta",
    "hg": 1,
    "ag": 0,
    "hst": 7,
    "ast": 4,
    "hs": 17,
    "as": 8,
    "hc": 8,
    "ac": 2,
    "evt_id": "629258",
    "temp": 2022
  },
  {
    "fecha": "2022-10-03T21:00Z",
    "ht": "Universidad de Chile",
    "at": "Audax Italiano",
    "hg": 2,
    "ag": 3,
    "hst": 5,
    "ast": 6,
    "hs": 13,
    "as": 11,
    "hc": 3,
    "ac": 1,
    "evt_id": "629259",
    "temp": 2022
  },
  {
    "fecha": "2022-09-30T23:00Z",
    "ht": "Unión La Calera",
    "at": "Coquimbo Unido",
    "hg": 2,
    "ag": 0,
    "hst": 5,
    "ast": 3,
    "hs": 15,
    "as": 13,
    "hc": 8,
    "ac": 3,
    "evt_id": "629260",
    "temp": 2022
  },
  {
    "fecha": "2022-10-01T18:00Z",
    "ht": "Palestino",
    "at": "Everton CD",
    "hg": 1,
    "ag": 4,
    "hst": 5,
    "ast": 9,
    "hs": 8,
    "as": 13,
    "hc": 4,
    "ac": 8,
    "evt_id": "629261",
    "temp": 2022
  },
  {
    "fecha": "2022-10-01T23:00Z",
    "ht": "Curicó Unido",
    "at": "La Serena",
    "hg": 1,
    "ag": 0,
    "hst": 7,
    "ast": 1,
    "hs": 22,
    "as": 11,
    "hc": 12,
    "ac": 3,
    "evt_id": "629262",
    "temp": 2022
  },
  {
    "fecha": "2022-10-02T15:00Z",
    "ht": "Ñublense",
    "at": "O'Higgins",
    "hg": 2,
    "ag": 2,
    "hst": 4,
    "ast": 9,
    "hs": 14,
    "as": 18,
    "hc": 3,
    "ac": 1,
    "evt_id": "629263",
    "temp": 2022
  },
  {
    "fecha": "2022-10-04T22:00Z",
    "ht": "Colo Colo",
    "at": "Universidad Católica",
    "hg": 0,
    "ag": 0,
    "hst": 4,
    "ast": 3,
    "hs": 14,
    "as": 9,
    "hc": 3,
    "ac": 1,
    "evt_id": "629264",
    "temp": 2022
  },
  {
    "fecha": "2022-10-02T21:00Z",
    "ht": "Cobresal",
    "at": "Unión Española",
    "hg": 2,
    "ag": 0,
    "hst": 4,
    "ast": 4,
    "hs": 16,
    "as": 9,
    "hc": 3,
    "ac": 3,
    "evt_id": "629265",
    "temp": 2022
  },
  {
    "fecha": "2022-09-13T21:00Z",
    "ht": "Coquimbo Unido",
    "at": "Audax Italiano",
    "hg": 0,
    "ag": 1,
    "hst": 1,
    "ast": 2,
    "hs": 12,
    "as": 9,
    "hc": 6,
    "ac": 1,
    "evt_id": "629266",
    "temp": 2022
  },
  {
    "fecha": "2022-09-14T20:00Z",
    "ht": "Cobresal",
    "at": "Colo Colo",
    "hg": 0,
    "ag": 2,
    "hst": 5,
    "ast": 7,
    "hs": 7,
    "as": 12,
    "hc": 3,
    "ac": 3,
    "evt_id": "629267",
    "temp": 2022
  },
  {
    "fecha": "2022-09-15T21:00Z",
    "ht": "Antofagasta",
    "at": "Curicó Unido",
    "hg": 0,
    "ag": 0,
    "hst": 5,
    "ast": 3,
    "hs": 20,
    "as": 12,
    "hc": 4,
    "ac": 2,
    "evt_id": "629268",
    "temp": 2022
  },
  {
    "fecha": "2022-09-14T18:30Z",
    "ht": "Unión Española",
    "at": "La Serena",
    "hg": 0,
    "ag": 1,
    "hst": 4,
    "ast": 5,
    "hs": 18,
    "as": 14,
    "hc": 10,
    "ac": 1,
    "evt_id": "629269",
    "temp": 2022
  },
  {
    "fecha": "2022-09-14T23:30Z",
    "ht": "Universidad Católica",
    "at": "Huachipato",
    "hg": 1,
    "ag": 0,
    "hst": 7,
    "ast": 1,
    "hs": 16,
    "as": 12,
    "hc": 8,
    "ac": 6,
    "evt_id": "629270",
    "temp": 2022
  },
  {
    "fecha": "2022-09-15T18:30Z",
    "ht": "Palestino",
    "at": "Universidad de Chile",
    "hg": 1,
    "ag": 2,
    "hst": 3,
    "ast": 4,
    "hs": 12,
    "as": 8,
    "hc": 4,
    "ac": 4,
    "evt_id": "629271",
    "temp": 2022
  },
  {
    "fecha": "2022-09-13T23:30Z",
    "ht": "O'Higgins",
    "at": "Unión La Calera",
    "hg": 2,
    "ag": 2,
    "hst": 6,
    "ast": 4,
    "hs": 16,
    "as": 10,
    "hc": 5,
    "ac": 5,
    "evt_id": "629272",
    "temp": 2022
  },
  {
    "fecha": "2022-09-14T21:00Z",
    "ht": "Everton CD",
    "at": "Ñublense",
    "hg": 1,
    "ag": 1,
    "hst": 9,
    "ast": 4,
    "hs": 17,
    "as": 11,
    "hc": 4,
    "ac": 3,
    "evt_id": "629273",
    "temp": 2022
  },
  {
    "fecha": "2022-09-09T22:00Z",
    "ht": "O'Higgins",
    "at": "Antofagasta",
    "hg": 1,
    "ag": 0,
    "hst": 4,
    "ast": 2,
    "hs": 16,
    "as": 11,
    "hc": 7,
    "ac": 10,
    "evt_id": "629274",
    "temp": 2022
  },
  {
    "fecha": "2022-09-08T00:30Z",
    "ht": "Audax Italiano",
    "at": "Cobresal",
    "hg": 2,
    "ag": 2,
    "hst": 6,
    "ast": 2,
    "hs": 14,
    "as": 5,
    "hc": 9,
    "ac": 4,
    "evt_id": "629275",
    "temp": 2022
  },
  {
    "fecha": "2022-09-07T19:30Z",
    "ht": "Universidad de Chile",
    "at": "Coquimbo Unido",
    "hg": 0,
    "ag": 0,
    "hst": 0,
    "ast": 2,
    "hs": 8,
    "as": 17,
    "hc": 5,
    "ac": 7,
    "evt_id": "629276",
    "temp": 2022
  },
  {
    "fecha": "2022-09-10T00:30Z",
    "ht": "Huachipato",
    "at": "Everton CD",
    "hg": 1,
    "ag": 1,
    "hst": 4,
    "ast": 7,
    "hs": 11,
    "as": 16,
    "hc": 8,
    "ac": 4,
    "evt_id": "629277",
    "temp": 2022
  },
  {
    "fecha": "2022-09-10T21:30Z",
    "ht": "Ñublense",
    "at": "Palestino",
    "hg": 2,
    "ag": 0,
    "hst": 6,
    "ast": 5,
    "hs": 10,
    "as": 15,
    "hc": 0,
    "ac": 7,
    "evt_id": "629278",
    "temp": 2022
  },
  {
    "fecha": "2022-09-10T19:00Z",
    "ht": "La Serena",
    "at": "Universidad Católica",
    "hg": 0,
    "ag": 4,
    "hst": 8,
    "ast": 9,
    "hs": 13,
    "as": 24,
    "hc": 5,
    "ac": 1,
    "evt_id": "629279",
    "temp": 2022
  },
  {
    "fecha": "2022-09-08T22:00Z",
    "ht": "Colo Colo",
    "at": "Unión Española",
    "hg": 4,
    "ag": 0,
    "hst": 9,
    "ast": 4,
    "hs": 20,
    "as": 12,
    "hc": 5,
    "ac": 10,
    "evt_id": "629280",
    "temp": 2022
  },
  {
    "fecha": "2022-09-09T00:30Z",
    "ht": "Curicó Unido",
    "at": "Unión La Calera",
    "hg": 2,
    "ag": 0,
    "hst": 2,
    "ast": 2,
    "hs": 10,
    "as": 14,
    "hc": 8,
    "ac": 3,
    "evt_id": "629281",
    "temp": 2022
  },
  {
    "fecha": "2022-08-29T00:00Z",
    "ht": "Unión Española",
    "at": "Audax Italiano",
    "hg": 2,
    "ag": 3,
    "hst": 5,
    "ast": 5,
    "hs": 13,
    "as": 12,
    "hc": 1,
    "ac": 1,
    "evt_id": "629282",
    "temp": 2022
  },
  {
    "fecha": "2022-08-28T21:30Z",
    "ht": "Unión La Calera",
    "at": "Colo Colo",
    "hg": 2,
    "ag": 1,
    "hst": 4,
    "ast": 4,
    "hs": 11,
    "as": 13,
    "hc": 5,
    "ac": 5,
    "evt_id": "629283",
    "temp": 2022
  },
  {
    "fecha": "2022-08-27T16:00Z",
    "ht": "Palestino",
    "at": "Curicó Unido",
    "hg": 2,
    "ag": 1,
    "hst": 4,
    "ast": 7,
    "hs": 15,
    "as": 13,
    "hc": 4,
    "ac": 4,
    "evt_id": "629284",
    "temp": 2022
  },
  {
    "fecha": "2022-08-27T00:00Z",
    "ht": "Everton CD",
    "at": "La Serena",
    "hg": 4,
    "ag": 0,
    "hst": 8,
    "ast": 0,
    "hs": 22,
    "as": 9,
    "hc": 1,
    "ac": 4,
    "evt_id": "629285",
    "temp": 2022
  },
  {
    "fecha": "2022-08-27T22:00Z",
    "ht": "Coquimbo Unido",
    "at": "O'Higgins",
    "hg": 0,
    "ag": 1,
    "hst": 0,
    "ast": 4,
    "hs": 5,
    "as": 14,
    "hc": 2,
    "ac": 5,
    "evt_id": "629286",
    "temp": 2022
  },
  {
    "fecha": "2022-08-28T19:00Z",
    "ht": "Cobresal",
    "at": "Huachipato",
    "hg": 2,
    "ag": 0,
    "hst": 3,
    "ast": 4,
    "hs": 11,
    "as": 11,
    "hc": 4,
    "ac": 4,
    "evt_id": "629287",
    "temp": 2022
  },
  {
    "fecha": "2022-08-27T19:00Z",
    "ht": "Universidad de Chile",
    "at": "Universidad Católica",
    "hg": 0,
    "ag": 3,
    "hst": 8,
    "ast": 6,
    "hs": 22,
    "as": 10,
    "hc": 6,
    "ac": 4,
    "evt_id": "629288",
    "temp": 2022
  },
  {
    "fecha": "2022-08-28T16:30Z",
    "ht": "Antofagasta",
    "at": "Ñublense",
    "hg": 1,
    "ag": 0,
    "hst": 3,
    "ast": 1,
    "hs": 12,
    "as": 8,
    "hc": 4,
    "ac": 1,
    "evt_id": "629289",
    "temp": 2022
  },
  {
    "fecha": "2022-08-14T00:30Z",
    "ht": "Unión La Calera",
    "at": "Antofagasta",
    "hg": 1,
    "ag": 1,
    "hst": 4,
    "ast": 4,
    "hs": 9,
    "as": 10,
    "hc": 2,
    "ac": 7,
    "evt_id": "629290",
    "temp": 2022
  },
  {
    "fecha": "2022-08-13T00:30Z",
    "ht": "Coquimbo Unido",
    "at": "Cobresal",
    "hg": 3,
    "ag": 1,
    "hst": 7,
    "ast": 2,
    "hs": 13,
    "as": 7,
    "hc": 5,
    "ac": 1,
    "evt_id": "629291",
    "temp": 2022
  },
  {
    "fecha": "2022-08-13T17:15Z",
    "ht": "Audax Italiano",
    "at": "Everton CD",
    "hg": 1,
    "ag": 0,
    "hst": 2,
    "ast": 1,
    "hs": 17,
    "as": 3,
    "hc": 9,
    "ac": 3,
    "evt_id": "629292",
    "temp": 2022
  },
  {
    "fecha": "2022-08-12T00:15Z",
    "ht": "Universidad Católica",
    "at": "O'Higgins",
    "hg": 2,
    "ag": 2,
    "hst": 3,
    "ast": 4,
    "hs": 7,
    "as": 18,
    "hc": 4,
    "ac": 2,
    "evt_id": "629293",
    "temp": 2022
  },
  {
    "fecha": "2022-08-14T21:30Z",
    "ht": "Colo Colo",
    "at": "Palestino",
    "hg": 1,
    "ag": 0,
    "hst": 4,
    "ast": 3,
    "hs": 10,
    "as": 10,
    "hc": 7,
    "ac": 1,
    "evt_id": "629294",
    "temp": 2022
  },
  {
    "fecha": "2022-08-14T19:00Z",
    "ht": "La Serena",
    "at": "Huachipato",
    "hg": 0,
    "ag": 1,
    "hst": 4,
    "ast": 4,
    "hs": 12,
    "as": 13,
    "hc": 6,
    "ac": 4,
    "evt_id": "629295",
    "temp": 2022
  },
  {
    "fecha": "2022-08-13T19:45Z",
    "ht": "Curicó Unido",
    "at": "Universidad de Chile",
    "hg": 3,
    "ag": 1,
    "hst": 9,
    "ast": 4,
    "hs": 16,
    "as": 11,
    "hc": 2,
    "ac": 2,
    "evt_id": "629296",
    "temp": 2022
  },
  {
    "fecha": "2022-08-15T00:00Z",
    "ht": "Ñublense",
    "at": "Unión Española",
    "hg": 1,
    "ag": 2,
    "hst": 4,
    "ast": 3,
    "hs": 16,
    "as": 23,
    "hc": 7,
    "ac": 8,
    "evt_id": "629297",
    "temp": 2022
  },
  {
    "fecha": "2022-08-07T22:15Z",
    "ht": "Colo Colo",
    "at": "Antofagasta",
    "hg": 1,
    "ag": 0,
    "hst": 6,
    "ast": 4,
    "hs": 25,
    "as": 9,
    "hc": 8,
    "ac": 1,
    "evt_id": "629298",
    "temp": 2022
  },
  {
    "fecha": "2022-08-07T17:15Z",
    "ht": "Palestino",
    "at": "Audax Italiano",
    "hg": 3,
    "ag": 3,
    "hst": 8,
    "ast": 3,
    "hs": 13,
    "as": 14,
    "hc": 8,
    "ac": 7,
    "evt_id": "629299",
    "temp": 2022
  },
  {
    "fecha": "2022-08-08T00:45Z",
    "ht": "Ñublense",
    "at": "Coquimbo Unido",
    "hg": 2,
    "ag": 1,
    "hst": 6,
    "ast": 3,
    "hs": 14,
    "as": 8,
    "hc": 8,
    "ac": 1,
    "evt_id": "629300",
    "temp": 2022
  },
  {
    "fecha": "2022-08-06T16:30Z",
    "ht": "O'Higgins",
    "at": "Curicó Unido",
    "hg": 0,
    "ag": 0,
    "hst": 4,
    "ast": 7,
    "hs": 26,
    "as": 11,
    "hc": 4,
    "ac": 7,
    "evt_id": "629301",
    "temp": 2022
  },
  {
    "fecha": "2022-08-06T19:00Z",
    "ht": "Cobresal",
    "at": "La Serena",
    "hg": 1,
    "ag": 1,
    "hst": 3,
    "ast": 3,
    "hs": 16,
    "as": 11,
    "hc": 7,
    "ac": 6,
    "evt_id": "629302",
    "temp": 2022
  },
  {
    "fecha": "2022-08-06T21:30Z",
    "ht": "Everton CD",
    "at": "Universidad Católica",
    "hg": 1,
    "ag": 1,
    "hst": 4,
    "ast": 1,
    "hs": 17,
    "as": 14,
    "hc": 1,
    "ac": 7,
    "evt_id": "629303",
    "temp": 2022
  },
  {
    "fecha": "2022-08-07T19:45Z",
    "ht": "Unión Española",
    "at": "Universidad de Chile",
    "hg": 1,
    "ag": 1,
    "hst": 6,
    "ast": 6,
    "hs": 12,
    "as": 19,
    "hc": 8,
    "ac": 8,
    "evt_id": "629304",
    "temp": 2022
  },
  {
    "fecha": "2022-08-08T21:30Z",
    "ht": "Huachipato",
    "at": "Unión La Calera",
    "hg": 3,
    "ag": 4,
    "hst": 7,
    "ast": 4,
    "hs": 21,
    "as": 7,
    "hc": 11,
    "ac": 4,
    "evt_id": "629305",
    "temp": 2022
  },
  {
    "fecha": "2022-07-30T22:00Z",
    "ht": "Universidad Católica",
    "at": "Cobresal",
    "hg": 1,
    "ag": 0,
    "hst": 4,
    "ast": 1,
    "hs": 19,
    "as": 6,
    "hc": 11,
    "ac": 3,
    "evt_id": "629306",
    "temp": 2022
  },
  {
    "fecha": "2022-07-31T17:30Z",
    "ht": "Universidad de Chile",
    "at": "Colo Colo",
    "hg": 1,
    "ag": 3,
    "hst": 3,
    "ast": 6,
    "hs": 14,
    "as": 11,
    "hc": 3,
    "ac": 2,
    "evt_id": "629307",
    "temp": 2022
  },
  {
    "fecha": "2022-07-30T16:30Z",
    "ht": "Antofagasta",
    "at": "Coquimbo Unido",
    "hg": 2,
    "ag": 1,
    "hst": 5,
    "ast": 6,
    "hs": 13,
    "as": 14,
    "hc": 5,
    "ac": 4,
    "evt_id": "629308",
    "temp": 2022
  },
  {
    "fecha": "2022-07-31T00:30Z",
    "ht": "Curicó Unido",
    "at": "Everton CD",
    "hg": 0,
    "ag": 4,
    "hst": 6,
    "ast": 7,
    "hs": 21,
    "as": 9,
    "hc": 9,
    "ac": 3,
    "evt_id": "629309",
    "temp": 2022
  },
  {
    "fecha": "2022-07-31T22:00Z",
    "ht": "Audax Italiano",
    "at": "O'Higgins",
    "hg": 2,
    "ag": 1,
    "hst": 3,
    "ast": 4,
    "hs": 13,
    "as": 9,
    "hc": 9,
    "ac": 2,
    "evt_id": "629310",
    "temp": 2022
  },
  {
    "fecha": "2022-07-30T00:30Z",
    "ht": "Unión La Calera",
    "at": "Palestino",
    "hg": 2,
    "ag": 2,
    "hst": 4,
    "ast": 3,
    "hs": 10,
    "as": 11,
    "hc": 4,
    "ac": 9,
    "evt_id": "629311",
    "temp": 2022
  },
  {
    "fecha": "2022-07-29T22:00Z",
    "ht": "Huachipato",
    "at": "Unión Española",
    "hg": 2,
    "ag": 5,
    "hst": 8,
    "ast": 6,
    "hs": 21,
    "as": 15,
    "hc": 8,
    "ac": 4,
    "evt_id": "629312",
    "temp": 2022
  },
  {
    "fecha": "2022-07-30T19:00Z",
    "ht": "La Serena",
    "at": "Ñublense",
    "hg": 3,
    "ag": 0,
    "hst": 4,
    "ast": 2,
    "hs": 9,
    "as": 18,
    "hc": 2,
    "ac": 10,
    "evt_id": "629313",
    "temp": 2022
  },
  {
    "fecha": "2022-07-23T16:30Z",
    "ht": "Antofagasta",
    "at": "Audax Italiano",
    "hg": 2,
    "ag": 3,
    "hst": 7,
    "ast": 6,
    "hs": 19,
    "as": 10,
    "hc": 8,
    "ac": 2,
    "evt_id": "629314",
    "temp": 2022
  },
  {
    "fecha": "2022-07-22T23:00Z",
    "ht": "Ñublense",
    "at": "Cobresal",
    "hg": 3,
    "ag": 2,
    "hst": 8,
    "ast": 5,
    "hs": 17,
    "as": 16,
    "hc": 3,
    "ac": 4,
    "evt_id": "629315",
    "temp": 2022
  },
  {
    "fecha": "2022-07-25T22:00Z",
    "ht": "Unión Española",
    "at": "Curicó Unido",
    "hg": 1,
    "ag": 3,
    "hst": 4,
    "ast": 5,
    "hs": 10,
    "as": 15,
    "hc": 5,
    "ac": 3,
    "evt_id": "629316",
    "temp": 2022
  },
  {
    "fecha": "2022-07-23T19:00Z",
    "ht": "Coquimbo Unido",
    "at": "La Serena",
    "hg": 2,
    "ag": 0,
    "hst": 6,
    "ast": 2,
    "hs": 16,
    "as": 9,
    "hc": 4,
    "ac": 4,
    "evt_id": "629317",
    "temp": 2022
  },
  {
    "fecha": "2022-07-24T21:30Z",
    "ht": "Universidad Católica",
    "at": "Palestino",
    "hg": 0,
    "ag": 1,
    "hst": 3,
    "ast": 5,
    "hs": 14,
    "as": 14,
    "hc": 8,
    "ac": 7,
    "evt_id": "629318",
    "temp": 2022
  },
  {
    "fecha": "2022-07-23T21:30Z",
    "ht": "Colo Colo",
    "at": "Huachipato",
    "hg": 1,
    "ag": 0,
    "hst": 5,
    "ast": 1,
    "hs": 17,
    "as": 8,
    "hc": 8,
    "ac": 4,
    "evt_id": "629319",
    "temp": 2022
  },
  {
    "fecha": "2022-07-24T19:00Z",
    "ht": "O'Higgins",
    "at": "Universidad de Chile",
    "hg": 1,
    "ag": 0,
    "hst": 3,
    "ast": 3,
    "hs": 16,
    "as": 10,
    "hc": 4,
    "ac": 4,
    "evt_id": "629320",
    "temp": 2022
  },
  {
    "fecha": "2022-07-24T00:00Z",
    "ht": "Everton CD",
    "at": "Unión La Calera",
    "hg": 0,
    "ag": 1,
    "hst": 3,
    "ast": 3,
    "hs": 10,
    "as": 12,
    "hc": 3,
    "ac": 2,
    "evt_id": "629321",
    "temp": 2022
  },
  {
    "fecha": "2022-07-17T16:30Z",
    "ht": "La Serena",
    "at": "Antofagasta",
    "hg": 0,
    "ag": 1,
    "hst": 4,
    "ast": 2,
    "hs": 8,
    "as": 9,
    "hc": 6,
    "ac": 3,
    "evt_id": "629322",
    "temp": 2022
  },
  {
    "fecha": "2022-07-16T19:45Z",
    "ht": "Audax Italiano",
    "at": "Colo Colo",
    "hg": 1,
    "ag": 2,
    "hst": 3,
    "ast": 6,
    "hs": 4,
    "as": 17,
    "hc": 1,
    "ac": 7,
    "evt_id": "629323",
    "temp": 2022
  },
  {
    "fecha": "2022-07-16T17:15Z",
    "ht": "Palestino",
    "at": "Coquimbo Unido",
    "hg": 5,
    "ag": 1,
    "hst": 6,
    "ast": 3,
    "hs": 13,
    "as": 12,
    "hc": 3,
    "ac": 3,
    "evt_id": "629324",
    "temp": 2022
  },
  {
    "fecha": "2022-07-18T00:00Z",
    "ht": "Huachipato",
    "at": "O'Higgins",
    "hg": 1,
    "ag": 2,
    "hst": 6,
    "ast": 6,
    "hs": 18,
    "as": 14,
    "hc": 6,
    "ac": 7,
    "evt_id": "629325",
    "temp": 2022
  },
  {
    "fecha": "2022-07-17T21:30Z",
    "ht": "Curicó Unido",
    "at": "Universidad Católica",
    "hg": 3,
    "ag": 2,
    "hst": 6,
    "ast": 5,
    "hs": 19,
    "as": 14,
    "hc": 6,
    "ac": 4,
    "evt_id": "629326",
    "temp": 2022
  },
  {
    "fecha": "2022-07-17T00:45Z",
    "ht": "Everton CD",
    "at": "Unión Española",
    "hg": 2,
    "ag": 1,
    "hst": 7,
    "ast": 8,
    "hs": 15,
    "as": 15,
    "hc": 5,
    "ac": 6,
    "evt_id": "629327",
    "temp": 2022
  },
  {
    "fecha": "2022-07-16T22:15Z",
    "ht": "Cobresal",
    "at": "Unión La Calera",
    "hg": 3,
    "ag": 1,
    "hst": 6,
    "ast": 0,
    "hs": 16,
    "as": 3,
    "hc": 4,
    "ac": 4,
    "evt_id": "629328",
    "temp": 2022
  },
  {
    "fecha": "2022-07-17T19:00Z",
    "ht": "Universidad de Chile",
    "at": "Ñublense",
    "hg": 0,
    "ag": 1,
    "hst": 6,
    "ast": 6,
    "hs": 16,
    "as": 14,
    "hc": 7,
    "ac": 1,
    "evt_id": "629329",
    "temp": 2022
  },
  {
    "fecha": "2022-07-09T19:00Z",
    "ht": "Curicó Unido",
    "at": "Cobresal",
    "hg": 1,
    "ag": 0,
    "hst": 6,
    "ast": 2,
    "hs": 14,
    "as": 14,
    "hc": 11,
    "ac": 8,
    "evt_id": "629330",
    "temp": 2022
  },
  {
    "fecha": "2022-07-10T00:00Z",
    "ht": "Coquimbo Unido",
    "at": "Everton CD",
    "hg": 1,
    "ag": 1,
    "hst": 5,
    "ast": 3,
    "hs": 11,
    "as": 13,
    "hc": 4,
    "ac": 7,
    "evt_id": "629331",
    "temp": 2022
  },
  {
    "fecha": "2022-07-10T22:00Z",
    "ht": "Colo Colo",
    "at": "La Serena",
    "hg": 3,
    "ag": 0,
    "hst": 6,
    "ast": 0,
    "hs": 13,
    "as": 9,
    "hc": 7,
    "ac": 3,
    "evt_id": "629332",
    "temp": 2022
  },
  {
    "fecha": "2022-07-09T00:30Z",
    "ht": "O'Higgins",
    "at": "Palestino",
    "hg": 1,
    "ag": 2,
    "hst": 3,
    "ast": 3,
    "hs": 18,
    "as": 11,
    "hc": 8,
    "ac": 5,
    "evt_id": "629333",
    "temp": 2022
  },
  {
    "fecha": "2022-07-09T21:30Z",
    "ht": "Audax Italiano",
    "at": "Huachipato",
    "hg": 1,
    "ag": 1,
    "hst": 9,
    "ast": 5,
    "hs": 21,
    "as": 13,
    "hc": 6,
    "ac": 1,
    "evt_id": "629334",
    "temp": 2022
  },
  {
    "fecha": "2022-10-19T22:00Z",
    "ht": "Unión Española",
    "at": "Universidad Católica",
    "hg": 1,
    "ag": 2,
    "hst": 6,
    "ast": 3,
    "hs": 17,
    "as": 6,
    "hc": 7,
    "ac": 0,
    "evt_id": "629335",
    "temp": 2022
  },
  {
    "fecha": "2022-07-10T19:00Z",
    "ht": "Antofagasta",
    "at": "Universidad de Chile",
    "hg": 1,
    "ag": 1,
    "hst": 6,
    "ast": 3,
    "hs": 18,
    "as": 13,
    "hc": 5,
    "ac": 2,
    "evt_id": "629336",
    "temp": 2022
  },
  {
    "fecha": "2022-07-11T00:30Z",
    "ht": "Unión La Calera",
    "at": "Ñublense",
    "hg": 2,
    "ag": 2,
    "hst": 5,
    "ast": 3,
    "hs": 5,
    "as": 19,
    "hc": 0,
    "ac": 7,
    "evt_id": "629337",
    "temp": 2022
  },
  {
    "fecha": "2022-07-04T00:00Z",
    "ht": "Cobresal",
    "at": "Antofagasta",
    "hg": 2,
    "ag": 1,
    "hst": 7,
    "ast": 1,
    "hs": 22,
    "as": 9,
    "hc": 4,
    "ac": 4,
    "evt_id": "629338",
    "temp": 2022
  },
  {
    "fecha": "2022-06-30T23:00Z",
    "ht": "Ñublense",
    "at": "Audax Italiano",
    "hg": 1,
    "ag": 2,
    "hst": 1,
    "ast": 5,
    "hs": 9,
    "as": 10,
    "hc": 5,
    "ac": 5,
    "evt_id": "629339",
    "temp": 2022
  },
  {
    "fecha": "2022-07-01T22:30Z",
    "ht": "Everton CD",
    "at": "Colo Colo",
    "hg": 1,
    "ag": 1,
    "hst": 3,
    "ast": 3,
    "hs": 19,
    "as": 9,
    "hc": 7,
    "ac": 5,
    "evt_id": "629340",
    "temp": 2022
  },
  {
    "fecha": "2022-07-03T21:30Z",
    "ht": "Universidad Católica",
    "at": "Coquimbo Unido",
    "hg": 2,
    "ag": 0,
    "hst": 7,
    "ast": 2,
    "hs": 10,
    "as": 10,
    "hc": 1,
    "ac": 6,
    "evt_id": "629341",
    "temp": 2022
  },
  {
    "fecha": "2022-07-03T00:00Z",
    "ht": "Huachipato",
    "at": "Curicó Unido",
    "hg": 2,
    "ag": 2,
    "hst": 6,
    "ast": 4,
    "hs": 19,
    "as": 16,
    "hc": 4,
    "ac": 2,
    "evt_id": "629342",
    "temp": 2022
  },
  {
    "fecha": "2022-07-03T19:00Z",
    "ht": "La Serena",
    "at": "O'Higgins",
    "hg": 1,
    "ag": 0,
    "hst": 3,
    "ast": 3,
    "hs": 8,
    "as": 16,
    "hc": 4,
    "ac": 4,
    "evt_id": "629343",
    "temp": 2022
  },
  {
    "fecha": "2022-07-02T19:00Z",
    "ht": "Palestino",
    "at": "Unión Española",
    "hg": 1,
    "ag": 0,
    "hst": 3,
    "ast": 3,
    "hs": 13,
    "as": 10,
    "hc": 4,
    "ac": 6,
    "evt_id": "629344",
    "temp": 2022
  },
  {
    "fecha": "2022-07-02T21:30Z",
    "ht": "Universidad de Chile",
    "at": "Unión La Calera",
    "hg": 2,
    "ag": 1,
    "hst": 4,
    "ast": 4,
    "hs": 8,
    "as": 13,
    "hc": 6,
    "ac": 6,
    "evt_id": "629345",
    "temp": 2022
  },
  {
    "fecha": "2022-05-29T21:30Z",
    "ht": "Universidad Católica",
    "at": "Antofagasta",
    "hg": 1,
    "ag": 0,
    "hst": 4,
    "ast": 2,
    "hs": 15,
    "as": 7,
    "hc": 5,
    "ac": 3,
    "evt_id": "629346",
    "temp": 2022
  },
  {
    "fecha": "2022-05-28T19:00Z",
    "ht": "La Serena",
    "at": "Audax Italiano",
    "hg": 3,
    "ag": 2,
    "hst": 7,
    "ast": 3,
    "hs": 11,
    "as": 19,
    "hc": 3,
    "ac": 8,
    "evt_id": "629347",
    "temp": 2022
  },
  {
    "fecha": "2022-05-28T00:30Z",
    "ht": "Curicó Unido",
    "at": "Coquimbo Unido",
    "hg": 3,
    "ag": 0,
    "hst": 5,
    "ast": 5,
    "hs": 11,
    "as": 18,
    "hc": 3,
    "ac": 4,
    "evt_id": "629348",
    "temp": 2022
  },
  {
    "fecha": "2022-05-31T00:30Z",
    "ht": "Everton CD",
    "at": "O'Higgins",
    "hg": 0,
    "ag": 0,
    "hst": 2,
    "ast": 2,
    "hs": 7,
    "as": 10,
    "hc": 1,
    "ac": 4,
    "evt_id": "629349",
    "temp": 2022
  },
  {
    "fecha": "2022-05-29T00:00Z",
    "ht": "Huachipato",
    "at": "Palestino",
    "hg": 2,
    "ag": 1,
    "hst": 2,
    "ast": 1,
    "hs": 7,
    "as": 7,
    "hc": 5,
    "ac": 2,
    "evt_id": "629350",
    "temp": 2022
  },
  {
    "fecha": "2022-05-28T21:30Z",
    "ht": "Cobresal",
    "at": "Universidad de Chile",
    "hg": 1,
    "ag": 0,
    "hst": 3,
    "ast": 0,
    "hs": 20,
    "as": 8,
    "hc": 5,
    "ac": 4,
    "evt_id": "629351",
    "temp": 2022
  },
  {
    "fecha": "2022-05-30T00:00Z",
    "ht": "Unión Española",
    "at": "Unión La Calera",
    "hg": 1,
    "ag": 1,
    "hst": 3,
    "ast": 2,
    "hs": 12,
    "as": 8,
    "hc": 4,
    "ac": 5,
    "evt_id": "629352",
    "temp": 2022
  },
  {
    "fecha": "2022-05-30T22:00Z",
    "ht": "Colo Colo",
    "at": "Ñublense",
    "hg": 0,
    "ag": 0,
    "hst": 3,
    "ast": 2,
    "hs": 16,
    "as": 7,
    "hc": 6,
    "ac": 1,
    "evt_id": "629353",
    "temp": 2022
  },
  {
    "fecha": "2022-05-22T16:00Z",
    "ht": "Palestino",
    "at": "Cobresal",
    "hg": 3,
    "ag": 1,
    "hst": 6,
    "ast": 4,
    "hs": 13,
    "as": 14,
    "hc": 4,
    "ac": 9,
    "evt_id": "629354",
    "temp": 2022
  },
  {
    "fecha": "2022-05-22T19:00Z",
    "ht": "O'Higgins",
    "at": "Colo Colo",
    "hg": 1,
    "ag": 1,
    "hst": 2,
    "ast": 2,
    "hs": 6,
    "as": 9,
    "hc": 3,
    "ac": 2,
    "evt_id": "629355",
    "temp": 2022
  },
  {
    "fecha": "2022-05-23T00:00Z",
    "ht": "Ñublense",
    "at": "Curicó Unido",
    "hg": 3,
    "ag": 1,
    "hst": 8,
    "ast": 3,
    "hs": 23,
    "as": 11,
    "hc": 8,
    "ac": 2,
    "evt_id": "629356",
    "temp": 2022
  },
  {
    "fecha": "2022-05-21T19:00Z",
    "ht": "Antofagasta",
    "at": "Everton CD",
    "hg": 2,
    "ag": 2,
    "hst": 3,
    "ast": 6,
    "hs": 15,
    "as": 18,
    "hc": 2,
    "ac": 9,
    "evt_id": "629357",
    "temp": 2022
  },
  {
    "fecha": "2022-05-22T00:00Z",
    "ht": "Unión La Calera",
    "at": "La Serena",
    "hg": 1,
    "ag": 1,
    "hst": 9,
    "ast": 2,
    "hs": 29,
    "as": 5,
    "hc": 5,
    "ac": 5,
    "evt_id": "629358",
    "temp": 2022
  },
  {
    "fecha": "2022-05-21T21:30Z",
    "ht": "Universidad de Chile",
    "at": "Huachipato",
    "hg": 3,
    "ag": 2,
    "hst": 8,
    "ast": 5,
    "hs": 14,
    "as": 13,
    "hc": 7,
    "ac": 2,
    "evt_id": "629359",
    "temp": 2022
  },
  {
    "fecha": "2022-05-21T19:00Z",
    "ht": "Audax Italiano",
    "at": "Universidad Católica",
    "hg": 3,
    "ag": 2,
    "hst": 6,
    "ast": 4,
    "hs": 13,
    "as": 7,
    "hc": 5,
    "ac": 5,
    "evt_id": "629360",
    "temp": 2022
  },
  {
    "fecha": "2022-05-20T23:00Z",
    "ht": "Coquimbo Unido",
    "at": "Unión Española",
    "hg": 2,
    "ag": 4,
    "hst": 4,
    "ast": 4,
    "hs": 12,
    "as": 17,
    "hc": 10,
    "ac": 7,
    "evt_id": "629361",
    "temp": 2022
  },
  {
    "fecha": "2022-05-14T00:30Z",
    "ht": "Unión Española",
    "at": "Antofagasta",
    "hg": 2,
    "ag": 0,
    "hst": 4,
    "ast": 3,
    "hs": 15,
    "as": 9,
    "hc": 10,
    "ac": 3,
    "evt_id": "629362",
    "temp": 2022
  },
  {
    "fecha": "2022-05-17T00:30Z",
    "ht": "Curicó Unido",
    "at": "Audax Italiano",
    "hg": 4,
    "ag": 1,
    "hst": 6,
    "ast": 2,
    "hs": 14,
    "as": 12,
    "hc": 6,
    "ac": 5,
    "evt_id": "629363",
    "temp": 2022
  },
  {
    "fecha": "2022-05-14T22:00Z",
    "ht": "Colo Colo",
    "at": "Coquimbo Unido",
    "hg": 4,
    "ag": 0,
    "hst": 8,
    "ast": 2,
    "hs": 17,
    "as": 9,
    "hc": 2,
    "ac": 3,
    "evt_id": "629364",
    "temp": 2022
  },
  {
    "fecha": "2022-05-15T18:45Z",
    "ht": "Cobresal",
    "at": "O'Higgins",
    "hg": 2,
    "ag": 0,
    "hst": 11,
    "ast": 2,
    "hs": 25,
    "as": 11,
    "hc": 10,
    "ac": 2,
    "evt_id": "629365",
    "temp": 2022
  },
  {
    "fecha": "2022-05-14T16:30Z",
    "ht": "La Serena",
    "at": "Palestino",
    "hg": 0,
    "ag": 0,
    "hst": 2,
    "ast": 5,
    "hs": 13,
    "as": 19,
    "hc": 6,
    "ac": 6,
    "evt_id": "629366",
    "temp": 2022
  },
  {
    "fecha": "2022-05-14T19:30Z",
    "ht": "Everton CD",
    "at": "Universidad de Chile",
    "hg": 2,
    "ag": 1,
    "hst": 6,
    "ast": 7,
    "hs": 11,
    "as": 15,
    "hc": 4,
    "ac": 4,
    "evt_id": "629367",
    "temp": 2022
  },
  {
    "fecha": "2022-05-13T22:00Z",
    "ht": "Universidad Católica",
    "at": "Unión La Calera",
    "hg": 3,
    "ag": 0,
    "hst": 7,
    "ast": 1,
    "hs": 10,
    "as": 8,
    "hc": 5,
    "ac": 5,
    "evt_id": "629368",
    "temp": 2022
  },
  {
    "fecha": "2022-05-15T21:30Z",
    "ht": "Huachipato",
    "at": "Ñublense",
    "hg": 1,
    "ag": 3,
    "hst": 3,
    "ast": 6,
    "hs": 15,
    "as": 23,
    "hc": 4,
    "ac": 1,
    "evt_id": "629369",
    "temp": 2022
  },
  {
    "fecha": "2022-05-08T16:00Z",
    "ht": "Palestino",
    "at": "Antofagasta",
    "hg": 1,
    "ag": 0,
    "hst": 5,
    "ast": 0,
    "hs": 14,
    "as": 5,
    "hc": 2,
    "ac": 5,
    "evt_id": "629370",
    "temp": 2022
  },
  {
    "fecha": "2022-05-10T00:30Z",
    "ht": "Unión La Calera",
    "at": "Audax Italiano",
    "hg": 1,
    "ag": 0,
    "hst": 3,
    "ast": 5,
    "hs": 10,
    "as": 18,
    "hc": 3,
    "ac": 5,
    "evt_id": "629371",
    "temp": 2022
  },
  {
    "fecha": "2022-05-09T22:00Z",
    "ht": "Curicó Unido",
    "at": "Colo Colo",
    "hg": 1,
    "ag": 2,
    "hst": 4,
    "ast": 3,
    "hs": 13,
    "as": 7,
    "hc": 6,
    "ac": 3,
    "evt_id": "629372",
    "temp": 2022
  },
  {
    "fecha": "2022-05-09T19:00Z",
    "ht": "Cobresal",
    "at": "Everton CD",
    "hg": 0,
    "ag": 0,
    "hst": 6,
    "ast": 4,
    "hs": 23,
    "as": 10,
    "hc": 11,
    "ac": 3,
    "evt_id": "629373",
    "temp": 2022
  },
  {
    "fecha": "2022-05-07T21:30Z",
    "ht": "Universidad de Chile",
    "at": "La Serena",
    "hg": 2,
    "ag": 0,
    "hst": 4,
    "ast": 2,
    "hs": 21,
    "as": 9,
    "hc": 8,
    "ac": 6,
    "evt_id": "629374",
    "temp": 2022
  },
  {
    "fecha": "2022-05-09T00:00Z",
    "ht": "Coquimbo Unido",
    "at": "Huachipato",
    "hg": 1,
    "ag": 2,
    "hst": 6,
    "ast": 5,
    "hs": 16,
    "as": 18,
    "hc": 4,
    "ac": 4,
    "evt_id": "629375",
    "temp": 2022
  },
  {
    "fecha": "2022-05-08T21:30Z",
    "ht": "Ñublense",
    "at": "Universidad Católica",
    "hg": 4,
    "ag": 0,
    "hst": 8,
    "ast": 3,
    "hs": 17,
    "as": 12,
    "hc": 4,
    "ac": 7,
    "evt_id": "629376",
    "temp": 2022
  },
  {
    "fecha": "2022-05-07T19:00Z",
    "ht": "O'Higgins",
    "at": "Unión Española",
    "hg": 2,
    "ag": 2,
    "hst": 3,
    "ast": 7,
    "hs": 16,
    "as": 13,
    "hc": 4,
    "ac": 6,
    "evt_id": "629377",
    "temp": 2022
  },
  {
    "fecha": "2022-04-27T00:00Z",
    "ht": "Unión Española",
    "at": "Cobresal",
    "hg": 2,
    "ag": 2,
    "hst": 4,
    "ast": 6,
    "hs": 12,
    "as": 12,
    "hc": 8,
    "ac": 1,
    "evt_id": "629378",
    "temp": 2022
  },
  {
    "fecha": "2022-04-24T16:30Z",
    "ht": "Universidad Católica",
    "at": "Colo Colo",
    "hg": 1,
    "ag": 1,
    "hst": 5,
    "ast": 2,
    "hs": 9,
    "as": 7,
    "hc": 2,
    "ac": 4,
    "evt_id": "629379",
    "temp": 2022
  },
  {
    "fecha": "2022-04-23T19:00Z",
    "ht": "La Serena",
    "at": "Curicó Unido",
    "hg": 1,
    "ag": 3,
    "hst": 7,
    "ast": 5,
    "hs": 13,
    "as": 8,
    "hc": 5,
    "ac": 4,
    "evt_id": "629380",
    "temp": 2022
  },
  {
    "fecha": "2022-04-23T00:00Z",
    "ht": "Everton CD",
    "at": "Palestino",
    "hg": 0,
    "ag": 0,
    "hst": 2,
    "ast": 4,
    "hs": 11,
    "as": 16,
    "hc": 4,
    "ac": 4,
    "evt_id": "629381",
    "temp": 2022
  },
  {
    "fecha": "2022-04-23T16:30Z",
    "ht": "Antofagasta",
    "at": "Huachipato",
    "hg": 0,
    "ag": 0,
    "hst": 4,
    "ast": 1,
    "hs": 18,
    "as": 8,
    "hc": 7,
    "ac": 4,
    "evt_id": "629382",
    "temp": 2022
  },
  {
    "fecha": "2022-04-29T18:00Z",
    "ht": "Audax Italiano",
    "at": "Universidad de Chile",
    "hg": 2,
    "ag": 0,
    "hst": 6,
    "ast": 2,
    "hs": 19,
    "as": 8,
    "hc": 6,
    "ac": 2,
    "evt_id": "629383",
    "temp": 2022
  },
  {
    "fecha": "2022-04-25T00:00Z",
    "ht": "Coquimbo Unido",
    "at": "Unión La Calera",
    "hg": 3,
    "ag": 2,
    "hst": 4,
    "ast": 7,
    "hs": 14,
    "as": 12,
    "hc": 9,
    "ac": 3,
    "evt_id": "629384",
    "temp": 2022
  },
  {
    "fecha": "2022-04-24T21:30Z",
    "ht": "O'Higgins",
    "at": "Ñublense",
    "hg": 1,
    "ag": 0,
    "hst": 4,
    "ast": 2,
    "hs": 9,
    "as": 11,
    "hc": 3,
    "ac": 5,
    "evt_id": "629385",
    "temp": 2022
  },
  {
    "fecha": "2022-04-17T16:30Z",
    "ht": "Curicó Unido",
    "at": "Antofagasta",
    "hg": 2,
    "ag": 0,
    "hst": 7,
    "ast": 1,
    "hs": 22,
    "as": 11,
    "hc": 3,
    "ac": 2,
    "evt_id": "629386",
    "temp": 2022
  },
  {
    "fecha": "2022-04-17T22:00Z",
    "ht": "Colo Colo",
    "at": "Cobresal",
    "hg": 2,
    "ag": 1,
    "hst": 4,
    "ast": 2,
    "hs": 13,
    "as": 11,
    "hc": 5,
    "ac": 3,
    "evt_id": "629387",
    "temp": 2022
  },
  {
    "fecha": "2022-04-16T19:00Z",
    "ht": "Audax Italiano",
    "at": "Coquimbo Unido",
    "hg": 1,
    "ag": 1,
    "hst": 3,
    "ast": 3,
    "hs": 10,
    "as": 8,
    "hc": 6,
    "ac": 4,
    "evt_id": "629388",
    "temp": 2022
  },
  {
    "fecha": "2022-04-18T22:00Z",
    "ht": "Ñublense",
    "at": "Everton CD",
    "hg": 2,
    "ag": 1,
    "hst": 6,
    "ast": 6,
    "hs": 22,
    "as": 15,
    "hc": 3,
    "ac": 6,
    "evt_id": "629389",
    "temp": 2022
  },
  {
    "fecha": "2022-04-19T00:30Z",
    "ht": "Unión La Calera",
    "at": "O'Higgins",
    "hg": 0,
    "ag": 0,
    "hst": 4,
    "ast": 2,
    "hs": 16,
    "as": 5,
    "hc": 6,
    "ac": 2,
    "evt_id": "629390",
    "temp": 2022
  },
  {
    "fecha": "2022-04-16T21:30Z",
    "ht": "Universidad de Chile",
    "at": "Palestino",
    "hg": 0,
    "ag": 0,
    "hst": 4,
    "ast": 4,
    "hs": 16,
    "as": 15,
    "hc": 7,
    "ac": 5,
    "evt_id": "629391",
    "temp": 2022
  },
  {
    "fecha": "2022-04-17T19:30Z",
    "ht": "Huachipato",
    "at": "Universidad Católica",
    "hg": 1,
    "ag": 0,
    "hst": 2,
    "ast": 4,
    "hs": 15,
    "as": 14,
    "hc": 6,
    "ac": 5,
    "evt_id": "629392",
    "temp": 2022
  },
  {
    "fecha": "2022-04-15T20:30Z",
    "ht": "La Serena",
    "at": "Unión Española",
    "hg": 1,
    "ag": 2,
    "hst": 2,
    "ast": 6,
    "hs": 6,
    "as": 14,
    "hc": 4,
    "ac": 5,
    "evt_id": "629393",
    "temp": 2022
  },
  {
    "fecha": "2022-04-10T16:30Z",
    "ht": "Cobresal",
    "at": "Audax Italiano",
    "hg": 0,
    "ag": 1,
    "hst": 2,
    "ast": 2,
    "hs": 13,
    "as": 5,
    "hc": 7,
    "ac": 3,
    "evt_id": "629394",
    "temp": 2022
  },
  {
    "fecha": "2022-04-10T21:30Z",
    "ht": "Unión Española",
    "at": "Colo Colo",
    "hg": 2,
    "ag": 1,
    "hst": 3,
    "ast": 3,
    "hs": 5,
    "as": 10,
    "hc": 4,
    "ac": 5,
    "evt_id": "629395",
    "temp": 2022
  },
  {
    "fecha": "2022-04-11T00:00Z",
    "ht": "Unión La Calera",
    "at": "Curicó Unido",
    "hg": 0,
    "ag": 0,
    "hst": 2,
    "ast": 1,
    "hs": 14,
    "as": 10,
    "hc": 5,
    "ac": 3,
    "evt_id": "629396",
    "temp": 2022
  },
  {
    "fecha": "2022-04-10T00:00Z",
    "ht": "Universidad Católica",
    "at": "La Serena",
    "hg": 0,
    "ag": 2,
    "hst": 0,
    "ast": 2,
    "hs": 16,
    "as": 5,
    "hc": 6,
    "ac": 1,
    "evt_id": "629397",
    "temp": 2022
  },
  {
    "fecha": "2022-04-30T16:00Z",
    "ht": "Antofagasta",
    "at": "O'Higgins",
    "hg": 1,
    "ag": 0,
    "hst": 6,
    "ast": 3,
    "hs": 13,
    "as": 12,
    "hc": 7,
    "ac": 2,
    "evt_id": "629398",
    "temp": 2022
  },
  {
    "fecha": "2022-04-09T19:00Z",
    "ht": "Everton CD",
    "at": "Huachipato",
    "hg": 0,
    "ag": 1,
    "hst": 1,
    "ast": 8,
    "hs": 3,
    "as": 19,
    "hc": 2,
    "ac": 8,
    "evt_id": "629399",
    "temp": 2022
  },
  {
    "fecha": "2022-04-09T21:30Z",
    "ht": "Coquimbo Unido",
    "at": "Universidad de Chile",
    "hg": 1,
    "ag": 0,
    "hst": 7,
    "ast": 6,
    "hs": 14,
    "as": 11,
    "hc": 4,
    "ac": 1,
    "evt_id": "629400",
    "temp": 2022
  },
  {
    "fecha": "2022-04-10T19:00Z",
    "ht": "Palestino",
    "at": "Ñublense",
    "hg": 1,
    "ag": 1,
    "hst": 3,
    "ast": 5,
    "hs": 11,
    "as": 18,
    "hc": 2,
    "ac": 6,
    "evt_id": "629401",
    "temp": 2022
  },
  {
    "fecha": "2022-04-02T18:00Z",
    "ht": "Ñublense",
    "at": "Antofagasta",
    "hg": 1,
    "ag": 1,
    "hst": 5,
    "ast": 6,
    "hs": 18,
    "as": 11,
    "hc": 4,
    "ac": 5,
    "evt_id": "629402",
    "temp": 2022
  },
  {
    "fecha": "2022-04-03T19:00Z",
    "ht": "Huachipato",
    "at": "Cobresal",
    "hg": 1,
    "ag": 0,
    "hst": 2,
    "ast": 5,
    "hs": 14,
    "as": 13,
    "hc": 4,
    "ac": 6,
    "evt_id": "629403",
    "temp": 2022
  },
  {
    "fecha": "2022-04-01T23:30Z",
    "ht": "O'Higgins",
    "at": "Coquimbo Unido",
    "hg": 2,
    "ag": 1,
    "hst": 8,
    "ast": 3,
    "hs": 12,
    "as": 14,
    "hc": 4,
    "ac": 5,
    "evt_id": "629404",
    "temp": 2022
  },
  {
    "fecha": "2022-04-01T20:30Z",
    "ht": "La Serena",
    "at": "Everton CD",
    "hg": 1,
    "ag": 3,
    "hst": 1,
    "ast": 7,
    "hs": 9,
    "as": 15,
    "hc": 2,
    "ac": 10,
    "evt_id": "629405",
    "temp": 2022
  },
  {
    "fecha": "2022-04-05T00:30Z",
    "ht": "Curicó Unido",
    "at": "Palestino",
    "hg": 0,
    "ag": 0,
    "hst": 3,
    "ast": 3,
    "hs": 16,
    "as": 7,
    "hc": 4,
    "ac": 2,
    "evt_id": "629406",
    "temp": 2022
  },
  {
    "fecha": "2022-04-02T21:00Z",
    "ht": "Universidad Católica",
    "at": "Universidad de Chile",
    "hg": 2,
    "ag": 1,
    "hst": 2,
    "ast": 3,
    "hs": 8,
    "as": 11,
    "hc": 5,
    "ac": 5,
    "evt_id": "629407",
    "temp": 2022
  },
  {
    "fecha": "2022-04-03T21:30Z",
    "ht": "Audax Italiano",
    "at": "Unión Española",
    "hg": 0,
    "ag": 1,
    "hst": 3,
    "ast": 4,
    "hs": 13,
    "as": 14,
    "hc": 7,
    "ac": 8,
    "evt_id": "629408",
    "temp": 2022
  },
  {
    "fecha": "2022-03-31T22:00Z",
    "ht": "Colo Colo",
    "at": "Unión La Calera",
    "hg": 4,
    "ag": 0,
    "hst": 7,
    "ast": 1,
    "hs": 15,
    "as": 7,
    "hc": 7,
    "ac": 4,
    "evt_id": "629409",
    "temp": 2022
  },
  {
    "fecha": "2022-03-20T23:30Z",
    "ht": "Everton CD",
    "at": "Audax Italiano",
    "hg": 0,
    "ag": 0,
    "hst": 2,
    "ast": 4,
    "hs": 10,
    "as": 14,
    "hc": 6,
    "ac": 5,
    "evt_id": "629410",
    "temp": 2022
  },
  {
    "fecha": "2022-03-20T20:30Z",
    "ht": "Palestino",
    "at": "Colo Colo",
    "hg": 0,
    "ag": 5,
    "hst": 2,
    "ast": 9,
    "hs": 6,
    "as": 13,
    "hc": 3,
    "ac": 4,
    "evt_id": "629411",
    "temp": 2022
  },
  {
    "fecha": "2022-03-19T23:30Z",
    "ht": "Cobresal",
    "at": "Coquimbo Unido",
    "hg": 2,
    "ag": 1,
    "hst": 8,
    "ast": 3,
    "hs": 20,
    "as": 9,
    "hc": 9,
    "ac": 3,
    "evt_id": "629412",
    "temp": 2022
  },
  {
    "fecha": "2022-03-17T23:30Z",
    "ht": "Universidad de Chile",
    "at": "Curicó Unido",
    "hg": 1,
    "ag": 1,
    "hst": 1,
    "ast": 6,
    "hs": 10,
    "as": 14,
    "hc": 6,
    "ac": 3,
    "evt_id": "629413",
    "temp": 2022
  },
  {
    "fecha": "2022-03-20T15:00Z",
    "ht": "Huachipato",
    "at": "La Serena",
    "hg": 2,
    "ag": 3,
    "hst": 5,
    "ast": 5,
    "hs": 14,
    "as": 13,
    "hc": 13,
    "ac": 4,
    "evt_id": "629414",
    "temp": 2022
  },
  {
    "fecha": "2022-03-19T21:00Z",
    "ht": "O'Higgins",
    "at": "Universidad Católica",
    "hg": 2,
    "ag": 1,
    "hst": 3,
    "ast": 1,
    "hs": 8,
    "as": 11,
    "hc": 2,
    "ac": 8,
    "evt_id": "629415",
    "temp": 2022
  },
  {
    "fecha": "2022-03-21T21:00Z",
    "ht": "Antofagasta",
    "at": "Unión La Calera",
    "hg": 0,
    "ag": 0,
    "hst": 3,
    "ast": 4,
    "hs": 19,
    "as": 16,
    "hc": 3,
    "ac": 5,
    "evt_id": "629416",
    "temp": 2022
  },
  {
    "fecha": "2022-03-21T23:30Z",
    "ht": "Unión Española",
    "at": "Ñublense",
    "hg": 1,
    "ag": 0,
    "hst": 7,
    "ast": 3,
    "hs": 12,
    "as": 11,
    "hc": 6,
    "ac": 3,
    "evt_id": "629417",
    "temp": 2022
  },
  {
    "fecha": "2022-03-11T21:00Z",
    "ht": "La Serena",
    "at": "Cobresal",
    "hg": 2,
    "ag": 3,
    "hst": 3,
    "ast": 9,
    "hs": 12,
    "as": 15,
    "hc": 1,
    "ac": 4,
    "evt_id": "629418",
    "temp": 2022
  },
  {
    "fecha": "2022-03-14T21:00Z",
    "ht": "Antofagasta",
    "at": "Colo Colo",
    "hg": 0,
    "ag": 1,
    "hst": 1,
    "ast": 4,
    "hs": 6,
    "as": 24,
    "hc": 3,
    "ac": 10,
    "evt_id": "629419",
    "temp": 2022
  },
  {
    "fecha": "2022-03-12T21:00Z",
    "ht": "Universidad Católica",
    "at": "Everton CD",
    "hg": 0,
    "ag": 1,
    "hst": 3,
    "ast": 2,
    "hs": 13,
    "as": 9,
    "hc": 3,
    "ac": 4,
    "evt_id": "629420",
    "temp": 2022
  },
  {
    "fecha": "2022-03-13T21:00Z",
    "ht": "Curicó Unido",
    "at": "O'Higgins",
    "hg": 5,
    "ag": 0,
    "hst": 8,
    "ast": 4,
    "hs": 9,
    "as": 9,
    "hc": 2,
    "ac": 6,
    "evt_id": "629421",
    "temp": 2022
  },
  {
    "fecha": "2022-03-13T23:30Z",
    "ht": "Audax Italiano",
    "at": "Palestino",
    "hg": 3,
    "ag": 1,
    "hst": 4,
    "ast": 2,
    "hs": 12,
    "as": 9,
    "hc": 4,
    "ac": 4,
    "evt_id": "629422",
    "temp": 2022
  },
  {
    "fecha": "2022-03-12T23:30Z",
    "ht": "Unión La Calera",
    "at": "Huachipato",
    "hg": 1,
    "ag": 0,
    "hst": 6,
    "ast": 4,
    "hs": 16,
    "as": 12,
    "hc": 3,
    "ac": 5,
    "evt_id": "629423",
    "temp": 2022
  },
  {
    "fecha": "2022-03-27T19:00Z",
    "ht": "Universidad de Chile",
    "at": "Unión Española",
    "hg": 2,
    "ag": 0,
    "hst": 7,
    "ast": 7,
    "hs": 12,
    "as": 23,
    "hc": 2,
    "ac": 14,
    "evt_id": "629424",
    "temp": 2022
  },
  {
    "fecha": "2022-03-12T15:00Z",
    "ht": "Coquimbo Unido",
    "at": "Ñublense",
    "hg": 0,
    "ag": 1,
    "hst": 4,
    "ast": 3,
    "hs": 14,
    "as": 11,
    "hc": 6,
    "ac": 2,
    "evt_id": "629425",
    "temp": 2022
  },
  {
    "fecha": "2022-03-05T15:00Z",
    "ht": "Coquimbo Unido",
    "at": "Antofagasta",
    "hg": 3,
    "ag": 2,
    "hst": 5,
    "ast": 4,
    "hs": 13,
    "as": 12,
    "hc": 3,
    "ac": 6,
    "evt_id": "629426",
    "temp": 2022
  },
  {
    "fecha": "2022-03-06T21:00Z",
    "ht": "O'Higgins",
    "at": "Audax Italiano",
    "hg": 2,
    "ag": 2,
    "hst": 3,
    "ast": 4,
    "hs": 7,
    "as": 8,
    "hc": 10,
    "ac": 3,
    "evt_id": "629427",
    "temp": 2022
  },
  {
    "fecha": "2022-03-05T23:30Z",
    "ht": "Everton CD",
    "at": "Curicó Unido",
    "hg": 1,
    "ag": 1,
    "hst": 5,
    "ast": 2,
    "hs": 18,
    "as": 11,
    "hc": 7,
    "ac": 4,
    "evt_id": "629428",
    "temp": 2022
  },
  {
    "fecha": "2022-03-04T23:30Z",
    "ht": "Ñublense",
    "at": "La Serena",
    "hg": 3,
    "ag": 1,
    "hst": 5,
    "ast": 5,
    "hs": 10,
    "as": 17,
    "hc": 2,
    "ac": 9,
    "evt_id": "629429",
    "temp": 2022
  },
  {
    "fecha": "2022-03-05T21:00Z",
    "ht": "Unión Española",
    "at": "Huachipato",
    "hg": 1,
    "ag": 0,
    "hst": 2,
    "ast": 4,
    "hs": 18,
    "as": 13,
    "hc": 6,
    "ac": 5,
    "evt_id": "629430",
    "temp": 2022
  },
  {
    "fecha": "2022-03-06T23:30Z",
    "ht": "Cobresal",
    "at": "Universidad Católica",
    "hg": 3,
    "ag": 1,
    "hst": 6,
    "ast": 3,
    "hs": 12,
    "as": 17,
    "hc": 4,
    "ac": 3,
    "evt_id": "629431",
    "temp": 2022
  },
  {
    "fecha": "2022-03-06T15:00Z",
    "ht": "Colo Colo",
    "at": "Universidad de Chile",
    "hg": 4,
    "ag": 1,
    "hst": 8,
    "ast": 6,
    "hs": 19,
    "as": 15,
    "hc": 6,
    "ac": 5,
    "evt_id": "629432",
    "temp": 2022
  },
  {
    "fecha": "2022-03-04T21:00Z",
    "ht": "Palestino",
    "at": "Unión La Calera",
    "hg": 0,
    "ag": 0,
    "hst": 0,
    "ast": 2,
    "hs": 8,
    "as": 8,
    "hc": 5,
    "ac": 1,
    "evt_id": "629433",
    "temp": 2022
  },
  {
    "fecha": "2022-02-26T23:30Z",
    "ht": "Audax Italiano",
    "at": "Antofagasta",
    "hg": 0,
    "ag": 3,
    "hst": 4,
    "ast": 3,
    "hs": 12,
    "as": 9,
    "hc": 2,
    "ac": 1,
    "evt_id": "629434",
    "temp": 2022
  },
  {
    "fecha": "2022-02-27T15:00Z",
    "ht": "Huachipato",
    "at": "Colo Colo",
    "hg": 1,
    "ag": 0,
    "hst": 4,
    "ast": 5,
    "hs": 8,
    "as": 15,
    "hc": 2,
    "ac": 5,
    "evt_id": "629435",
    "temp": 2022
  },
  {
    "fecha": "2022-02-26T15:00Z",
    "ht": "La Serena",
    "at": "Coquimbo Unido",
    "hg": 1,
    "ag": 1,
    "hst": 3,
    "ast": 5,
    "hs": 6,
    "as": 14,
    "hc": 3,
    "ac": 8,
    "evt_id": "629436",
    "temp": 2022
  },
  {
    "fecha": "2022-02-25T23:00Z",
    "ht": "Unión La Calera",
    "at": "Everton CD",
    "hg": 1,
    "ag": 1,
    "hst": 4,
    "ast": 1,
    "hs": 10,
    "as": 5,
    "hc": 4,
    "ac": 1,
    "evt_id": "629437",
    "temp": 2022
  },
  {
    "fecha": "2022-02-28T23:30Z",
    "ht": "Universidad de Chile",
    "at": "O'Higgins",
    "hg": 0,
    "ag": 1,
    "hst": 3,
    "ast": 3,
    "hs": 13,
    "as": 10,
    "hc": 6,
    "ac": 3,
    "evt_id": "629438",
    "temp": 2022
  },
  {
    "fecha": "2022-02-27T21:00Z",
    "ht": "Palestino",
    "at": "Universidad Católica",
    "hg": 3,
    "ag": 2,
    "hst": 7,
    "ast": 4,
    "hs": 18,
    "as": 15,
    "hc": 8,
    "ac": 0,
    "evt_id": "629439",
    "temp": 2022
  },
  {
    "fecha": "2022-02-28T21:00Z",
    "ht": "Curicó Unido",
    "at": "Unión Española",
    "hg": 0,
    "ag": 1,
    "hst": 5,
    "ast": 2,
    "hs": 13,
    "as": 16,
    "hc": 3,
    "ac": 5,
    "evt_id": "629440",
    "temp": 2022
  },
  {
    "fecha": "2022-02-26T21:00Z",
    "ht": "Cobresal",
    "at": "Ñublense",
    "hg": 1,
    "ag": 1,
    "hst": 8,
    "ast": 2,
    "hs": 20,
    "as": 12,
    "hc": 9,
    "ac": 1,
    "evt_id": "629441",
    "temp": 2022
  },
  {
    "fecha": "2022-02-19T21:00Z",
    "ht": "Colo Colo",
    "at": "Audax Italiano",
    "hg": 1,
    "ag": 1,
    "hst": 6,
    "ast": 1,
    "hs": 13,
    "as": 5,
    "hc": 8,
    "ac": 1,
    "evt_id": "629442",
    "temp": 2022
  },
  {
    "fecha": "2022-02-20T21:00Z",
    "ht": "Unión La Calera",
    "at": "Cobresal",
    "hg": 0,
    "ag": 2,
    "hst": 3,
    "ast": 3,
    "hs": 11,
    "as": 10,
    "hc": 2,
    "ac": 3,
    "evt_id": "629443",
    "temp": 2022
  },
  {
    "fecha": "2022-02-20T23:30Z",
    "ht": "Universidad Católica",
    "at": "Curicó Unido",
    "hg": 1,
    "ag": 0,
    "hst": 5,
    "ast": 2,
    "hs": 23,
    "as": 9,
    "hc": 8,
    "ac": 5,
    "evt_id": "629444",
    "temp": 2022
  },
  {
    "fecha": "2022-02-18T23:30Z",
    "ht": "Unión Española",
    "at": "Everton CD",
    "hg": 1,
    "ag": 1,
    "hst": 5,
    "ast": 1,
    "hs": 21,
    "as": 6,
    "hc": 11,
    "ac": 7,
    "evt_id": "629445",
    "temp": 2022
  },
  {
    "fecha": "2022-02-19T23:30Z",
    "ht": "Antofagasta",
    "at": "La Serena",
    "hg": 2,
    "ag": 2,
    "hst": 3,
    "ast": 2,
    "hs": 12,
    "as": 8,
    "hc": 6,
    "ac": 4,
    "evt_id": "629446",
    "temp": 2022
  },
  {
    "fecha": "2022-02-20T15:00Z",
    "ht": "Coquimbo Unido",
    "at": "Palestino",
    "hg": 2,
    "ag": 2,
    "hst": 6,
    "ast": 5,
    "hs": 13,
    "as": 13,
    "hc": 7,
    "ac": 6,
    "evt_id": "629447",
    "temp": 2022
  },
  {
    "fecha": "2022-02-18T21:00Z",
    "ht": "O'Higgins",
    "at": "Huachipato",
    "hg": 1,
    "ag": 1,
    "hst": 4,
    "ast": 2,
    "hs": 13,
    "as": 8,
    "hc": 3,
    "ac": 3,
    "evt_id": "629448",
    "temp": 2022
  },
  {
    "fecha": "2022-02-21T21:00Z",
    "ht": "Ñublense",
    "at": "Universidad de Chile",
    "hg": 3,
    "ag": 2,
    "hst": 10,
    "ast": 5,
    "hs": 20,
    "as": 11,
    "hc": 3,
    "ac": 4,
    "evt_id": "629449",
    "temp": 2022
  },
  {
    "fecha": "2022-02-12T23:30Z",
    "ht": "Universidad de Chile",
    "at": "Antofagasta",
    "hg": 2,
    "ag": 1,
    "hst": 4,
    "ast": 6,
    "hs": 6,
    "as": 18,
    "hc": 0,
    "ac": 6,
    "evt_id": "629450",
    "temp": 2022
  },
  {
    "fecha": "2022-02-12T21:00Z",
    "ht": "Huachipato",
    "at": "Audax Italiano",
    "hg": 2,
    "ag": 1,
    "hst": 2,
    "ast": 4,
    "hs": 8,
    "as": 17,
    "hc": 3,
    "ac": 7,
    "evt_id": "629451",
    "temp": 2022
  },
  {
    "fecha": "2022-02-13T21:00Z",
    "ht": "La Serena",
    "at": "Colo Colo",
    "hg": 1,
    "ag": 1,
    "hst": 4,
    "ast": 6,
    "hs": 10,
    "as": 18,
    "hc": 3,
    "ac": 5,
    "evt_id": "629452",
    "temp": 2022
  },
  {
    "fecha": "2022-02-11T23:30Z",
    "ht": "Everton CD",
    "at": "Coquimbo Unido",
    "hg": 2,
    "ag": 0,
    "hst": 9,
    "ast": 6,
    "hs": 22,
    "as": 17,
    "hc": 6,
    "ac": 7,
    "evt_id": "629453",
    "temp": 2022
  },
  {
    "fecha": "2022-02-14T23:30Z",
    "ht": "Cobresal",
    "at": "Curicó Unido",
    "hg": 2,
    "ag": 3,
    "hst": 6,
    "ast": 4,
    "hs": 22,
    "as": 13,
    "hc": 2,
    "ac": 3,
    "evt_id": "629454",
    "temp": 2022
  },
  {
    "fecha": "2022-02-11T21:00Z",
    "ht": "Palestino",
    "at": "O'Higgins",
    "hg": 1,
    "ag": 0,
    "hst": 5,
    "ast": 3,
    "hs": 14,
    "as": 7,
    "hc": 8,
    "ac": 3,
    "evt_id": "629455",
    "temp": 2022
  },
  {
    "fecha": "2022-02-13T23:30Z",
    "ht": "Universidad Católica",
    "at": "Unión Española",
    "hg": 2,
    "ag": 1,
    "hst": 5,
    "ast": 3,
    "hs": 15,
    "as": 12,
    "hc": 10,
    "ac": 6,
    "evt_id": "629456",
    "temp": 2022
  },
  {
    "fecha": "2022-02-14T21:00Z",
    "ht": "Ñublense",
    "at": "Unión La Calera",
    "hg": 0,
    "ag": 0,
    "hst": 5,
    "ast": 1,
    "hs": 19,
    "as": 10,
    "hc": 8,
    "ac": 2,
    "evt_id": "629457",
    "temp": 2022
  },
  {
    "fecha": "2022-02-06T15:00Z",
    "ht": "Antofagasta",
    "at": "Cobresal",
    "hg": 0,
    "ag": 1,
    "hst": 1,
    "ast": 5,
    "hs": 9,
    "as": 13,
    "hc": 7,
    "ac": 5,
    "evt_id": "629458",
    "temp": 2022
  },
  {
    "fecha": "2022-02-06T23:30Z",
    "ht": "Colo Colo",
    "at": "Everton CD",
    "hg": 2,
    "ag": 0,
    "hst": 4,
    "ast": 0,
    "hs": 20,
    "as": 5,
    "hc": 12,
    "ac": 1,
    "evt_id": "629459",
    "temp": 2022
  },
  {
    "fecha": "2022-02-04T23:00Z",
    "ht": "O'Higgins",
    "at": "La Serena",
    "hg": 3,
    "ag": 0,
    "hst": 5,
    "ast": 0,
    "hs": 12,
    "as": 13,
    "hc": 2,
    "ac": 8,
    "evt_id": "629460",
    "temp": 2022
  },
  {
    "fecha": "2022-02-05T21:00Z",
    "ht": "Unión Española",
    "at": "Palestino",
    "hg": 1,
    "ag": 1,
    "hst": 4,
    "ast": 2,
    "hs": 13,
    "as": 12,
    "hc": 5,
    "ac": 5,
    "evt_id": "629461",
    "temp": 2022
  },
  {
    "fecha": "2022-02-07T23:30Z",
    "ht": "Curicó Unido",
    "at": "Huachipato",
    "hg": 4,
    "ag": 0,
    "hst": 11,
    "ast": 6,
    "hs": 18,
    "as": 14,
    "hc": 4,
    "ac": 4,
    "evt_id": "629462",
    "temp": 2022
  },
  {
    "fecha": "2022-02-05T23:30Z",
    "ht": "Coquimbo Unido",
    "at": "Universidad Católica",
    "hg": 2,
    "ag": 3,
    "hst": 3,
    "ast": 7,
    "hs": 8,
    "as": 17,
    "hc": 4,
    "ac": 3,
    "evt_id": "629463",
    "temp": 2022
  },
  {
    "fecha": "2022-02-06T21:00Z",
    "ht": "Unión La Calera",
    "at": "Universidad de Chile",
    "hg": 2,
    "ag": 4,
    "hst": 7,
    "ast": 7,
    "hs": 19,
    "as": 10,
    "hc": 7,
    "ac": 3,
    "evt_id": "629464",
    "temp": 2022
  },
  {
    "fecha": "2022-02-07T21:00Z",
    "ht": "Audax Italiano",
    "at": "Ñublense",
    "hg": 1,
    "ag": 2,
    "hst": 3,
    "ast": 5,
    "hs": 10,
    "as": 13,
    "hc": 6,
    "ac": 2,
    "evt_id": "629465",
    "temp": 2022
  }
]