{
  "vista_total_unitario": {
    "Q1": {
      "fecha_lo": "2026-03-16",
      "fecha_hi": "2026-03-26",
      "n": 39,
      "n_gano": 28,
      "hit_pct": 71.7948717948718,
      "yield_pct": 79.64102564102564,
      "ci95_lo": 36.564102564102555,
      "ci95_hi": 121.9596153846153,
      "brier_avg": 0.5941425312075781,
      "n_brier": 39
    },
    "Q2": {
      "fecha_lo": "2026-03-26",
      "fecha_hi": "2026-04-05",
      "n": 38,
      "n_gano": 26,
      "hit_pct": 68.42105263157895,
      "yield_pct": 126.81578947368422,
      "ci95_lo": 66.9467105263158,
      "ci95_hi": 189.60789473684207,
      "brier_avg": 0.5634064259235008,
      "n_brier": 38
    },
    "Q3": {
      "fecha_lo": "2026-04-05",
      "fecha_hi": "2026-04-15",
      "n": 59,
      "n_gano": 34,
      "hit_pct": 57.6271186440678,
      "yield_pct": 29.33898305084746,
      "ci95_lo": -2.528389830508471,
      "ci95_hi": 62.022881355932164,
      "brier_avg": 0.5937752705748294,
      "n_brier": 59
    },
    "Q4": {
      "fecha_lo": "2026-04-15",
      "fecha_hi": "2026-04-26",
      "n": 222,
      "n_gano": 127,
      "hit_pct": 57.20720720720721,
      "yield_pct": 13.364864864864876,
      "ci95_lo": -1.1246621621621635,
      "ci95_hi": 27.99245495495495,
      "brier_avg": 0.5992589340427489,
      "n_brier": 222
    }
  },
  "vista_stake_real": {
    "Q1": {
      "fecha_lo": "2026-03-16",
      "fecha_hi": "2026-03-26",
      "n": 26,
      "n_gano": 17,
      "hit_pct": 65.38461538461539,
      "yield_pct": 105.3338747616277,
      "sum_stake": 239022.11000000002,
      "sum_pl": 251771.25,
      "ci95_lo": 44.11388123941205,
      "ci95_hi": 167.51302397311463,
      "brier_avg": 0.627187030951654,
      "n_brier": 26
    },
    "Q2": {
      "fecha_lo": "2026-03-26",
      "fecha_hi": "2026-04-05",
      "n": 31,
      "n_gano": 20,
      "hit_pct": 64.51612903225806,
      "yield_pct": 143.23233364513203,
      "sum_stake": 715707.49,
      "sum_pl": 1025124.5399999999,
      "ci95_lo": 65.8530176277035,
      "ci95_hi": 221.64920692261884,
      "brier_avg": 0.5809980728180784,
      "n_brier": 31
    },
    "Q3": {
      "fecha_lo": "2026-04-05",
      "fecha_hi": "2026-04-15",
      "n": 36,
      "n_gano": 18,
      "hit_pct": 50.0,
      "yield_pct": 37.34597343266975,
      "sum_stake": 1589679.49,
      "sum_pl": 593681.28,
      "ci95_lo": -17.042146740805787,
      "ci95_hi": 92.92066914307462,
      "brier_avg": 0.6223613994100249,
      "n_brier": 36
    },
    "Q4": {
      "fecha_lo": "2026-04-15",
      "fecha_hi": "2026-04-26",
      "n": 135,
      "n_gano": 62,
      "hit_pct": 45.925925925925924,
      "yield_pct": 4.686302540494661,
      "sum_stake": 11048338.12,
      "sum_pl": 517758.55000000005,
      "ci95_lo": -15.563210804687401,
      "ci95_hi": 26.571877057162,
      "brier_avg": 0.633619408658022,
      "n_brier": 135
    }
  },
  "global_stake_real": {
    "n": 228,
    "n_gano": 117,
    "hit_pct": 51.31578947368421,
    "yield_pct": 17.570661641106174,
    "sum_stake": 13592747.21,
    "sum_pl": 2388335.62,
    "brier_avg": 0.6239536561828829,
    "n_brier": 228,
    "yield_mean": 17.620139911595704,
    "ci95_lo": -1.7837603400468205,
    "ci95_hi": 38.56549777403889
  },
  "por_camino": {
    "C1": {
      "n": 104,
      "hit_pct": 48.07692307692308,
      "yield_pct": 29.50961538461539,
      "ci95_lo": 4.332932692307692,
      "ci95_hi": 55.358653846153835
    },
    "C2": {
      "n": 29,
      "hit_pct": 37.93103448275862,
      "yield_pct": 40.96551724137932,
      "ci95_lo": -22.553448275862067,
      "ci95_hi": 109.00172413793103
    },
    "C2B": {
      "n": 37,
      "hit_pct": 40.54054054054054,
      "yield_pct": 65.94594594594594,
      "ci95_lo": 0.6290540540540546,
      "ci95_hi": 134.84527027027022
    },
    "C3": {
      "n": 5,
      "hit_pct": 80.0,
      "yield_pct": 376.19999999999993,
      "ci95_lo": 133.20000000000002,
      "ci95_hi": 520.4
    },
    "C4": {
      "n": 135,
      "hit_pct": 75.55555555555556,
      "yield_pct": 20.67407407407407,
      "ci95_lo": 9.184629629629628,
      "ci95_hi": 32.32888888888887
    },
    "OU": {
      "n": 48,
      "hit_pct": 68.75,
      "yield_pct": 26.124999999999993,
      "ci95_lo": 1.4749999999999992,
      "ci95_hi": 50.6046875
    }
  },
  "por_liga": {
    "Brasil": {
      "n": 58,
      "hit_pct": 56.896551724137936,
      "yield_pct": 55.56896551724139,
      "ci95_lo": 13.046120689655167,
      "ci95_hi": 102.6935344827586
    },
    "Argentina": {
      "n": 55,
      "hit_pct": 67.27272727272727,
      "yield_pct": 72.70909090909093,
      "ci95_lo": 32.05363636363636,
      "ci95_hi": 113.81863636363639
    },
    "Turquia": {
      "n": 47,
      "hit_pct": 65.95744680851064,
      "yield_pct": 42.06382978723404,
      "ci95_lo": 9.219148936170214,
      "ci95_hi": 75.91542553191489
    },
    "Inglaterra": {
      "n": 34,
      "hit_pct": 67.64705882352942,
      "yield_pct": 42.941176470588246,
      "ci95_lo": 3.105882352941177,
      "ci95_hi": 82.825
    },
    "Noruega": {
      "n": 29,
      "hit_pct": 68.96551724137932,
      "yield_pct": 65.10344827586206,
      "ci95_lo": 17.718103448275862,
      "ci95_hi": 116.62241379310342
    },
    "Bolivia": {
      "n": 21,
      "hit_pct": 61.904761904761905,
      "yield_pct": -4.4285714285714315,
      "ci95_lo": -37.52857142857143,
      "ci95_hi": 27.720238095238063
    },
    "Espana": {
      "n": 20,
      "hit_pct": 45.0,
      "yield_pct": -13.750000000000004,
      "ci95_lo": -57.705,
      "ci95_hi": 29.401249999999983
    },
    "Chile": {
      "n": 19,
      "hit_pct": 47.368421052631575,
      "yield_pct": 2.368421052631573,
      "ci95_lo": -50.1078947368421,
      "ci95_hi": 52.31842105263156
    }
  },
  "n_bins": 4,
  "liga_x_bin": {
    "Brasil": {
      "Q1": {
        "n": 9,
        "hit_pct": 44.44444444444444,
        "yield_pct": 6.88888888888889,
        "brier_avg": 0.6428320684754445
      },
      "Q2": {
        "n": 20,
        "hit_pct": 70.0,
        "yield_pct": 158.70000000000002,
        "brier_avg": 0.5803607112064803
      },
      "Q3": {
        "n": 9,
        "hit_pct": 33.33333333333333,
        "yield_pct": -26.666666666666668,
        "brier_avg": 0.7149973417305556
      },
      "Q4": {
        "n": 20,
        "hit_pct": 60.0,
        "yield_pct": 11.35,
        "brier_avg": 0.5735718340041867
      }
    },
    "Argentina": {
      "Q1": {
        "n": 15,
        "hit_pct": 93.33333333333333,
        "yield_pct": 131.26666666666665,
        "brier_avg": 0.5261814757423031
      },
      "Q2": {
        "n": 10,
        "hit_pct": 60.0,
        "yield_pct": 86.39999999999999,
        "brier_avg": 0.5650106667542427
      },
      "Q3": {
        "n": 9,
        "hit_pct": 77.77777777777779,
        "yield_pct": 87.00000000000001,
        "brier_avg": 0.49200081911899995
      },
      "Q4": {
        "n": 21,
        "hit_pct": 47.61904761904761,
        "yield_pct": 18.23809523809523,
        "brier_avg": 0.6320116615125694
      }
    },
    "Turquia": {
      "Q1": {
        "n": 4,
        "hit_pct": 75.0,
        "yield_pct": 55.50000000000001,
        "brier_avg": 0.5221415253385
      },
      "Q2": {
        "n": 8,
        "hit_pct": 75.0,
        "yield_pct": 97.62499999999999,
        "brier_avg": 0.519015411677625
      },
      "Q3": {
        "n": 18,
        "hit_pct": 66.66666666666666,
        "yield_pct": 33.22222222222222,
        "brier_avg": 0.5813773036554408
      },
      "Q4": {
        "n": 17,
        "hit_pct": 58.82352941176471,
        "yield_pct": 22.11764705882353,
        "brier_avg": 0.5463389085407647
      }
    },
    "Inglaterra": {
      "Q1": {
        "n": 7,
        "hit_pct": 57.14285714285714,
        "yield_pct": 69.28571428571428,
        "brier_avg": 0.7203602088097142
      },
      "Q3": {
        "n": 8,
        "hit_pct": 37.5,
        "yield_pct": -29.375,
        "brier_avg": 0.60424358319375
      },
      "Q4": {
        "n": 19,
        "hit_pct": 84.21052631578947,
        "yield_pct": 63.68421052631579,
        "brier_avg": 0.5520866976492631
      }
    },
    "Noruega": {
      "Q1": {
        "n": 4,
        "hit_pct": 75.0,
        "yield_pct": 92.0,
        "brier_avg": 0.590565100415
      },
      "Q3": {
        "n": 14,
        "hit_pct": 64.28571428571429,
        "yield_pct": 66.07142857142857,
        "brier_avg": 0.5990944252614285
      },
      "Q4": {
        "n": 11,
        "hit_pct": 72.72727272727273,
        "yield_pct": 54.090909090909086,
        "brier_avg": 0.5583327517119078
      }
    },
    "Bolivia": {
      "Q4": {
        "n": 21,
        "hit_pct": 61.904761904761905,
        "yield_pct": -4.4285714285714315,
        "brier_avg": 0.5842524519035688
      }
    },
    "Espana": {
      "Q4": {
        "n": 20,
        "hit_pct": 45.0,
        "yield_pct": -13.750000000000004,
        "brier_avg": 0.6052378188212291
      }
    },
    "Chile": {
      "Q3": {
        "n": 1,
        "hit_pct": 0.0,
        "yield_pct": -100.0,
        "brier_avg": 0.48369543126100006
      },
      "Q4": {
        "n": 18,
        "hit_pct": 50.0,
        "yield_pct": 8.05555555555555,
        "brier_avg": 0.6319373450306872
      }
    }
  },
  "tendencia": {
    "yield_total_unitario": [
      79.64102564102564,
      126.81578947368422,
      29.33898305084746,
      13.364864864864876
    ],
    "hit_total_unitario": [
      71.7948717948718,
      68.42105263157895,
      57.6271186440678,
      57.20720720720721
    ],
    "n_bins": 4
  }
}